[
  {
    "dateString": "20150901",
    "date": 1441065600000,
    "attribute": "鳞次栉比的黄色校车",
    "title": "黄色校车",
    "story": [
      {
        "title": "各国校车",
        "au": "安全是不变的宗旨",
        "describe": "马路上最有“特权”的车辆是什么？不是警车，不是救护车，也不是名流政要的专车，而是那些颜色醒目的黄色校车！它不仅最有“特权”，也是公路上最安全的交通工具。",
        "miniImage": "http://s3.cn.bing.net/th?id=OJ.00aTjUrERda0fw&pid=MSNJVFeeds",
        "miniUrl": "https://zhanghao-zhoushan.cn/image/story/s3.OJ.00aTjUrERda0fw.png"
      },
      {
        "title": "黄色校车之父",
        "au": "希尔博士",
        "describe": "上世纪50年代的美国就已经有校车了，但都自行制定车型规范，使用的校车五花八门，也存在着很大的安全隐患。于是教育专家希尔博士开始对各州的校车都做了研究，并制定出沿用至今的校车设计规范，因此被称为“黄色校车之父”。",
        "miniImage": "http://s4.cn.bing.net/th?id=OJ.d090UqO303xgRg&pid=MSNJVFeeds",
        "miniUrl": "https://zhanghao-zhoushan.cn/image/story/s4.OJ.d090UqO303xgRg.png"
      },
      {
        "title": "安全永远第一",
        "au": "校车设计规范",
        "describe": "刹车装置比一般车辆更好；加强型的钢结构系统能在翻车事故中保护学生；配备有在紧急出口开启时防止发动机启动的锁止系统；车厢内有精心设计的填充结构来保护学生……设计的宗旨就是从方方面面都考虑到学生的安全，避免发生事故。",
        "miniImage": "http://s1.cn.bing.net/th?id=OJ.sT5QnHpFwUiVjw&pid=MSNJVFeeds",
        "miniUrl": "https://zhanghao-zhoushan.cn/image/story/s1.OJ.sT5QnHpFwUiVjw.png"
      }
    ],
    "primaryImageUrl": "http://hpimges.blob.core.chinacloudapi.cn/coverstory/watermark_schoolbuslot_zh-cn10293629077_1920x1080.jpg",
    "imageUrl": "https://zhanghao-zhoushan.cn/image/large/StrokkurGeyserVideo_ZH-CN13059478273_1366x768.jpg",
    "downLoadUrl": "https://zhanghao-zhoushan.cn/image/large/StrokkurGeyserVideo_ZH-CN13059478273.jpg",
    "url": "http://cdn.nanxiongnandi.com/bing/StrokkurGeyserVideo_ZH-CN13059478273_1366x768.jpg",
    "name": "StrokkurGeyserVideo_ZH-CN13059478273.jpg",
    "provider": "© Space Images/Blend Images/Getty Images",
    "copyright": "冰岛，东雷克雅未克，赫维塔河热地附近的史托克间歇泉 (© Zinaida Sopina/Shutterstock)(Bing China)",
    "Continent": "",
    "Country": "",
    "City": "",
    "Longitude": "",
    "Latitude": ""
  },
  {
    "dateString": "20150902",
    "date": 1441152000000,
    "attribute": "冰岛，赫维塔河热地",
    "title": "雷克雅未克",
    "story": [
      {
        "title": "自然风光",
        "au": "奇幻美丽",
        "describe": "这座城市接近北极圈，你会被那迷幻的极光、冰川、火山、温泉美景所迷住。城市里街道不宽，住宅小巧精致，整座城给人以古色古香、整洁干净之感。",
        "miniImage": "http://s.cn.bing.net/th?id=OJ.FTe9Q5M2V0JLtg&pid=MSNJVFeeds",
        "miniUrl": "https://zhanghao-zhoushan.cn/image/story/s.OJ.FTe9Q5M2V0JLtg.png"
      },
      {
        "title": "五彩的极光",
        "au": "欧若拉",
        "describe": "在北欧，人们将极光称作“欧若拉”，每年的9月至来年3月都是看极光的好时节。在远离城镇的晴朗夜空下，绿色的光芒划破黑暗夜空，天空变成了这些彩光的舞台，任由它们在此尽情舞动。",
        "miniImage": "http://s1.cn.bing.net/th?id=OJ.WrFk5X3DGBqfGQ&pid=MSNJVFeeds",
        "miniUrl": "https://zhanghao-zhoushan.cn/image/story/s1.OJ.WrFk5X3DGBqfGQ.png"
      },
      {
        "title": "没有污染的健康美味",
        "au": "冰岛美食",
        "describe": "冰岛以肉为主食，当地人喜爱鱼和羊肉。政府禁止农夫们使用化学饲料和增长素，并且采用传统的放养方式来饲养牛羊，它们只吃青草等植物，因此肉质健康、鲜美，一定不要错过。",
        "miniImage": "http://s1.cn.bing.net/th?id=OJ.nHBKK6QxCi5q0A&pid=MSNJVFeeds",
        "miniUrl": "https://zhanghao-zhoushan.cn/image/story/s1.OJ.nHBKK6QxCi5q0A.png"
      }
    ],
    "primaryImageUrl": "http://hpimges.blob.core.chinacloudapi.cn/coverstory/watermark_strokkurgeyservideo_zh-cn13059478273_1920x1080.jpg",
    "imageUrl": "https://zhanghao-zhoushan.cn/image/large/CanadianSnails_ZH-CN13917940387_1366x768.jpg",
    "downLoadUrl": "https://zhanghao-zhoushan.cn/image/large/CanadianSnails_ZH-CN13917940387.jpg",
    "url": "http://cdn.nanxiongnandi.com/bing/CanadianSnails_ZH-CN13917940387_1366x768.jpg",
    "name": "CanadianSnails_ZH-CN13917940387.jpg",
    "provider": "© Zinaida Sopina/Shutterstock",
    "copyright": "蘑菇上的蜗牛 (© Marianna Armata/Getty Images)(Bing China)",
    "Continent": "",
    "Country": "冰岛",
    "City": "赫维塔河热地",
    "Longitude": "52.334457",
    "Latitude": "124.709996"
  },
  {
    "dateString": "20150903",
    "date": 1441238400000,
    "attribute": "蘑菇上的蜗牛",
    "title": "它不可爱吗？",
    "story": [
      {
        "title": "小蜗牛的大世界",
        "au": "种类繁多的动物",
        "describe": "娇小柔软的身体上扛着它的家，再苦再累也不停下向前的脚步，一点一点向上爬，到达终点前永不言弃。这就是蜗牛，不起眼的小身体里，却有着令人钦佩的意志力。",
        "miniImage": "http://s.cn.bing.net/th?id=OJ.jJk7LP7CKOmMcQ&pid=MSNJVFeeds",
        "miniUrl": "https://zhanghao-zhoushan.cn/image/story/s.OJ.jJk7LP7CKOmMcQ.png"
      },
      {
        "title": "法国名菜",
        "au": "蜗牛料理",
        "describe": "法国人早在几百年前就开始食用蜗牛，厨师们比较青睐勃艮第蜗牛和“小灰”这两种。前一种个大，适合用来烹饪大餐，后一种则适合炖来吃。",
        "miniImage": "http://s.cn.bing.net/th?id=OJ.QYuSd8gQXjjKLA&pid=MSNJVFeeds",
        "miniUrl": "https://zhanghao-zhoushan.cn/image/story/s.OJ.QYuSd8gQXjjKLA.png"
      },
      {
        "title": "清热解毒 美容养颜",
        "au": "药用价值",
        "describe": "蜗牛蛋白质含量高，性寒，有清热解毒的功效，入药后还可用来治疗小便不利等症状。此外，蜗牛分泌的黏液有美容的作用，可以保湿、愈合伤口、促进肌肤再生。",
        "miniImage": "http://s2.cn.bing.net/th?id=OJ.h0q8uRHiTAw05Q&pid=MSNJVFeeds",
        "miniUrl": "https://zhanghao-zhoushan.cn/image/story/s2.OJ.h0q8uRHiTAw05Q.png"
      }
    ],
    "primaryImageUrl": "http://hpimges.blob.core.chinacloudapi.cn/coverstory/watermark_canadiansnails_zh-cn13917940387_1920x1080.jpg",
    "imageUrl": "https://zhanghao-zhoushan.cn/image/large/FloreanaIslandSeaLion_ZH-CN12024860324_1366x768.jpg",
    "downLoadUrl": "https://zhanghao-zhoushan.cn/image/large/FloreanaIslandSeaLion_ZH-CN12024860324.jpg",
    "url": "http://cdn.nanxiongnandi.com/bing/FloreanaIslandSeaLion_ZH-CN12024860324_1366x768.jpg",
    "name": "FloreanaIslandSeaLion_ZH-CN12024860324.jpg",
    "provider": "© Marianna Armata/Getty Images",
    "copyright": "厄瓜多尔，加拉帕戈斯群岛，佛罗雷阿纳岛的冠军小岛，加拉帕戈海狮妈妈亲吻着小海狮 (© Tui De Roy/Minden Pictures)(Bing China)",
    "Continent": "",
    "Country": "",
    "City": "",
    "Longitude": "",
    "Latitude": ""
  },
  {
    "dateString": "20150904",
    "date": 1441324800000,
    "attribute": "厄瓜多尔，加拉帕戈斯群岛",
    "title": "加拉帕戈斯群岛",
    "story": [
      {
        "title": "海岛假期",
        "au": "享受纯粹慢生活",
        "describe": "五百万年前，海底火山喷发，熔岩终于在一百万年前浮出水面，形成如今这座美丽富饶的加拉帕戈斯群岛。岛上植被茂密，动物遍布，一座座可爱的小岛等着你去探索。",
        "miniImage": "http://s4.cn.bing.net/th?id=OJ.9IZFoU494KMdpA&pid=MSNJVFeeds",
        "miniUrl": "https://zhanghao-zhoushan.cn/image/story/s4.OJ.9IZFoU494KMdpA.png"
      },
      {
        "title": "终极潜水体验",
        "au": "潜水胜地",
        "describe": "这里有专门的潜水线路，吃住都在船上，大约一周的时间，每天潜两次。海水温度适中，能见度高，海里还有各种动物陪你一同畅泳，有海龟、海狮陪伴的潜水体验，是不是更有趣呢？",
        "miniImage": "http://s.cn.bing.net/th?id=OJ.AC1Qi8Aqjtdhpg&pid=MSNJVFeeds",
        "miniUrl": "https://zhanghao-zhoushan.cn/image/story/s.OJ.AC1Qi8Aqjtdhpg.png"
      },
      {
        "title": "岛上最具代表性的动物",
        "au": "象龟",
        "describe": "象龟遍布整个群岛，放眼望去，海边，悬崖上，到处都是这些萌物的身影。象龟的祖先千万年前就在这里生活，它们才是岛上真正的主人。象龟们淡定地在一旁晒太阳，毫不理会身旁的游人，专心地享受自己的生活。",
        "miniImage": "http://s3.cn.bing.net/th?id=OJ.xux0RRnYnOOUbw&pid=MSNJVFeeds",
        "miniUrl": "https://zhanghao-zhoushan.cn/image/story/s3.OJ.xux0RRnYnOOUbw.png"
      }
    ],
    "primaryImageUrl": "http://hpimges.blob.core.chinacloudapi.cn/coverstory/watermark_floreanaislandsealion_zh-cn12024860324_1920x1080.jpg",
    "imageUrl": "https://zhanghao-zhoushan.cn/image/large/GreetingtotheSun_ZH-CN13553844047_1366x768.jpg",
    "downLoadUrl": "https://zhanghao-zhoushan.cn/image/large/GreetingtotheSun_ZH-CN13553844047.jpg",
    "url": "http://cdn.nanxiongnandi.com/bing/GreetingtotheSun_ZH-CN13553844047_1366x768.jpg",
    "name": "GreetingtotheSun_ZH-CN13553844047.jpg",
    "provider": "© Tui De Roy/Minden Pictures",
    "copyright": "‘Greeting to the Sun’ installation by Nikola Bašić, Zadar, Croatia (© Ivan Coric/Alamy)(Bing China)",
    "Continent": "",
    "Country": "厄瓜多尔",
    "City": "Floreana Island",
    "Longitude": "-1.28299999237061",
    "Latitude": "-90.4329986572266"
  },
  {
    "dateString": "20150905",
    "date": 1441411200000,
    "attribute": "克罗地亚，扎达尔",
    "title": "历史名城",
    "story": [
      {
        "title": "魅力古城",
        "au": "沉淀之美",
        "describe": "这座历史名城经过千百年的时光洗礼之后，依然魅力四射，风光无限。那一座座古旧的城墙，喃喃诉说着扎达尔的历史；那一栋栋教堂，向世人们展示着人民们虔诚的信仰。静静漫步于此，你将会收获内心的宁静。",
        "miniImage": "http://s.cn.bing.net/th?id=OJ.bSjDziPJn6jaYw&pid=MSNJVFeeds",
        "miniUrl": "https://zhanghao-zhoushan.cn/image/story/s.OJ.bSjDziPJn6jaYw.png"
      },
      {
        "title": "地中海式气候",
        "au": "气候特点",
        "describe": "扎达尔属于地中海式气候，冬季温和多雨，一月平均气温7度左右，适宜出行，但由于常常下雨，最好带上雨具；夏季则较为炎热干燥一些，但气温是舒适的25度左右，是旅游的好时节。",
        "miniImage": "http://s3.cn.bing.net/th?id=OJ.GxemGXX5yPU0kw&pid=MSNJVFeeds",
        "miniUrl": "https://zhanghao-zhoushan.cn/image/story/s3.OJ.GxemGXX5yPU0kw.png"
      },
      {
        "title": "欧陆各国的融合",
        "au": "克罗地亚风味",
        "describe": "克罗地亚的菜融合了意大利、匈牙利和奥地利的口味，再加上本国自己的烹饪手法，使得整个菜式味道独特令人难忘。其中篝火烤肉、达尔马提亚熏火腿、以及羊奶酪都是不可错过的美味。",
        "miniImage": "http://s2.cn.bing.net/th?id=OJ.3daI16wL2sHBWg&pid=MSNJVFeeds",
        "miniUrl": "https://zhanghao-zhoushan.cn/image/story/s2.OJ.3daI16wL2sHBWg.png"
      }
    ],
    "primaryImageUrl": "http://hpimges.blob.core.chinacloudapi.cn/coverstory/watermark_greetingtothesun_zh-cn13553844047_1920x1080.jpg",
    "imageUrl": "https://zhanghao-zhoushan.cn/image/large/NaturalBridgesStateBeach_ZH-CN12512693578_1366x768.jpg",
    "downLoadUrl": "https://zhanghao-zhoushan.cn/image/large/NaturalBridgesStateBeach_ZH-CN12512693578.jpg",
    "url": "http://cdn.nanxiongnandi.com/bing/NaturalBridgesStateBeach_ZH-CN12512693578_1366x768.jpg",
    "name": "NaturalBridgesStateBeach_ZH-CN12512693578.jpg",
    "provider": "© Ivan Coric/Alamy",
    "copyright": "美国，加利福尼亚州，圣克鲁斯县，自然桥州立海滩 (© Fotofeeling/Westend61/plainpicture)(Bing China)",
    "Continent": "",
    "Country": "克罗地亚",
    "City": "Zadar",
    "Longitude": "44.1244010925293",
    "Latitude": "15.2469997406006"
  },
  {
    "dateString": "20150906",
    "date": 1441497600000,
    "attribute": "美国，加利福尼亚州",
    "title": "加州的海滩",
    "story": [
      {
        "title": "细沙柔浪",
        "au": "令人迷醉的景致",
        "describe": "加州，一个充满正能量的地方，阳光充足，大海迷人，在这里，当乞丐都是快乐的。今秋，趁着这还未消尽的暑气，去加州的海滩晒晒太阳，吹吹海风吧。",
        "miniImage": "http://s.cn.bing.net/th?id=OJ.q0ntAPo7jZwvqg&pid=MSNJVFeeds",
        "miniUrl": "https://zhanghao-zhoushan.cn/image/story/s.OJ.q0ntAPo7jZwvqg.png"
      },
      {
        "title": "早晚防寒",
        "au": "衣着建议",
        "describe": "若是夏秋季节去加州的海滩，早晚较凉且有海风，中午和下午温度较高，因此最好带上防寒外套，同时也要注意防晒。",
        "miniImage": "http://s2.cn.bing.net/th?id=OJ.Nlm8rquNA5PLzA&pid=MSNJVFeeds",
        "miniUrl": "https://zhanghao-zhoushan.cn/image/story/s2.OJ.Nlm8rquNA5PLzA.png"
      },
      {
        "title": "最好租车自驾",
        "au": "当地交通",
        "describe": "加州的公交系统并不是特别方便，外地游客前往最好是租车自驾游。这里许多公路沿路都有很好的美景，自驾既可以尽情地将美景慢慢看个够，又更加自由。",
        "miniImage": "http://s.cn.bing.net/th?id=OJ.wQQjednNxlQXRQ&pid=MSNJVFeeds",
        "miniUrl": "https://zhanghao-zhoushan.cn/image/story/s.OJ.wQQjednNxlQXRQ.png"
      }
    ],
    "primaryImageUrl": "http://hpimges.blob.core.chinacloudapi.cn/coverstory/watermark_naturalbridgesstatebeach_zh-cn12512693578_1920x1080.jpg",
    "imageUrl": "https://zhanghao-zhoushan.cn/image/large/BrooklynHeights_ZH-CN9036840807_1366x768.jpg",
    "downLoadUrl": "https://zhanghao-zhoushan.cn/image/large/BrooklynHeights_ZH-CN9036840807.jpg",
    "url": "http://cdn.nanxiongnandi.com/bing/BrooklynHeights_ZH-CN9036840807_1366x768.jpg",
    "name": "BrooklynHeights_ZH-CN9036840807.jpg",
    "provider": "© Fotofeeling/Westend61/plainpicture",
    "copyright": "纽约布鲁克林高地，在赤褐色砂石建筑上拍下的曼哈顿 (© Andrew C. Mace/Getty Images)(Bing China)",
    "Continent": "",
    "Country": "美国",
    "City": "Santa Cruz County",
    "Longitude": "37.0371284484863",
    "Latitude": "-122.008613586426"
  },
  {
    "dateString": "20150907",
    "date": 1441584000000,
    "attribute": "纽约，布鲁克林高地",
    "title": "性感的大苹果",
    "story": [
      {
        "title": "性感城市",
        "au": "自由自在的生活",
        "describe": "纽约，一个不可被定义的城市，它性感妖娆又文艺范儿十足，它纸醉金迷却又是艺术之都。在纽约，不必担心别人的眼光，你可以自由地做你自己。",
        "miniImage": "http://s4.cn.bing.net/th?id=OJ.Mkdrb5fP8pfobQ&pid=MSNJVFeeds",
        "miniUrl": "https://zhanghao-zhoushan.cn/image/story/s4.OJ.Mkdrb5fP8pfobQ.png"
      },
      {
        "title": "喂饱你的中国胃",
        "au": "唐人街",
        "describe": "出门在外最是思念那一盘盘温热的中国菜，此时，唐人街就是最好的去处。这里餐馆遍布，港式、川菜都很容易找到，虽说价格比国内的餐馆贵一些，但味道还不错，运气好的话还能吃到比国内餐馆还正宗的中国菜。",
        "miniImage": "http://s4.cn.bing.net/th?id=OJ.HP07JbXskkK3uQ&pid=MSNJVFeeds",
        "miniUrl": "https://zhanghao-zhoushan.cn/image/story/s4.OJ.HP07JbXskkK3uQ.png"
      },
      {
        "title": "纽约城中的意式风情",
        "au": "小意大利",
        "describe": "与唐人街毗邻，充满着意大利风情。沿街随处可见意大利餐厅、带有意大利标志的物件和国旗。一路上飘着匹萨饼和芝士的香味，让人忍不住立刻钻进旁边的餐厅大吃特吃。",
        "miniImage": "http://s4.cn.bing.net/th?id=OJ.2j7V62wegHZCcA&pid=MSNJVFeeds",
        "miniUrl": "https://zhanghao-zhoushan.cn/image/story/s4.OJ.2j7V62wegHZCcA.png"
      }
    ],
    "primaryImageUrl": "http://hpimges.blob.core.chinacloudapi.cn/coverstory/watermark_brooklynheights_zh-cn9036840807_1920x1080.jpg",
    "imageUrl": "https://zhanghao-zhoushan.cn/image/large/LeafcutterAnts_ZH-CN13590580459_1366x768.jpg",
    "downLoadUrl": "https://zhanghao-zhoushan.cn/image/large/LeafcutterAnts_ZH-CN13590580459.jpg",
    "url": "http://cdn.nanxiongnandi.com/bing/LeafcutterAnts_ZH-CN13590580459_1366x768.jpg",
    "name": "LeafcutterAnts_ZH-CN13590580459.jpg",
    "provider": "© Andrew C. Mace/Getty Images",
    "copyright": "哥斯达黎加，圣丽塔，切叶蚁（美洲切叶蚁属Atta） (© Bence Mate/Visuals Unlimited/Corbis)(Bing China)",
    "Continent": "",
    "Country": "美国",
    "City": "纽约",
    "Longitude": "40.7820014953613",
    "Latitude": "-73.8317031860352"
  },
  {
    "dateString": "20150908",
    "date": 1441670400000,
    "attribute": "哥斯达黎加，圣丽塔",
    "title": "哥斯达黎加",
    "story": [
      {
        "title": "美景常在",
        "au": "惬意之地",
        "describe": "这里有壮丽火山，有森林小镇，有可爱个性的都城，有迷人海滩，还有味道独特的美食。哥斯达黎加，满足你对旅行的一切幻想。",
        "miniImage": "http://s.cn.bing.net/th?id=OJ.NuW0ZPUqjiCxgA&pid=MSNJVFeeds",
        "miniUrl": "https://zhanghao-zhoushan.cn/image/story/s.OJ.NuW0ZPUqjiCxgA.png"
      },
      {
        "title": "毫不马虎的早餐",
        "au": "国菜",
        "describe": "早餐是当地人最重要的一顿，因此在菜式的烹饪手法和食材的使用上都很讲究。用大米和黑豆，与洋葱、辣椒、香菜等混合，再加上大蒜和香草等香料，吃的时候就着玉米饼、鸡蛋和酸奶油，美味可口。之后再来一个蛋羹甜品，吃完后，美好的一天就这样开始了。",
        "miniImage": "http://s3.cn.bing.net/th?id=OJ.2SecKdQXMWUgWA&pid=MSNJVFeeds",
        "miniUrl": "https://zhanghao-zhoushan.cn/image/story/s3.OJ.2SecKdQXMWUgWA.png"
      },
      {
        "title": "种类丰富多样",
        "au": "独特的果汁",
        "describe": "地处热带的哥斯达黎加水果种类特别丰富，木瓜、芒果、绿椰子、黑莓、番石榴等都可以将他们混合制成口感独特的果汁。此外这里还有一些奇怪的水果如腰果苹果，也就是包在腰果外面的果肉，榨成果汁后味道可口，值得尝试。",
        "miniImage": "http://s3.cn.bing.net/th?id=OJ.LnoD0qZX9KL80Q&pid=MSNJVFeeds",
        "miniUrl": "https://zhanghao-zhoushan.cn/image/story/s3.OJ.LnoD0qZX9KL80Q.png"
      }
    ],
    "primaryImageUrl": "http://hpimges.blob.core.chinacloudapi.cn/coverstory/watermark_leafcutterants_zh-cn13590580459_1920x1080.jpg",
    "imageUrl": "https://zhanghao-zhoushan.cn/image/large/CoalTitVideo_ZH-CN7865623960_1366x768.jpg",
    "downLoadUrl": "https://zhanghao-zhoushan.cn/image/large/CoalTitVideo_ZH-CN7865623960.jpg",
    "url": "http://cdn.nanxiongnandi.com/bing/CoalTitVideo_ZH-CN7865623960_1366x768.jpg",
    "name": "CoalTitVideo_ZH-CN7865623960.jpg",
    "provider": "© Bence Mate/Visuals Unlimited/Corbis",
    "copyright": "大不列颠，苏格兰，煤山雀栖息在地衣覆盖的树枝上 (© NHPA/SuperStock)(Bing China)",
    "Continent": "",
    "Country": "哥斯达黎加",
    "City": "Santa Rita",
    "Longitude": "15.0042295455933",
    "Latitude": "120.60563659668"
  },
  {
    "dateString": "20150909",
    "date": 1441756800000,
    "attribute": "大不列颠，苏格兰",
    "title": "爱丁堡",
    "story": [
      {
        "title": "小城大玩",
        "au": "转角便是惊喜",
        "describe": "作为一个地方的首府，爱丁堡算是很小的一座城了，用不了一天就能将整座城走遍。城市虽小，“五脏”俱全，这里的每一条小巷，每一个转角，都会给人惊喜。",
        "miniImage": "http://s1.cn.bing.net/th?id=OJ.r0syC5je8St2Rw&pid=MSNJVFeeds",
        "miniUrl": "https://zhanghao-zhoushan.cn/image/story/s1.OJ.r0syC5je8St2Rw.png"
      },
      {
        "title": "英国人的童年回忆",
        "au": "童年博物馆",
        "describe": "位于皇家英里的童年博物馆很有意思，这里收藏了从18世纪到现在英国儿童们的玩具，在这你将看到从古至今英国人的童年是什么样的，它既是小朋友们长知识的地方，也是大人们怀旧的地方。",
        "miniImage": "http://s2.cn.bing.net/th?id=OJ.wh1qu2HEd0d1bQ&pid=MSNJVFeeds",
        "miniUrl": "https://zhanghao-zhoushan.cn/image/story/s2.OJ.wh1qu2HEd0d1bQ.png"
      },
      {
        "title": "《哈利波特》的诞生地",
        "au": "大象咖啡厅",
        "describe": "这里就是J.K.罗琳写《哈利.波特》的地方，咖啡厅里装潢别致，咖啡香浓，食物美味，在这你可以吃到地道的当地食物，捷克土豆和牛肉派都是不错的选择。",
        "miniImage": "http://s2.cn.bing.net/th?id=OJ.BNxEdbg2ZXOApA&pid=MSNJVFeeds",
        "miniUrl": "https://zhanghao-zhoushan.cn/image/story/s2.OJ.BNxEdbg2ZXOApA.png"
      }
    ],
    "primaryImageUrl": "http://hpimges.blob.core.chinacloudapi.cn/coverstory/watermark_coaltitvideo_zh-cn7865623960_1920x1080.jpg",
    "imageUrl": "https://zhanghao-zhoushan.cn/image/large/HangSonDoong_ZH-CN6876052785_1366x768.jpg",
    "downLoadUrl": "https://zhanghao-zhoushan.cn/image/large/HangSonDoong_ZH-CN6876052785.jpg",
    "url": "http://cdn.nanxiongnandi.com/bing/HangSonDoong_ZH-CN6876052785_1366x768.jpg",
    "name": "HangSonDoong_ZH-CN6876052785.jpg",
    "provider": "© NHPA/SuperStock",
    "copyright": "[教师节：孤独求索，勇敢前行] 越南，丰芽格邦国家公园，韩松洞  (© Carsten Peter/Getty Images)(Bing China)",
    "Continent": "",
    "Country": "大不列颠",
    "City": "苏格兰",
    "Longitude": "56.6889381408691",
    "Latitude": "-4.04259967803955"
  },
  {
    "dateString": "20150910",
    "date": 1441843200000,
    "attribute": "越南，丰芽格邦国家公园",
    "title": "清新越南",
    "story": [
      {
        "title": "越南之约",
        "au": "风光无限",
        "describe": "湿润的气候、绵长的海岸线、奇特的钟乳石、神圣的名胜古迹，这些都是不断吸引游客前往的重要元素。这座融合了东方神秘色彩和法国浪漫风情的城市，一直散发着无穷的魅力。",
        "miniImage": "http://s4.cn.bing.net/th?id=OJ.hKNXxx8t2lxW3w&pid=MSNJVFeeds",
        "miniUrl": "https://zhanghao-zhoushan.cn/image/story/s4.OJ.hKNXxx8t2lxW3w.png"
      },
      {
        "title": "浓郁香醇",
        "au": "越南咖啡",
        "describe": "越南也是一个咖啡盛产地，咖啡是当地人的日常饮料。越南咖啡香味较浓，酸味略淡，香醇中带着微苦。传统的喝法是加入一些炼奶，这样口感更佳浓郁醇厚。",
        "miniImage": "http://s2.cn.bing.net/th?id=OJ.MZSoJRY6jJmlUw&pid=MSNJVFeeds",
        "miniUrl": "https://zhanghao-zhoushan.cn/image/story/s2.OJ.MZSoJRY6jJmlUw.png"
      },
      {
        "title": "清新爽口",
        "au": "越南鸡粉",
        "describe": "越南鸡粉久负盛名，在很多街边小店都可以吃到。一碗热腾腾的汤粉里有鸡丝、蛋丝、木耳、葱、香菜，再挤几滴柠檬汁进去，搅拌搅拌，看着叫人口舌生津。",
        "miniImage": "http://s3.cn.bing.net/th?id=OJ.91WG680Inq1Qmg&pid=MSNJVFeeds",
        "miniUrl": "https://zhanghao-zhoushan.cn/image/story/s3.OJ.91WG680Inq1Qmg.png"
      }
    ],
    "primaryImageUrl": "http://hpimges.blob.core.chinacloudapi.cn/coverstory/watermark_hangsondoong_zh-cn6876052785_1920x1080.jpg",
    "imageUrl": "https://zhanghao-zhoushan.cn/image/large/GorgesOfTarn_ZH-CN10940261268_1366x768.jpg",
    "downLoadUrl": "https://zhanghao-zhoushan.cn/image/large/GorgesOfTarn_ZH-CN10940261268.jpg",
    "url": "http://cdn.nanxiongnandi.com/bing/GorgesOfTarn_ZH-CN10940261268_1366x768.jpg",
    "name": "GorgesOfTarn_ZH-CN10940261268.jpg",
    "provider": "© Carsten Peter/Getty Images",
    "copyright": "法国，朗格多克-鲁西永，塞文山脉国家公园，塔尔恩峡谷 (© Jan Wlodarczyk/Alamy)(Bing China)",
    "Continent": "",
    "Country": "越南",
    "City": "Phong Nha Ke Bang National Park",
    "Longitude": "17.5333003997803",
    "Latitude": "106.150001525879"
  },
  {
    "dateString": "20150911",
    "date": 1441929600000,
    "attribute": "法国，朗格多克-鲁西永",
    "title": "南法风情",
    "story": [
      {
        "title": "自然与人文的较量",
        "au": "天然景观中又有古典人文景致",
        "describe": "法国不止有浪漫的巴黎，南部的恬静美丽或许更让人着迷。这里的景致风情万种，亦荒凉，亦清新，可以满足你任何需求。",
        "miniImage": "http://s4.cn.bing.net/th?id=OJ.6hUsTHY0fIjBDQ&pid=MSNJVFeeds",
        "miniUrl": "https://zhanghao-zhoushan.cn/image/story/s4.OJ.6hUsTHY0fIjBDQ.png"
      },
      {
        "title": "世界三大蓝莓干酪之一",
        "au": "罗克福干酪",
        "describe": "说到这里的特产，就不得不提罗克福干酪。它与意大利的戈贡佐拉干酪和英国的斯蒂尔顿干酪并称为世界三大干酪。外观呈白色，有强烈的盐香味，质地湿软、易碎，口感醇厚、香甜。若是喜欢奶酪的话，罗克福干酪一定不要错过。",
        "miniImage": "http://s3.cn.bing.net/th?id=OJ.HiBMEtnbcgP0DA&pid=MSNJVFeeds",
        "miniUrl": "https://zhanghao-zhoushan.cn/image/story/s3.OJ.HiBMEtnbcgP0DA.png"
      },
      {
        "title": "畜牧圣地",
        "au": "农牧业之乡",
        "describe": "这里山峦交错、沟壑纵横，加上宜人的气候让此地成为一个农牧业之乡。此处饲养着许多母绵羊，因此也造就了这里的奶酪传说。每到夏季，山峦上尽是白白的绵羊，画面很是迷人。",
        "miniImage": "http://s.cn.bing.net/th?id=OJ.2OFi3AApYDcKxQ&pid=MSNJVFeeds",
        "miniUrl": "https://zhanghao-zhoushan.cn/image/story/s.OJ.2OFi3AApYDcKxQ.png"
      }
    ],
    "primaryImageUrl": "http://hpimges.blob.core.chinacloudapi.cn/coverstory/watermark_gorgesoftarn_zh-cn10940261268_1920x1080.jpg",
    "imageUrl": "https://zhanghao-zhoushan.cn/image/large/UnaLagoon_ZH-CN11291682527_1366x768.jpg",
    "downLoadUrl": "https://zhanghao-zhoushan.cn/image/large/UnaLagoon_ZH-CN11291682527.jpg",
    "url": "http://cdn.nanxiongnandi.com/bing/UnaLagoon_ZH-CN11291682527_1366x768.jpg",
    "name": "UnaLagoon_ZH-CN11291682527.jpg",
    "provider": "© Jan Wlodarczyk/Alamy",
    "copyright": "西班牙，靠近昆卡的潟湖 (© David Santiago Garcia/Aurora Photos)(Bing China)",
    "Continent": "",
    "Country": "法国",
    "City": "朗格多克-鲁西永",
    "Longitude": "43.6543875",
    "Latitude": "3.266995"
  },
  {
    "dateString": "20150912",
    "date": 1442016000000,
    "attribute": "西班牙，昆卡",
    "title": "古老而安静的地方",
    "story": [
      {
        "title": "走进昆卡",
        "au": "静品它的历史魅力",
        "describe": "西班牙诗人卡米洛·何塞·塞拉曾说：“昆卡，如爱情一般，优雅而断肠。”它历史悠久，充满生活气息，对于当地人来说，没有什么比生活本身更加重要的事情了。",
        "miniImage": "http://s1.cn.bing.net/th?id=OJ.LNQCgq0Mbrw0xA&pid=MSNJVFeeds",
        "miniUrl": "https://zhanghao-zhoushan.cn/image/story/s1.OJ.LNQCgq0Mbrw0xA.png"
      },
      {
        "title": "九月的狂欢",
        "au": "圣马特奥节",
        "describe": "这个节日是为了纪念阿方索八世攻占昆卡而举办。每年的9月21日城中都会非常热闹，当地的民众从马约尔广场出发，在附近的街道狂奔。这一盛景一年只能见到一次。",
        "miniImage": "http://s2.cn.bing.net/th?id=OJ.M25WpQevuWUAUw&pid=MSNJVFeeds",
        "miniUrl": "https://zhanghao-zhoushan.cn/image/story/s2.OJ.M25WpQevuWUAUw.png"
      },
      {
        "title": "编藤手工艺的传人",
        "au": "何塞路易斯",
        "describe": "在古城附近的小镇上有一位编藤手工艺人名叫何塞路易斯，编藤是西班牙的传统手工艺，他是这种技艺仅存的唯一传人。当地总会有人高价购买他的作品作为收藏，有效保护了这一手工技艺的传承。",
        "miniImage": "http://s4.cn.bing.net/th?id=OJ.9a94a95dq1H1mg&pid=MSNJVFeeds",
        "miniUrl": "https://zhanghao-zhoushan.cn/image/story/s4.OJ.9a94a95dq1H1mg.png"
      }
    ],
    "primaryImageUrl": "http://hpimges.blob.core.chinacloudapi.cn/coverstory/watermark_unalagoon_zh-cn11291682527_1920x1080.jpg",
    "imageUrl": "https://zhanghao-zhoushan.cn/image/large/GreySeals_ZH-CN10078575122_1366x768.jpg",
    "downLoadUrl": "https://zhanghao-zhoushan.cn/image/large/GreySeals_ZH-CN10078575122.jpg",
    "url": "http://cdn.nanxiongnandi.com/bing/GreySeals_ZH-CN10078575122_1366x768.jpg",
    "name": "GreySeals_ZH-CN10078575122.jpg",
    "provider": "© David Santiago Garcia/Aurora Photos",
    "copyright": "德国，黑尔戈兰岛，灰海豹 (© Robert Harding Picture Library/Superstock)(Bing China)",
    "Continent": "",
    "Country": "西班牙",
    "City": "昆卡",
    "Longitude": "40.0619721",
    "Latitude": "-2.1480249"
  },
  {
    "dateString": "20150913",
    "date": 1442102400000,
    "attribute": "德国，黑尔戈兰岛",
    "title": "美丽巴伐利亚",
    "story": [
      {
        "title": "德意志",
        "au": "一个活泼有趣的国度",
        "describe": "德国，不仅仅只有像柏林那样现代化的城市，更有风景优美，却没那么热门的旅游胜地，比如黑尔戈兰岛；也有充满童话色彩的古旧老城，如杜塞尔多夫。在德国，你想怎么玩都可以。",
        "miniImage": "http://s1.cn.bing.net/th?id=OJ.tXqE7cI4EbfzAw&pid=MSNJVFeeds",
        "miniUrl": "https://zhanghao-zhoushan.cn/image/story/s1.OJ.tXqE7cI4EbfzAw.png"
      },
      {
        "title": "最纯正的德国味",
        "au": "杜塞尔多夫的老啤酒",
        "describe": "有人曾这样说：“在杜塞尔多夫，人们不是在喝啤酒，就是在去喝啤酒的路上。”说这里是啤酒胜地一点也不为过，其中最有名的便是发源于此的老啤酒。这种啤酒色泽丰富，有琥珀色、棕黄和深褐色，口感芳香清爽，又带些苦味，来到杜城一定不可错过。",
        "miniImage": "http://s4.cn.bing.net/th?id=OJ.4uwLysDMpNfSDw&pid=MSNJVFeeds",
        "miniUrl": "https://zhanghao-zhoushan.cn/image/story/s4.OJ.4uwLysDMpNfSDw.png"
      },
      {
        "title": "清新舒适的疗养胜地",
        "au": "黑尔戈兰",
        "describe": "岛很小，人也非常少。与德国其它疗养地相比，这里的空气最洁净，含氧量最高。有医生曾说，在这里疗养一周的效果，比在棕榈海滩上呆三周还要好。这里远离陆地，因而远离烦扰，再加上有无可取代的自然资源，成为疗养胜地是再合理不过的了。",
        "miniImage": "http://s.cn.bing.net/th?id=OJ.JC0lBBk0tuMnxg&pid=MSNJVFeeds",
        "miniUrl": "https://zhanghao-zhoushan.cn/image/story/s.OJ.JC0lBBk0tuMnxg.png"
      }
    ],
    "primaryImageUrl": "http://hpimges.blob.core.chinacloudapi.cn/coverstory/watermark_greyseals_zh-cn10078575122_1920x1080.jpg",
    "imageUrl": "https://zhanghao-zhoushan.cn/image/large/BlackNapedMonarch_ZH-CN13391768581_1366x768.jpg",
    "downLoadUrl": "https://zhanghao-zhoushan.cn/image/large/BlackNapedMonarch_ZH-CN13391768581.jpg",
    "url": "http://cdn.nanxiongnandi.com/bing/BlackNapedMonarch_ZH-CN13391768581_1366x768.jpg",
    "name": "BlackNapedMonarch_ZH-CN13391768581.jpg",
    "provider": "© Robert Harding Picture Library/Superstoc",
    "copyright": "枝头上的黑枕王鹟 (© kajornyot/Shutterstock)(Bing China)",
    "Continent": "",
    "Country": "",
    "City": "",
    "Longitude": "",
    "Latitude": ""
  },
  {
    "dateString": "20150914",
    "date": 1442188800000,
    "attribute": "枝头上的黑枕王鹟",
    "title": "枝头上的精灵们",
    "story": [
      {
        "title": "观鸟就去这些地方",
        "au": "景色迷人，鸟儿们的天堂",
        "describe": "每当看到天空中展翅飞翔的鸟儿们，就无比羡慕它们能够如此自由自在。只需扑闪扑闪翅膀，便能在万里晴空中遨游。看着它们，自己的心也跟着飞翔起来。",
        "miniImage": "http://s2.cn.bing.net/th?id=OJ.zWX6YHLH2f1i1g&pid=MSNJVFeeds",
        "miniUrl": "https://zhanghao-zhoushan.cn/image/story/s2.OJ.zWX6YHLH2f1i1g.png"
      },
      {
        "title": "蓝色精灵",
        "au": "黑枕王鹟",
        "describe": "这种小鸟体态轻盈，性格活泼好奇，非常可爱。它们的羽毛多为蓝色，肚子则为白色，娇小美丽。这种鸟类喜欢栖息于树枝和灌木丛中，多生长于云南、广西、贵州和海南岛一带。当你听到它欢快的叽喳声时，心情也会随之愉悦起来。",
        "miniImage": "http://s2.cn.bing.net/th?id=OJ.bzYil1FRQx88Zg&pid=MSNJVFeeds",
        "miniUrl": "https://zhanghao-zhoushan.cn/image/story/s2.OJ.bzYil1FRQx88Zg.png"
      },
      {
        "title": "灰黑色的捕猎手",
        "au": "黑颈鹤",
        "describe": "黑颈鹤属于大型鸟类，全长约120厘米，脖子和腿部较长。黑颈鹤全身灰白，头顶裸露出来的部分呈红色，在阳光的照耀下非常显眼。这种鸟类多生长在高原，在西藏、青海、甘肃一带，在贵州、云南等地也能看到。",
        "miniImage": "http://s2.cn.bing.net/th?id=OJ.USU4qHT00KTntQ&pid=MSNJVFeeds",
        "miniUrl": "https://zhanghao-zhoushan.cn/image/story/s2.OJ.USU4qHT00KTntQ.png"
      }
    ],
    "primaryImageUrl": "http://hpimges.blob.core.chinacloudapi.cn/coverstory/watermark_blacknapedmonarch_zh-cn13391768581_1920x1080.jpg",
    "imageUrl": "https://zhanghao-zhoushan.cn/image/large/BirchTreesChina_ZH-CN9148200557_1366x768.jpg",
    "downLoadUrl": "https://zhanghao-zhoushan.cn/image/large/BirchTreesChina_ZH-CN9148200557.jpg",
    "url": "http://cdn.nanxiongnandi.com/bing/BirchTreesChina_ZH-CN9148200557_1366x768.jpg",
    "name": "BirchTreesChina_ZH-CN9148200557.jpg",
    "provider": "© kajornyot/Shutterstock",
    "copyright": "中国，坝上草原上的桦树 (© Aaron Ng Photography/Getty Images)(Bing China)",
    "Continent": "",
    "Country": "",
    "City": "",
    "Longitude": "",
    "Latitude": ""
  },
  {
    "dateString": "20150915",
    "date": 1442275200000,
    "attribute": "中国，坝上草原",
    "title": "坝上草原",
    "story": [
      {
        "title": "坝上的美好时光",
        "au": "与草原赴一场秋日之约",
        "describe": "大清帝王喜游猎，常率众精兵前往坝上打猎巡游，如此过瘾之地怎能错过？这里天高云低，空气里弥漫着青草香，沁人心脾。",
        "miniImage": "http://s4.cn.bing.net/th?id=OJ.VMt8Dx8zpvalEQ&pid=MSNJVFeeds",
        "miniUrl": "https://zhanghao-zhoushan.cn/image/story/s4.OJ.VMt8Dx8zpvalEQ.png"
      },
      {
        "title": "层林尽染",
        "au": "迷人白桦林",
        "describe": "一入秋，坝上的白桦林便开始搔首弄姿起来。霜降过后，满山的桦树、红松和云杉树便开启它们最灿烂美丽的时光。当你沿途经过坝上时，那无尽的美景会让你舍不得眨眼。",
        "miniImage": "http://s4.cn.bing.net/th?id=OJ.gB5BUwzVD1zFcw&pid=MSNJVFeeds",
        "miniUrl": "https://zhanghao-zhoushan.cn/image/story/s4.OJ.gB5BUwzVD1zFcw.png"
      },
      {
        "title": "不可不去的人间仙境",
        "au": "闪电湖",
        "describe": "天苍苍，野茫茫，一片旷野之中澄澈的闪电湖静静地躺在那里，宛若处子。时不时你可以看到马儿们在此低头饮水，好一幅唯美的坝上草原画面。",
        "miniImage": "http://s1.cn.bing.net/th?id=OJ.Rt9vndUnHWgwug&pid=MSNJVFeeds",
        "miniUrl": "https://zhanghao-zhoushan.cn/image/story/s1.OJ.Rt9vndUnHWgwug.png"
      }
    ],
    "primaryImageUrl": "http://hpimges.blob.core.chinacloudapi.cn/coverstory/watermark_birchtreeschina_zh-cn9148200557_1920x1080.jpg",
    "imageUrl": "https://zhanghao-zhoushan.cn/image/large/CapReefMilky_ZH-CN15296973338_1366x768.jpg",
    "downLoadUrl": "https://zhanghao-zhoushan.cn/image/large/CapReefMilky_ZH-CN15296973338.jpg",
    "url": "http://cdn.nanxiongnandi.com/bing/CapReefMilky_ZH-CN15296973338_1366x768.jpg",
    "name": "CapReefMilky_ZH-CN15296973338.jpg",
    "provider": "© Aaron Ng Photography/Getty Images",
    "copyright": "美国，犹他州，圆顶礁国家公园上空的银河 (© Dave Lane/NASA)(Bing China)",
    "Continent": "",
    "Country": "中国",
    "City": "坝上草原",
    "Longitude": "41.589182",
    "Latitude": "116.0019635"
  },
  {
    "dateString": "20150916",
    "date": 1442361600000,
    "attribute": "美国，犹他州",
    "title": "难忘的犹他之旅",
    "story": [
      {
        "title": "旷世美景",
        "au": "会让你眼前一亮",
        "describe": "位于美国西部，浩瀚的沙漠，嶙峋怪石遍布，给人以视觉上的冲击。在这里，你既可以进行狂野的探险活动，又可以静下来感受古代神话和历史的魅力，由你随心所欲。",
        "miniImage": "http://s2.cn.bing.net/th?id=OJ.kgpSwcbBtMJQ2A&pid=MSNJVFeeds",
        "miniUrl": "https://zhanghao-zhoushan.cn/image/story/s2.OJ.kgpSwcbBtMJQ2A.png"
      },
      {
        "title": "不可错过的观星胜地",
        "au": "锡达布雷克斯国家保护区",
        "describe": "这里远离城市的光污染，因此有全美最黑暗的夜空之一的称号，是一个名副其实的观星胜地。一入夜，当你抬头仰望，便能被那漫天的繁星所惊艳。工作人员和志愿者们每到夏季就会举办观星派对，让你得以好好享受这迷人的仲夏夜。",
        "miniImage": "http://s4.cn.bing.net/th?id=OJ.sWfkH0pZ2pnOTQ&pid=MSNJVFeeds",
        "miniUrl": "https://zhanghao-zhoushan.cn/image/story/s4.OJ.sWfkH0pZ2pnOTQ.png"
      },
      {
        "title": "来一次历史文化之旅",
        "au": "犹他州自然历史博物馆",
        "describe": "在亲身踏入自然美景之前，可以先到自然历史博物馆梳理一下这里的历史知识，亦或是在疲惫旅行之后来到此处回味之前的所见所闻。不管怎样，犹他州自然历史博物馆一定会为你的旅途锦上添花。",
        "miniImage": "http://s.cn.bing.net/th?id=OJ.d6bK0TOryK07hA&pid=MSNJVFeeds",
        "miniUrl": "https://zhanghao-zhoushan.cn/image/story/s.OJ.d6bK0TOryK07hA.png"
      }
    ],
    "primaryImageUrl": "http://hpimges.blob.core.chinacloudapi.cn/coverstory/watermark_capreefmilky_zh-cn15296973338_1920x1080.jpg",
    "imageUrl": "https://zhanghao-zhoushan.cn/image/large/SegoviaVideo_ZH-CN11936776081_1366x768.jpg",
    "downLoadUrl": "https://zhanghao-zhoushan.cn/image/large/SegoviaVideo_ZH-CN11936776081.jpg",
    "url": "http://cdn.nanxiongnandi.com/bing/SegoviaVideo_ZH-CN11936776081_1366x768.jpg",
    "name": "SegoviaVideo_ZH-CN11936776081.jpg",
    "provider": "© Dave Lane/NASA",
    "copyright": "西班牙，塞哥维亚 (© Shutterstock)(Bing China)",
    "Continent": "",
    "Country": "美国",
    "City": "犹他州",
    "Longitude": "39.4997605",
    "Latitude": "-111.547028"
  },
  {
    "dateString": "20150917",
    "date": 1442448000000,
    "attribute": "西班牙，塞哥维亚",
    "title": "热情不一定非似火",
    "story": [
      {
        "title": "深厚却不沉闷",
        "au": "历史之城也有童话色彩",
        "describe": "西班牙总是热情似火，而塞哥维亚却冷静许多。许多年前的战役赋予它沉重且让人肃然起敬的一面，但也不妨碍它发散发出梦幻的童话色彩和骨子里的热情。",
        "miniImage": "http://s4.cn.bing.net/th?id=OJ.DwYLpcnQt37O8g&pid=MSNJVFeeds",
        "miniUrl": "https://zhanghao-zhoushan.cn/image/story/s4.OJ.DwYLpcnQt37O8g.png"
      },
      {
        "title": "红肠、蛋卷不容错过",
        "au": "特色美食",
        "describe": "塞哥维亚的红肠和肉蛋卷是当地特色，推荐尝试。这两道菜都以伊比利亚猪肉作为原料，鲜香而不油腻，一口咬下去唇齿留香。这里的烤乳猪和黑毛火腿也值得品尝。",
        "miniImage": "http://s3.cn.bing.net/th?id=OJ.Xk0H27fdlto3WA&pid=MSNJVFeeds",
        "miniUrl": "https://zhanghao-zhoushan.cn/image/story/s3.OJ.Xk0H27fdlto3WA.png"
      },
      {
        "title": "小店云集 琳琅满目",
        "au": "购物该去哪？",
        "describe": "萨拉曼加区的街道上遍布着时尚精品店、古玩店、书店、画廊等；楚埃卡区有着十足的波西米亚风格，在这里可以买到漂亮的皮具和鞋子，也有不少纹身店；在马约尔广场一带则有不少纪念品店，可以买到当地传统的工艺品，同样非常好逛。",
        "miniImage": "http://s.cn.bing.net/th?id=OJ.mI6pFW4vhO7CkQ&pid=MSNJVFeeds",
        "miniUrl": "https://zhanghao-zhoushan.cn/image/story/s.OJ.mI6pFW4vhO7CkQ.png"
      }
    ],
    "primaryImageUrl": "http://hpimges.blob.core.chinacloudapi.cn/coverstory/watermark_segoviavideo_zh-cn11936776081_1920x1080.jpg",
    "imageUrl": "https://zhanghao-zhoushan.cn/image/large/Charoite_ZH-CN12214915707_1366x768.jpg",
    "downLoadUrl": "https://zhanghao-zhoushan.cn/image/large/Charoite_ZH-CN12214915707.jpg",
    "url": "http://cdn.nanxiongnandi.com/bing/Charoite_ZH-CN12214915707_1366x768.jpg",
    "name": "Charoite_ZH-CN12214915707.jpg",
    "provider": "© Shutterstock",
    "copyright": "俄罗斯，雅库特，紫龙晶截面 (© Bernardo Cesare/Corbis)(Bing China)",
    "Continent": "",
    "Country": "西班牙",
    "City": "塞哥维亚",
    "Longitude": "40.9118568",
    "Latitude": "-4.1942675"
  },
  {
    "dateString": "20150918",
    "date": 1442534400000,
    "attribute": "俄罗斯，雅库特",
    "title": "北国好风光",
    "story": [
      {
        "title": "情迷俄罗斯",
        "au": "大国里那些迷人的景色",
        "describe": "在世界上最寒冷的城市雅库特体验一回冰酒吧；在全球最深最清澈的贝加尔湖畔乘火车赏美景；在这个全世界最大的国度，留下最美好的回忆。俄罗斯，让人无法忘怀。",
        "miniImage": "http://s4.cn.bing.net/th?id=OJ.DwYLpcnQt37O8g&pid=MSNJVFeeds",
        "miniUrl": "https://zhanghao-zhoushan.cn/image/story/s4.OJ.DwYLpcnQt37O8g.png"
      },
      {
        "title": "戏剧之都",
        "au": "俄国艺术",
        "describe": "没错，俄罗斯也是一个戏剧盛行的国家。这里有好几百个专业剧院，大约一半是专业的戏剧院，剩下的均是木偶或少数民族剧院。剧种丰富，尤其是歌剧很受人们的喜爱。",
        "miniImage": "http://s.cn.bing.net/th?id=OJ.q9K3pchiFQgTng&pid=MSNJVFeeds",
        "miniUrl": "https://zhanghao-zhoushan.cn/image/story/s.OJ.q9K3pchiFQgTng.png"
      },
      {
        "title": "最具宗教品格的民族",
        "au": "虔诚信仰",
        "describe": "在现实生活和俄罗斯的文学作品中，随处可发现东正教所宣扬的爱与宽恕的思想。在果戈里、列夫·托尔斯泰的作品中都能看到东正教的宗教哲理。这一宗教对当地人的影响至深，从当地人的性格当中也能看出。",
        "miniImage": "http://s4.cn.bing.net/th?id=OJ.bROZaxGQBzzmVw&pid=MSNJVFeeds",
        "miniUrl": "https://zhanghao-zhoushan.cn/image/story/s4.OJ.bROZaxGQBzzmVw.png"
      }
    ],
    "primaryImageUrl": "http://hpimges.blob.core.chinacloudapi.cn/coverstory/watermark_charoite_zh-cn12214915707_1920x1080.jpg",
    "imageUrl": "https://zhanghao-zhoushan.cn/image/large/BratwurstPolka_ZH-CN13791851201_1366x768.jpg",
    "downLoadUrl": "https://zhanghao-zhoushan.cn/image/large/BratwurstPolka_ZH-CN13791851201.jpg",
    "url": "http://cdn.nanxiongnandi.com/bing/BratwurstPolka_ZH-CN13791851201_1366x768.jpg",
    "name": "BratwurstPolka_ZH-CN13791851201.jpg",
    "provider": "© Bernardo Cesare/Corbis",
    "copyright": "德国，慕尼黑，啤酒节帐篷内景 (© WRIGHT/Superstock)(Bing China)",
    "Continent": "",
    "Country": "",
    "City": "",
    "Longitude": "",
    "Latitude": ""
  },
  {
    "dateString": "20150919",
    "date": 1442620800000,
    "attribute": "德国，慕尼黑",
    "title": "在慕尼黑狂欢",
    "story": [
      {
        "title": "乐游慕尼黑",
        "au": "是历史古城，亦是欢乐海洋",
        "describe": "这里有全世界最好喝的啤酒和最软糯的烤猪肘，有哥特式的市政厅和古旧迷人的圣母教堂，更有充满童话色彩的城堡和历史悠久的广场。淳朴的巴伐利亚人民用他们的热情融化你，用他们的快乐感染你的心。",
        "miniImage": "http://s.cn.bing.net/th?id=OJ.lqiNyqQkyHUJNQ&pid=MSNJVFeeds",
        "miniUrl": "https://zhanghao-zhoushan.cn/image/story/s.OJ.lqiNyqQkyHUJNQ.png"
      },
      {
        "title": "上千人的嘉年华",
        "au": "啤酒节帐篷",
        "describe": "每年的慕尼黑啤酒节，德国的啤酒厂便会在此搭起巨大的帐篷，招待来自世界的游客。棚内摆放着一排排可以坐下20人左右的长凳长桌，会场中心则是用鲜花装饰的舞台，会有艺术家献上现场表演。这种帐篷一般可以容纳4000-5000人，有的甚至能容纳7000人左右。",
        "miniImage": "http://s1.cn.bing.net/th?id=OJ.RPrUYZXmWUvqiw&pid=MSNJVFeeds",
        "miniUrl": "https://zhanghao-zhoushan.cn/image/story/s1.OJ.RPrUYZXmWUvqiw.png"
      },
      {
        "title": "新鲜醇厚的特别体验",
        "au": "特酿美酒",
        "describe": "每次啤酒节，酒厂们都会特别酿制一种名为Wiesenbier的啤酒。它的颜色更深，酒劲更大，也更加香醇。除了啤酒，还有当地特色食物可以品尝，如烤猪肘、香肠、酸菜和牛尾等。大口吃肉，大口喝酒，非常过瘾。",
        "miniImage": "http://s1.cn.bing.net/th?id=OJ.gjv6r0wUS38fQg&pid=MSNJVFeeds",
        "miniUrl": "https://zhanghao-zhoushan.cn/image/story/s1.OJ.gjv6r0wUS38fQg.png"
      }
    ],
    "primaryImageUrl": "http://hpimges.blob.core.chinacloudapi.cn/coverstory/watermark_bratwurstpolka_zh-cn13791851201_1920x1080.jpg",
    "imageUrl": "https://zhanghao-zhoushan.cn/image/large/LakeMyvat_ZH-CN9633085054_1366x768.jpg",
    "downLoadUrl": "https://zhanghao-zhoushan.cn/image/large/LakeMyvat_ZH-CN9633085054.jpg",
    "url": "http://cdn.nanxiongnandi.com/bing/LakeMyvat_ZH-CN9633085054_1366x768.jpg",
    "name": "LakeMyvat_ZH-CN9633085054.jpg",
    "provider": "© WRIGHT/Superstock",
    "copyright": "冰岛，米湖附近的温泉洞 (© Joerg Abendroth/Tandem Stills + Motion)(Bing China)",
    "Continent": "",
    "Country": "德国",
    "City": "慕尼黑",
    "Longitude": "48.1549107",
    "Latitude": "11.5418357"
  },
  {
    "dateString": "20150920",
    "date": 1442707200000,
    "attribute": "冰岛，米湖",
    "title": "冰火之国",
    "story": [
      {
        "title": "仙境之地",
        "au": "冰川之下，白雾缭绕",
        "describe": "位于北大西洋和北冰洋的交界处，这座岛屿看上去是那么清冷孤傲，可当你踏入它的国土时，会被那如火的热情给融化。冰岛，这座冰与火相交互融的迷人国度，会让你爱上后无法自拔。",
        "miniImage": "http://s1.cn.bing.net/th?id=OJ.IbdtTFPtIwF2Yw&pid=MSNJVFeeds",
        "miniUrl": "https://zhanghao-zhoushan.cn/image/story/s1.OJ.IbdtTFPtIwF2Yw.png"
      },
      {
        "title": "北国的新鲜美味",
        "au": "冰岛美食",
        "describe": "若你是爱肉之人，那冰岛一定能满足你。这里的三文鱼肉质鲜嫩，口感和质量都属顶级；羊肉更是鲜美无比，当地人采用传统的饲养方式，羊吃的都是青草等植物，健康又美味；此外，这里的奶酪、酸奶等奶制品也是有名的特产，值得一试。",
        "miniImage": "http://s1.cn.bing.net/th?id=OJ.4unar23qH2gbWA&pid=MSNJVFeeds",
        "miniUrl": "https://zhanghao-zhoushan.cn/image/story/s1.OJ.4unar23qH2gbWA.png"
      },
      {
        "title": "冰川脚下的温暖仙境",
        "au": "温泉之乡",
        "describe": "冰岛是个火山之国，岛内有好几百座火山，因此自然是温泉遍布，是全世界温泉最多的国家。一个个地热温泉被誉为“天然美容院”，泡在热气腾腾的湖中，周围有冰川作伴，如此场景如梦如幻。",
        "miniImage": "http://s3.cn.bing.net/th?id=OJ.JCj0YbQYDVzukQ&pid=MSNJVFeeds",
        "miniUrl": "https://zhanghao-zhoushan.cn/image/story/s3.OJ.JCj0YbQYDVzukQ.png"
      }
    ],
    "primaryImageUrl": "http://hpimges.blob.core.chinacloudapi.cn/coverstory/watermark_lakemyvat_zh-cn9633085054_1920x1080.jpg",
    "imageUrl": "https://zhanghao-zhoushan.cn/image/large/IxtapaJellyfish_ZH-CN9411866711_1366x768.jpg",
    "downLoadUrl": "https://zhanghao-zhoushan.cn/image/large/IxtapaJellyfish_ZH-CN9411866711.jpg",
    "url": "http://cdn.nanxiongnandi.com/bing/IxtapaJellyfish_ZH-CN9411866711_1366x768.jpg",
    "name": "IxtapaJellyfish_ZH-CN9411866711.jpg",
    "provider": "© Joerg Abendroth/Tandem Stills + Motion",
    "copyright": "墨西哥，格雷罗州，伊斯塔帕，紫水母 (© Christian Vizl/Tandem Stills + Motion)(Bing China)",
    "Continent": "",
    "Country": "冰岛",
    "City": "米湖",
    "Longitude": "65.603259",
    "Latitude": "-17.0049959"
  },
  {
    "dateString": "20150921",
    "date": 1442793600000,
    "attribute": "墨西哥，格雷罗州",
    "title": "魅力坎昆",
    "story": [
      {
        "title": "斑斓之地",
        "au": "一个有灵魂的地方",
        "describe": "三面环海，风光旖旎，洁白软绵的沙滩让人喜欢至极。动物们憨态可掬，轻柔的海风时刻抚摸着脸庞，叫人万分舍不得这个地方。",
        "miniImage": "http://s3.cn.bing.net/th?id=OJ.uBnrIz4ZXAqxpA&pid=MSNJVFeeds",
        "miniUrl": "https://zhanghao-zhoushan.cn/image/story/s3.OJ.uBnrIz4ZXAqxpA.png"
      },
      {
        "title": "神秘与智慧",
        "au": "玛雅文化",
        "describe": "大约在5000年前，玛雅人来到墨西哥，在这里繁衍生息。从石器时代开始，一直过渡到农耕时代。玛雅人认为，人的死亡并不是终点，而是另一段旅程的开始。玛雅文化在此繁盛，却突然消失，消失的原因至今仍是一个迷。这一古文明一直吸引着世界各地的游客前往探索。",
        "miniImage": "http://s.cn.bing.net/th?id=OJ.0dMsPdg5WUpObQ&pid=MSNJVFeeds",
        "miniUrl": "https://zhanghao-zhoushan.cn/image/story/s.OJ.0dMsPdg5WUpObQ.png"
      },
      {
        "title": "酸酸辣辣，让人大呼过瘾",
        "au": "墨西哥菜",
        "describe": "墨西哥菜的口味以辣为主，当地的辣酱多采用彩椒和番茄烹制而成，口味独特，辣中带酸，非常开胃。不容错过的菜式有包着香嫩牛肉的墨西哥卷饼、又香又脆的玉米卷以及传统地道的托底拉汤，每一道都让人唇齿留香。",
        "miniImage": "http://s3.cn.bing.net/th?id=OJ.PxIC8wHLS367pA&pid=MSNJVFeeds",
        "miniUrl": "https://zhanghao-zhoushan.cn/image/story/s3.OJ.PxIC8wHLS367pA.png"
      }
    ],
    "primaryImageUrl": "http://hpimges.blob.core.chinacloudapi.cn/coverstory/watermark_ixtapajellyfish_zh-cn9411866711_1920x1080.jpg",
    "imageUrl": "https://zhanghao-zhoushan.cn/image/large/Hobbiton_ZH-CN11259204468_1366x768.jpg",
    "downLoadUrl": "https://zhanghao-zhoushan.cn/image/large/Hobbiton_ZH-CN11259204468.jpg",
    "url": "http://cdn.nanxiongnandi.com/bing/Hobbiton_ZH-CN11259204468_1366x768.jpg",
    "name": "Hobbiton_ZH-CN11259204468.jpg",
    "provider": "© Christian Vizl/Tandem Stills + Motion",
    "copyright": "新西兰，北岛，玛塔玛塔附近，霍比屯 (© imageBROKER/Rex Features)(Bing China)",
    "Continent": "",
    "Country": "",
    "City": "",
    "Longitude": "",
    "Latitude": ""
  },
  {
    "dateString": "20150922",
    "date": 1442880000000,
    "attribute": "新西兰，霍比屯",
    "title": "精灵王国",
    "story": [
      {
        "title": "走进童话世界",
        "au": "与霍比特人赴一场秋日之约",
        "describe": "这里犹如一个天然的大花园，葱绿植被伸手可触，站在海湾面上朝大海望去，活泼的海豚纵身跳跃，让人惊喜不已。这是一个精灵王国，奇幻又美丽。",
        "miniImage": "http://s4.cn.bing.net/th?id=OJ.ftjF7efrTj5EbQ&pid=MSNJVFeeds",
        "miniUrl": "https://zhanghao-zhoushan.cn/image/story/s4.OJ.ftjF7efrTj5EbQ.png"
      },
      {
        "title": "能歌善舞 心灵手巧",
        "au": "毛利人",
        "describe": "这个民族是公认的天生的艺术家，他们能歌善舞、手艺精湛，将传教士教授的赞美歌稍加改编，便成了他们专有的音乐。此外，那些随处可见的精湛木雕更是显示了这个民族的心灵手巧。",
        "miniImage": "http://s2.cn.bing.net/th?id=OJ.1J02igZNkiyxMg&pid=MSNJVFeeds",
        "miniUrl": "https://zhanghao-zhoushan.cn/image/story/s2.OJ.1J02igZNkiyxMg.png"
      },
      {
        "title": "醇香浓郁",
        "au": "新西兰咖啡",
        "describe": "咖啡发烧友一定要去“咖啡之都”惠灵顿走一趟。走在街上，咖啡馆随处可见，坐下来点一杯滴漏咖啡或是奶香浓郁的拿铁，一边看路人走过，一边品着醇美的咖啡，实属享受。",
        "miniImage": "http://s4.cn.bing.net/th?id=OJ.ElwYRN00gBhE0w&pid=MSNJVFeeds",
        "miniUrl": "https://zhanghao-zhoushan.cn/image/story/s4.OJ.ElwYRN00gBhE0w.png"
      }
    ],
    "primaryImageUrl": "http://hpimges.blob.core.chinacloudapi.cn/coverstory/watermark_hobbiton_zh-cn11259204468_1920x1080.jpg",
    "imageUrl": "https://zhanghao-zhoushan.cn/image/large/XinjiangAltaiMountains_ZH-CN12714378532_1366x768.jpg",
    "downLoadUrl": "https://zhanghao-zhoushan.cn/image/large/XinjiangAltaiMountains_ZH-CN12714378532.jpg",
    "url": "http://cdn.nanxiongnandi.com/bing/XinjiangAltaiMountains_ZH-CN12714378532_1366x768.jpg",
    "name": "XinjiangAltaiMountains_ZH-CN12714378532.jpg",
    "provider": "© imageBROKER/Rex Features",
    "copyright": "[今日秋分] 新疆，阿勒泰，阳光划过晨雾 (© Allensima/Getty Images)(Bing China)",
    "Continent": "",
    "Country": "新西兰",
    "City": "霍比屯",
    "Longitude": "-37.8721273",
    "Latitude": "175.754205"
  },
  {
    "dateString": "20150923",
    "date": 1442966400000,
    "attribute": "新疆，阿勒泰",
    "title": "秋分",
    "story": [
      {
        "title": "天凉好个秋",
        "au": "这是凉爽而欢乐的日子",
        "describe": "雨季结束，天气渐凉，白天与黑夜将此日平分。在这个秋高气爽的时节，农民们开始为一年的收成和来年的耕种而忙碌。辛苦，却不亦乐乎。",
        "miniImage": "http://s1.cn.bing.net/th?id=OJ.DZWR7ujrD9NNHA&pid=MSNJVFeeds",
        "miniUrl": "https://zhanghao-zhoushan.cn/image/story/s1.OJ.DZWR7ujrD9NNHA.png"
      },
      {
        "title": "秋分吃秋菜",
        "au": "饮食习俗",
        "describe": "秋菜是一种野苋菜，在很传统的村落，每到这一天村民们便会去山间亲自摘采。村民们把采到的苋菜带回家，和鱼片一起熬煮成秋汤，鲜美无比，润燥清肠。",
        "miniImage": "http://s.cn.bing.net/th?id=OJ.z6fAGLOe1A7kBw&pid=MSNJVFeeds",
        "miniUrl": "https://zhanghao-zhoushan.cn/image/story/s.OJ.z6fAGLOe1A7kBw.png"
      },
      {
        "title": "为农夫送上祝福",
        "au": "送秋牛",
        "describe": "古时候，每到秋分这天，就会有人在一张红纸上印上农夫耕作的图样并附上全年节气，这就是秋牛图。制作好后，制图人便挨家挨户的去送，每到一家便说一些祝福收成的话，主人听了便可按喜好给送图人一些钱。",
        "miniImage": "http://s4.cn.bing.net/th?id=OJ.AwlKeYbSeVFNDQ&pid=MSNJVFeeds",
        "miniUrl": "https://zhanghao-zhoushan.cn/image/story/s4.OJ.AwlKeYbSeVFNDQ.png"
      }
    ],
    "primaryImageUrl": "http://hpimges.blob.core.chinacloudapi.cn/coverstory/watermark_xinjiangaltaimountains_zh-cn12714378532_1920x1080.jpg",
    "imageUrl": "https://zhanghao-zhoushan.cn/image/large/JaswantThada_ZH-CN12492852271_1366x768.jpg",
    "downLoadUrl": "https://zhanghao-zhoushan.cn/image/large/JaswantThada_ZH-CN12492852271.jpg",
    "url": "http://cdn.nanxiongnandi.com/bing/JaswantThada_ZH-CN12492852271_1366x768.jpg",
    "name": "JaswantThada_ZH-CN12492852271.jpg",
    "provider": "© Allensima/Getty Images",
    "copyright": "印度，拉贾斯坦邦，焦特布尔 (© Lucas Vallecillos/age fotostock)(Bing China)",
    "Continent": "",
    "Country": "中国",
    "City": "阿勒泰",
    "Longitude": "47.0917101",
    "Latitude": "88.3042441"
  },
  {
    "dateString": "20150924",
    "date": 1443052800000,
    "attribute": "印度，焦特布尔",
    "title": "梦幻的蓝色屋子",
    "story": [
      {
        "title": "处处皆宫殿",
        "au": "寻找昔日皇室的足迹",
        "describe": "这里城堡林立，矗立在山丘上，恢弘气势难掩。站在一百多米高的山坡上，一片古老的蓝色房屋映入眼帘，这便是焦特布尔初映像。",
        "miniImage": "http://s.cn.bing.net/th?id=OJ.n2k9Dzrg0X8Sfw&pid=MSNJVFeeds",
        "miniUrl": "https://zhanghao-zhoushan.cn/image/story/s.OJ.n2k9Dzrg0X8Sfw.png"
      },
      {
        "title": "虔诚之邦",
        "au": "宗教圣地",
        "describe": "印度是个宗教圣地，多信奉印度教、佛教，有的也信仰基督教和伊斯兰教，不少人会因此而吃素，尽量避免在信徒面前吃肉饮酒，以示尊重。进入寺庙前也需遵守规则，按照寺庙的要求来着装。",
        "miniImage": "http://s1.cn.bing.net/th?id=OJ.SBJN6s69jK1WrQ&pid=MSNJVFeeds",
        "miniUrl": "https://zhanghao-zhoushan.cn/image/story/s1.OJ.SBJN6s69jK1WrQ.png"
      },
      {
        "title": "印度也有小清新",
        "au": "蓝色之城",
        "describe": "焦特布尔老城的很多老房子外墙都被漆成蓝色，因此又被称为“蓝色之城”。站在120多米高的城堡上俯瞰整座城，会被眼前这片蓝色给迷住。没错，你就是在印度，印度也有这样的浪漫小清新。",
        "miniImage": "http://s.cn.bing.net/th?id=OJ.jtNjJBdPnpmjZA&pid=MSNJVFeeds",
        "miniUrl": "https://zhanghao-zhoushan.cn/image/story/s.OJ.jtNjJBdPnpmjZA.png"
      }
    ],
    "primaryImageUrl": "http://hpimges.blob.core.chinacloudapi.cn/coverstory/watermark_jaswantthada_zh-cn12492852271_1920x1080.jpg",
    "imageUrl": "https://zhanghao-zhoushan.cn/image/large/JapaneseFlyingSquirrel_ZH-CN13057615880_1366x768.jpg",
    "downLoadUrl": "https://zhanghao-zhoushan.cn/image/large/JapaneseFlyingSquirrel_ZH-CN13057615880.jpg",
    "url": "http://cdn.nanxiongnandi.com/bing/JapaneseFlyingSquirrel_ZH-CN13057615880_1366x768.jpg",
    "name": "JapaneseFlyingSquirrel_ZH-CN13057615880.jpg",
    "provider": "© Lucas Vallecillos/age fotostoc",
    "copyright": "日本小鼯鼠 (© Shiroh Yabe/SEBUN PHOTO/amanaimages/Corbis)(Bing China)",
    "Continent": "",
    "Country": "印度",
    "City": "焦特布尔",
    "Longitude": "26.2703528",
    "Latitude": "73.0305433"
  },
  {
    "dateString": "20150925",
    "date": 1443139200000,
    "attribute": "日本",
    "title": "萌萌小鼠",
    "story": [
      {
        "title": "精灵鼠小弟",
        "au": "定会好好照顾你",
        "describe": "不少人对可爱萌物毫无抵抗力，龙猫、仓鼠、刺猬、松鼠什么的都是心头好。现在，又多了一个，那就是日本小鼯鼠。它娇小又可爱，活泼又聪明，关键是，还能飞哦。",
        "miniImage": "http://s1.cn.bing.net/th?id=OJ.GDiDOvW6DP14Cg&pid=MSNJVFeeds",
        "miniUrl": "https://zhanghao-zhoushan.cn/image/story/s1.OJ.GDiDOvW6DP14Cg.png"
      },
      {
        "title": "不同时期有不同需求",
        "au": "喂食贴士",
        "describe": "小鼯鼠最喜欢坚果，既可以当玩具，又可以用来磨牙，还能吃，简直一举三得。而对于妊娠期的鼯鼠们则需要特别的照料，可以喂一些面包、牛奶和饲料，以补充蛋白质和钙。",
        "miniImage": "http://s1.cn.bing.net/th?id=OJ.uy7i9TZaqoz1TQ&pid=MSNJVFeeds",
        "miniUrl": "https://zhanghao-zhoushan.cn/image/story/s1.OJ.uy7i9TZaqoz1TQ.png"
      },
      {
        "title": "舒适最重要",
        "au": "屋舍贴士",
        "describe": "家庭饲养的话可以准备一个小笼子，里面放上一个小鸟用的巢箱，供小飞鼠白天睡觉用。夏季若天气炎热的话，可以加个草席，或适当喷一些水给它消暑。",
        "miniImage": "http://s1.cn.bing.net/th?id=OJ.THN9IkQab0spxA&pid=MSNJVFeeds",
        "miniUrl": "https://zhanghao-zhoushan.cn/image/story/s1.OJ.THN9IkQab0spxA.png"
      }
    ],
    "primaryImageUrl": "http://hpimges.blob.core.chinacloudapi.cn/coverstory/watermark_japaneseflyingsquirrel_zh-cn13057615880_1920x1080.jpg",
    "imageUrl": "https://zhanghao-zhoushan.cn/image/large/BlackwaterFalls_ZH-CN10824353954_1366x768.jpg",
    "downLoadUrl": "https://zhanghao-zhoushan.cn/image/large/BlackwaterFalls_ZH-CN10824353954.jpg",
    "url": "http://cdn.nanxiongnandi.com/bing/BlackwaterFalls_ZH-CN10824353954_1366x768.jpg",
    "name": "BlackwaterFalls_ZH-CN10824353954.jpg",
    "provider": "© Shiroh Yabe/SEBUN PHOTO/amanaimages/Corbis",
    "copyright": "美国，西弗吉尼亚州，位于黑水瀑布州立公园的艾拉卡拉瀑布 (© Randall Sanger/Tandem Stills + Motion)(Bing China)",
    "Continent": "",
    "Country": "",
    "City": "",
    "Longitude": "",
    "Latitude": ""
  },
  {
    "dateString": "20150926",
    "date": 1443225600000,
    "attribute": "美国",
    "title": "西弗吉尼亚",
    "story": [
      {
        "title": "美丽的西弗吉尼亚",
        "au": "看万山红遍，赏层林尽染",
        "describe": "你可以在深山中徒步，尽享大自然的鬼斧神工；还可以走在历史名城中，体会独立自主的美国精神。西弗吉尼亚，一个能让你的旅程丰富多彩的地方。",
        "miniImage": "http://s2.cn.bing.net/th?id=OJ.3vmt9CxIHsmNww&pid=MSNJVFeeds",
        "miniUrl": "https://zhanghao-zhoushan.cn/image/story/s2.OJ.3vmt9CxIHsmNww.png"
      },
      {
        "title": "前总统的艺术大作",
        "au": "蒙蒂塞洛庄园",
        "describe": "这座庄园由前总统托马斯·杰佛逊亲自设计建造，位于一座小山顶上，周围是葱绿的丛林和一湾碧泉，风景独好。白色屋顶和红砖墙体相搭配，再加上周围的碧草、红叶和蓝天，形成一幅色彩斑斓的画面。",
        "miniImage": "http://s1.cn.bing.net/th?id=OJ.p0xJW0OcthkjUg&pid=MSNJVFeeds",
        "miniUrl": "https://zhanghao-zhoushan.cn/image/story/s1.OJ.p0xJW0OcthkjUg.png"
      },
      {
        "title": "山脉之州的标志之花",
        "au": "杜鹃花",
        "describe": "杜鹃花，我们常说的映山红，是西弗吉尼亚州的州花。相传，古有杜鹃鸟，日夜哀鸣而咯血，染红遍山的花朵，因而得名。春天伊始，山间开满杜鹃，杏红、雪青、白色，煞是好看。",
        "miniImage": "http://s3.cn.bing.net/th?id=OJ.YT1nlZpupC3Wmw&pid=MSNJVFeeds",
        "miniUrl": "https://zhanghao-zhoushan.cn/image/story/s3.OJ.YT1nlZpupC3Wmw.png"
      }
    ],
    "primaryImageUrl": "http://hpimges.blob.core.chinacloudapi.cn/coverstory/watermark_blackwaterfalls_zh-cn10824353954_1920x1080.jpg",
    "imageUrl": "https://zhanghao-zhoushan.cn/image/large/StoneBridgeMoonrise_ZH-CN9003736777_1366x768.jpg",
    "downLoadUrl": "https://zhanghao-zhoushan.cn/image/large/StoneBridgeMoonrise_ZH-CN9003736777.jpg",
    "url": "http://cdn.nanxiongnandi.com/bing/StoneBridgeMoonrise_ZH-CN9003736777_1366x768.jpg",
    "name": "StoneBridgeMoonrise_ZH-CN9003736777.jpg",
    "provider": "© Randall Sanger/Tandem Stills + Motion",
    "copyright": "[中秋快乐] 北京，月亮从颐和园的十七拱桥上升起 (© Grant Fant/Getty Images)(Bing China)",
    "Continent": "",
    "Country": "美国",
    "City": " 西弗吉尼亚州",
    "Longitude": "38.9201705",
    "Latitude": "-80.1816905"
  },
  {
    "dateString": "20150927",
    "date": 1443312000000,
    "attribute": "北京，颐和园",
    "title": "团圆之夜",
    "story": [
      {
        "title": "中秋佳节",
        "au": "好时光 不可虚度",
        "describe": "中秋，是一个与家人团圆的日子。在这花好月圆之夜，能与家人团聚，是再幸福不过的事。若无法如愿，也不必让良辰美景虚度，美食和美酒也能慰藉你的心。",
        "miniImage": "http://s3.cn.bing.net/th?id=OJ.R1crm0G8YcJKBA&pid=MSNJVFeeds",
        "miniUrl": "https://zhanghao-zhoushan.cn/image/story/s3.OJ.R1crm0G8YcJKBA.png"
      },
      {
        "title": "宫廷中的美酒佳肴",
        "au": "中秋宴食",
        "describe": "清朝时期，在宫中一般会找一个空旷的院子，在向东的地方摆上一个屏风。屏风前则是一张八仙桌，一个浑圆巨大的月饼便放在桌子的正中央，周围摆满了糕点和瓜果。祭月过后，大家便可大啖这一桌的美食了。",
        "miniImage": "http://s3.cn.bing.net/th?id=OJ.jVoO0F39J8hfJw&pid=MSNJVFeeds",
        "miniUrl": "https://zhanghao-zhoushan.cn/image/story/s3.OJ.jVoO0F39J8hfJw.png"
      },
      {
        "title": "善男信女来相会",
        "au": "猜灯谜",
        "describe": "猜灯谜也是古时候中秋的一大习俗，月圆之夜，公共场所会挂着许多灯笼，人们都聚集在此猜灯笼上写着的谜语。由于来猜灯谜的大多是年轻的男女，因此慢慢演变成了古时候的“相亲会”。",
        "miniImage": "http://s2.cn.bing.net/th?id=OJ.egeRBy094g0Drg&pid=MSNJVFeeds",
        "miniUrl": "https://zhanghao-zhoushan.cn/image/story/s2.OJ.egeRBy094g0Drg.png"
      }
    ],
    "primaryImageUrl": "http://hpimges.blob.core.chinacloudapi.cn/coverstory/watermark_stonebridgemoonrise_zh-cn9003736777_1920x1080.jpg",
    "imageUrl": "https://zhanghao-zhoushan.cn/image/large/MaunaKea_ZH-CN11895121205_1366x768.jpg",
    "downLoadUrl": "https://zhanghao-zhoushan.cn/image/large/MaunaKea_ZH-CN11895121205.jpg",
    "url": "http://cdn.nanxiongnandi.com/bing/MaunaKea_ZH-CN11895121205_1366x768.jpg",
    "name": "MaunaKea_ZH-CN11895121205.jpg",
    "provider": "© Grant Fant/Getty Images",
    "copyright": "通往夏威夷大岛，冒纳凯阿火山的公路 (© Gary S. Chapman/Shutterstock)(Bing China)",
    "Continent": "",
    "Country": "中国",
    "City": "北京",
    "Longitude": "39.9388838",
    "Latitude": "116.3974589"
  },
  {
    "dateString": "20150928",
    "date": 1443398400000,
    "attribute": "美国，夏威夷",
    "title": "热情之岛",
    "story": [
      {
        "title": "太平洋上的十字路口",
        "au": "风情万种的迷人岛屿",
        "describe": "位于太平洋的十字路口，这个由火山爆发而形成的群岛一直吸引着世界各地的游客。热情的草裙舞、独特的文化、美味的食物，还有那些唯美浪漫的海滩，这一切都让人心驰神往。",
        "miniImage": "http://s4.cn.bing.net/th?id=OJ.Q0X0kCNZHXUT6Q&pid=MSNJVFeeds",
        "miniUrl": "https://zhanghao-zhoushan.cn/image/story/s4.OJ.Q0X0kCNZHXUT6Q.png"
      },
      {
        "title": "东西南北相互交织",
        "au": "夏威夷文化",
        "describe": "夏威夷文化是东西方文化与南北半球文明相互交织的产物，于是被称为“世界十字路口的文化”。由波利尼西亚、新西兰、斐济、夏威夷、玛贵斯、大溪地和汤加文化组成，丰富多彩，包容性强。",
        "miniImage": "http://s.cn.bing.net/th?id=OJ.SIJp3DwGhO0Ixg&pid=MSNJVFeeds",
        "miniUrl": "https://zhanghao-zhoushan.cn/image/story/s.OJ.SIJp3DwGhO0Ixg.png"
      },
      {
        "title": "奔放又欢快",
        "au": "草裙舞",
        "describe": "草裙舞又名呼啦舞，注重手脚和腰部动作。舞者们挂着花环穿着金色草裙，配合着欢快的音乐纷纷起舞。坐在沙滩上凉风习习的椰林中，享受一场夏威夷草裙舞，度过一个难忘的晚夜。",
        "miniImage": "http://s2.cn.bing.net/th?id=OJ.jkNHEuX0lts9Dw&pid=MSNJVFeeds",
        "miniUrl": "https://zhanghao-zhoushan.cn/image/story/s2.OJ.jkNHEuX0lts9Dw.png"
      }
    ],
    "primaryImageUrl": "http://hpimges.blob.core.chinacloudapi.cn/coverstory/watermark_maunakea_zh-cn11895121205_1920x1080.jpg",
    "imageUrl": "https://zhanghao-zhoushan.cn/image/large/RoverSelfie_ZH-CN6914958241_1366x768.jpg",
    "downLoadUrl": "https://zhanghao-zhoushan.cn/image/large/RoverSelfie_ZH-CN6914958241.jpg",
    "url": "http://cdn.nanxiongnandi.com/bing/RoverSelfie_ZH-CN6914958241_1366x768.jpg",
    "name": "RoverSelfie_ZH-CN6914958241.jpg",
    "provider": "© Gary S. Chapman/Shutterstock",
    "copyright": "NASA好奇号火星探测器 (© NASA/JPL-Caltech/MSSS)(Bing China)",
    "Continent": "",
    "Country": "美国",
    "City": "夏威夷",
    "Longitude": "20.46",
    "Latitude": "-157.505"
  },
  {
    "dateString": "20150929",
    "date": 1443484800000,
    "attribute": "NASA好奇号火星探测器",
    "title": "火星上的来客",
    "story": [
      {
        "title": "有哪些发现？",
        "au": "生命的迹象",
        "describe": "对于地球以外的星球，普通人难以触及，因此更有好奇心去探索个究竟。2011年11月，一架名为好奇号的探测器登陆火星，为人类发掘火星的奥秘。",
        "miniImage": "http://s1.cn.bing.net/th?id=OJ.d40jbmU0hfcY1w&pid=MSNJVFeeds",
        "miniUrl": "https://zhanghao-zhoushan.cn/image/story/s1.OJ.d40jbmU0hfcY1w.png"
      },
      {
        "title": "主要成像工具",
        "au": "桅杆相机",
        "describe": "地面科学家们收到的彩色图片和视频都是由桅杆相机拍摄的，这是让我们认识火星的重要工具。相机被安装在一根立在探测器上的桅杆上，当探测器在火星表面行走时，地面的工作人员则根据相机传递过来的图像和视频来更好的操控“好奇”号。",
        "miniImage": "http://s3.cn.bing.net/th?id=OJ.yNcoqi072VBZ7w&pid=MSNJVFeeds",
        "miniUrl": "https://zhanghao-zhoushan.cn/image/story/s3.OJ.yNcoqi072VBZ7w.png"
      },
      {
        "title": "探测车的“心脏”",
        "au": "火星样本分析仪",
        "describe": "分析仪由三个独立仪器构成，分别为质谱仪、气相色谱仪和激光分光计。这三个仪器主要用来搜寻构成生命的要素碳化合物，以及探测一切与地球上生命有关的其它元素，因此可以说是“好奇”号的“心脏”。",
        "miniImage": "http://s.cn.bing.net/th?id=OJ.DhYGZPYJy2SsJg&pid=MSNJVFeeds",
        "miniUrl": "https://zhanghao-zhoushan.cn/image/story/s.OJ.DhYGZPYJy2SsJg.png"
      }
    ],
    "primaryImageUrl": "http://hpimges.blob.core.chinacloudapi.cn/coverstory/watermark_roverselfie_zh-cn6914958241_1920x1080.jpg",
    "imageUrl": "https://zhanghao-zhoushan.cn/image/large/HooverBday_ZH-CN9980812747_1366x768.jpg",
    "downLoadUrl": "https://zhanghao-zhoushan.cn/image/large/HooverBday_ZH-CN9980812747.jpg",
    "url": "http://cdn.nanxiongnandi.com/bing/HooverBday_ZH-CN9980812747_1366x768.jpg",
    "name": "HooverBday_ZH-CN9980812747.jpg",
    "provider": "© NASA/JPL-Caltech/MSSS",
    "copyright": "美国，亚利桑那州和内华达州边界上的胡佛水坝 (© George Steinmetz/Corbis)(Bing China)",
    "Continent": "",
    "Country": "",
    "City": "",
    "Longitude": "",
    "Latitude": ""
  },
  {
    "dateString": "20150930",
    "date": 1443571200000,
    "attribute": "美国，亚利桑那州",
    "title": "胡佛水坝",
    "story": [
      {
        "title": "让人骄傲的大坝",
        "au": "既是奇迹 也创造了奇迹",
        "describe": "在亚利桑那州和内华达州交接处，胡佛水坝如同巨龙一般卧在沙漠坚硬的岩石之上。曾经湍急的科罗拉多河来到这里后却像一头被驯服的野兽，缓缓而行。",
        "miniImage": "http://s2.cn.bing.net/th?id=OJ.8bMXM8leSQn0tg&pid=MSNJVFeeds",
        "miniUrl": "https://zhanghao-zhoushan.cn/image/story/s2.OJ.8bMXM8leSQn0tg.png"
      },
      {
        "title": "拉斯维加斯的兴起",
        "au": "历史贡献",
        "describe": "没错，正是因为胡佛水坝的修建，才有了拉斯维加斯这个城市。这里原本只是一片荒无人烟的沙漠，建造水坝时，大批工人在此休息，并以赌博来解闷。因修建水坝而出现的水、电和铁路也为城市的兴起创造了条件。后来内华达州政府为了吸引人气，将赌博合法化，吸引了许多资本家前来修建赌场。一个光怪陆离的拉斯维加斯就这样出现了。",
        "miniImage": "http://s4.cn.bing.net/th?id=OJ.oDFd0P4rORNNzQ&pid=MSNJVFeeds",
        "miniUrl": "https://zhanghao-zhoushan.cn/image/story/s4.OJ.oDFd0P4rORNNzQ.png"
      },
      {
        "title": "如此壮观景致难得一见",
        "au": "旅游观光",
        "describe": "在大坝的顶部将壮观景致尽收眼底，之后乘电梯到达底部，去到上世纪30年代风格的建筑里一览那些由美洲土著设计的风格独特的图案地板，然后再去到拥有17台水力发电机的发电厂房参观，之后还可以前往陈列馆去了解大坝的创建历史，感叹设计师和工人们为此所付出的一切。",
        "miniImage": "http://s2.cn.bing.net/th?id=OJ.ZvBzHifZKye4BA&pid=MSNJVFeeds",
        "miniUrl": "https://zhanghao-zhoushan.cn/image/story/s2.OJ.ZvBzHifZKye4BA.png"
      }
    ],
    "primaryImageUrl": "http://hpimges.blob.core.chinacloudapi.cn/coverstory/watermark_hooverbday_zh-cn9980812747_1920x1080.jpg",
    "imageUrl": "",
    "downLoadUrl": "",
    "provider": "© George Steinmetz/Corbis",
    "Continent": "",
    "Country": "美国",
    "City": "亚利桑那州",
    "Longitude": "34.1682185",
    "Latitude": "-111.930907"
  }
]