[
  {
    "dateString": "20151201",
    "date": 1448928000000,
    "attribute": "日本，金泽市",
    "title": "兼六园",
    "story": [
      {
        "title": "迷人古城",
        "au": "历史的魅力",
        "describe": "这里有池塘、瀑布、喷泉和溪流，有青松、樱花、梅花等植被，更有古朴精致的亭、台、楼、阁。这里就是位于日本金泽市的兼六园。",
        "miniImage": "http://s4.cn.bing.net/th?id=OJ.xhZ0JbYcDlLw5A&pid=MSNJVFeeds",
        "miniUrl": "https://zhanghao-zhoushan.cn/image/story/s4.OJ.xhZ0JbYcDlLw5A.png"
      },
      {
        "title": "来自宋代诗词",
        "au": "兼六园名字由来",
        "describe": "“兼六园”取自中国宋代诗人李格非的《洛阳名园记》。当时幕府的老中松平定信认为它具有李格非提出的宏大、幽邃、人力、苍古、水泉、和眺望的条件，因此取名为兼六园。",
        "miniImage": "http://s4.cn.bing.net/th?id=OJ.sqW31gzHnIxSSQ&pid=MSNJVFeeds",
        "miniUrl": "https://zhanghao-zhoushan.cn/image/story/s4.OJ.sqW31gzHnIxSSQ.png"
      },
      {
        "title": "四季皆景",
        "au": "兼六园的景观",
        "describe": "如此久负盛名的园林中，自然不乏精美的亭、台、楼、阁，此外，更有全日本最古老的喷泉，和上万种美丽植物。这里四季都有美丽的景色，让人沉醉不已。",
        "miniImage": "http://s3.cn.bing.net/th?id=OJ.NGsYWOs04O4bag&pid=MSNJVFeeds",
        "miniUrl": "https://zhanghao-zhoushan.cn/image/story/s3.OJ.NGsYWOs04O4bag.png"
      }
    ],
    "primaryImageUrl": "http://hpimges.blob.core.chinacloudapi.cn/coverstory/watermark_kenrokuengarden_zh-cn11375106351_1920x1080.jpg",
    "imageUrl": "https://zhanghao-zhoushan.cn/image/large/BearGlacierLake_ZH-CN11648553737_1366x768.jpg",
    "downLoadUrl": "https://zhanghao-zhoushan.cn/image/large/BearGlacierLake_ZH-CN11648553737.jpg",
    "url": "http://cdn.nanxiongnandi.com/bing/BearGlacierLake_ZH-CN11648553737_1366x768.jpg",
    "name": "BearGlacierLake_ZH-CN11648553737.jpg",
    "provider": "© JTB Media Creation, Inc./Alamy",
    "copyright": "美国，阿拉斯加，基奈峡湾国家公园的熊冰川湖 (© Michael DeYoung/age fotostock)(Bing China)",
    "Continent": "",
    "Country": "日本",
    "City": "兼六园",
    "Longitude": "136.6604628",
    "Latitude": "36.5621321"
  },
  {
    "dateString": "20151202",
    "date": 1449014400000,
    "attribute": "美国，阿拉斯加",
    "title": "迷人的基奈湾国家公园",
    "story": [
      {
        "title": "冰城雪原",
        "au": "走进童话世界",
        "describe": "这是一个纯净洁白的世界。皑皑冰川高耸，澄澈湖泊静谧安详，岸边的动物活泼好动，冰天雪地中仍然充满勃勃生机。",
        "miniImage": "http://s1.cn.bing.net/th?id=OJ.QNjRq1HkcjC5xw&pid=MSNJVFeeds",
        "miniUrl": "https://zhanghao-zhoushan.cn/image/story/s1.OJ.QNjRq1HkcjC5xw.png"
      },
      {
        "title": "世界上最棒的火车",
        "au": "北极特快",
        "describe": "乘坐北极特快迪纳利之星列车，驰骋在阿拉斯加的冰川雪原之上，领略山水之间的绝美景色，享受180度阿拉斯加原始风光。冰雪世界的奇幻之旅由此展开。",
        "miniImage": "http://s1.cn.bing.net/th?id=OJ.dGSZGNU1jringA&pid=MSNJVFeeds",
        "miniUrl": "https://zhanghao-zhoushan.cn/image/story/s1.OJ.dGSZGNU1jringA.png"
      },
      {
        "title": "纯正阿拉斯加风情",
        "au": "狗拉雪橇之旅",
        "describe": "阿拉斯加的狗拉雪橇已有上百年历史，一直到现在都是最具当地风情的项目。坐在雪橇上，可爱的雪橇犬将带领你近距离探索这片神秘雪原。",
        "miniImage": "http://s1.cn.bing.net/th?id=OJ.8qo2ljLN8truow&pid=MSNJVFeeds",
        "miniUrl": "https://zhanghao-zhoushan.cn/image/story/s1.OJ.8qo2ljLN8truow.png"
      }
    ],
    "primaryImageUrl": "http://hpimges.blob.core.chinacloudapi.cn/coverstory/watermark_bearglacierlake_zh-cn11648553737_1920x1080.jpg",
    "imageUrl": "https://zhanghao-zhoushan.cn/image/large/OverlandPark_ZH-CN7518447869_1366x768.jpg",
    "downLoadUrl": "https://zhanghao-zhoushan.cn/image/large/OverlandPark_ZH-CN7518447869.jpg",
    "url": "http://cdn.nanxiongnandi.com/bing/OverlandPark_ZH-CN7518447869_1366x768.jpg",
    "name": "OverlandPark_ZH-CN7518447869.jpg",
    "provider": "© Michael DeYoung/age fotostock",
    "copyright": "美国，堪萨斯州，欧弗兰帕克，燎原火博物馆 (© Derek Siagle/Getty Images)(Bing China)",
    "Continent": "",
    "Country": "美国",
    "City": "基奈峡湾国家公园",
    "Longitude": "-149.8185531",
    "Latitude": "60.0437791"
  },
  {
    "dateString": "20151203",
    "date": 1449100800000,
    "attribute": "美国，堪萨斯州",
    "title": "美国西部风情",
    "story": [
      {
        "title": "堪萨斯州",
        "au": "充满传奇色彩的地方",
        "describe": "这里不缺历史，更不缺故事。堪萨斯州，向世人展现着经典美国的风貌，深入人心的牛仔文化和一望无际的宽阔草原都让人们不禁心向往之。",
        "miniImage": "http://s.cn.bing.net/th?id=OJ.GYzX09bpKAnqWQ&pid=MSNJVFeeds",
        "miniUrl": "https://zhanghao-zhoushan.cn/image/story/s.OJ.GYzX09bpKAnqWQ.png"
      },
      {
        "title": "沧海变桑田",
        "au": "国家高草草原自然保护区",
        "describe": "用沧海桑田来形容这座横跨了三个州的大草原一点也不为过。这里曾是一片汪洋大海后，后来由于板块运动使得该地区抬升，于是便有了如今的高草草原。这里没有经过农耕的洗礼，因此仍保持着最为原始的状态。",
        "miniImage": "http://s2.cn.bing.net/th?id=OJ.7cofd7jB8bNgRw&pid=MSNJVFeeds",
        "miniUrl": "https://zhanghao-zhoushan.cn/image/story/s2.OJ.7cofd7jB8bNgRw.png"
      },
      {
        "title": "充满故事的地方",
        "au": "伊甸园",
        "describe": "恩斯莫尔是一位退休老兵，在他64岁之时建立了这座充满传奇色彩的伊甸园。屋里的每一个元素都充满故事，从自由女神、地痞流氓到社会贪污者，在这里，将世间百态都看尽。",
        "miniImage": "http://s2.cn.bing.net/th?id=OJ.awSw0V85jdEpZA&pid=MSNJVFeeds",
        "miniUrl": "https://zhanghao-zhoushan.cn/image/story/s2.OJ.awSw0V85jdEpZA.png"
      }
    ],
    "primaryImageUrl": "http://hpimges.blob.core.chinacloudapi.cn/coverstory/watermark_overlandpark_zh-cn7518447869_1920x1080.jpg",
    "imageUrl": "https://zhanghao-zhoushan.cn/image/large/IngolfshofdiBlackSand_ZH-CN9362134214_1366x768.jpg",
    "downLoadUrl": "https://zhanghao-zhoushan.cn/image/large/IngolfshofdiBlackSand_ZH-CN9362134214.jpg",
    "url": "http://cdn.nanxiongnandi.com/bing/IngolfshofdiBlackSand_ZH-CN9362134214_1366x768.jpg",
    "name": "IngolfshofdiBlackSand_ZH-CN9362134214.jpg",
    "provider": "© Derek Siagle/Getty Images",
    "copyright": "冰岛， 因戈尔夫海岬的黑沙滩 (© Nigel Hicks/Getty Images)(Bing China)",
    "Continent": "",
    "Country": "美国",
    "City": "欧弗兰帕克",
    "Longitude": "-94.8244439",
    "Latitude": "38.9168474"
  },
  {
    "dateString": "20151204",
    "date": 1449187200000,
    "attribute": "冰岛， 因戈尔夫海岬",
    "title": "神秘与美",
    "story": [
      {
        "title": "个性十足的海滩",
        "au": "永恒的美",
        "describe": "沙滩，总给人以洁白、浪漫的印象。让人想不到的是，在冰岛的小镇维克边上，竟有一片乌黑的沙滩，每当白色浪花拍打在沙滩上时，对比鲜明的颜色让人印象深刻。",
        "miniImage": "http://s3.cn.bing.net/th?id=OJ.Td6tfeOqbhME4A&pid=MSNJVFeeds",
        "miniUrl": "https://zhanghao-zhoushan.cn/image/story/s3.OJ.Td6tfeOqbhME4A.png"
      },
      {
        "title": "大自然的杰作",
        "au": "黑沙滩",
        "describe": "在8万年前的一次火山大喷发中，形成了大量的黑色沙砾，经过海风和海浪长年的侵蚀，便有了眼前这个壮观的黑色沙滩。",
        "miniImage": "http://s.cn.bing.net/th?id=OJ.SjFtRF0SI3rqEA&pid=MSNJVFeeds",
        "miniUrl": "https://zhanghao-zhoushan.cn/image/story/s.OJ.SjFtRF0SI3rqEA.png"
      },
      {
        "title": "风景如画",
        "au": "维克小镇",
        "describe": "一旁是浩瀚的汪洋大海，另一旁则是绿草葱葱的小镇。小镇旁的风琴岩壁上悬挂着一条条天然形成的石柱，没有矫揉造作的姿态，只有大自然赋予的那一抹迷人、厚重的色彩。",
        "miniImage": "http://s2.cn.bing.net/th?id=OJ.zP0CyrgqXxijMw&pid=MSNJVFeeds",
        "miniUrl": "https://zhanghao-zhoushan.cn/image/story/s2.OJ.zP0CyrgqXxijMw.png"
      }
    ],
    "primaryImageUrl": "http://hpimges.blob.core.chinacloudapi.cn/coverstory/watermark_ingolfshofdiblacksand_zh-cn9362134214_1920x1080.jpg",
    "imageUrl": "https://zhanghao-zhoushan.cn/image/large/GeladaBaboons_ZH-CN11015062372_1366x768.jpg",
    "downLoadUrl": "https://zhanghao-zhoushan.cn/image/large/GeladaBaboons_ZH-CN11015062372.jpg",
    "url": "http://cdn.nanxiongnandi.com/bing/GeladaBaboons_ZH-CN11015062372_1366x768.jpg",
    "name": "GeladaBaboons_ZH-CN11015062372.jpg",
    "provider": "© Nigel Hicks/Getty Images",
    "copyright": "静坐着的狮尾狒 (© Pavel Blažek/500px)(Bing China)",
    "Continent": "",
    "Country": "冰岛",
    "City": "因戈尔夫海岬",
    "Longitude": "-17.7636913",
    "Latitude": "63.7938712"
  },
  {
    "dateString": "20151205",
    "date": 1449273600000,
    "attribute": "静坐着的狮尾狒",
    "title": "林中精灵",
    "story": [
      {
        "title": "埃塞俄比亚",
        "au": "人杰地灵之地",
        "describe": "壮硕的身体上有着长长的毛发，胸脯是艳丽的红色，尾部那长长的毛簇让它多了几分狮子的气质，狮尾狒便由此得名。这种狒狒是埃塞俄比亚的特有物种，埃塞俄比亚林中的精灵。",
        "miniImage": "http://s1.cn.bing.net/th?id=OJ.FIqrLWSnNCpXfg&pid=MSNJVFeeds",
        "miniUrl": "https://zhanghao-zhoushan.cn/image/story/s1.OJ.FIqrLWSnNCpXfg.png"
      },
      {
        "title": "非洲精灵",
        "au": "狮尾狒",
        "describe": "狮尾狒是埃塞俄比亚特有的品种，它尾巴上有一撮毛簇，很象狮子尾巴，因此便有了狮尾狒这个名字。它们头上毛发浓密且长，嘴里有着尖而长的獠牙，活泼好动，是埃塞俄比亚森林中的精灵。",
        "miniImage": "http://s1.cn.bing.net/th?id=OJ.050rKzImXHEt1w&pid=MSNJVFeeds",
        "miniUrl": "https://zhanghao-zhoushan.cn/image/story/s1.OJ.050rKzImXHEt1w.png"
      },
      {
        "title": "一个人杰地灵的地方",
        "au": "美人国",
        "describe": "这个有着3000多年历史的东非国家，除了有迷人的古文明，更是一个美女辈出的地方。她们大都能歌善舞，言谈大方，举止得体，与这个地方深厚的文化底蕴是分不开的。",
        "miniImage": "http://s.cn.bing.net/th?id=OJ.VVFEpdXeIBNk9A&pid=MSNJVFeeds",
        "miniUrl": "https://zhanghao-zhoushan.cn/image/story/s.OJ.VVFEpdXeIBNk9A.png"
      }
    ],
    "primaryImageUrl": "http://hpimges.blob.core.chinacloudapi.cn/coverstory/watermark_geladababoons_zh-cn11015062372_1920x1080.jpg",
    "imageUrl": "https://zhanghao-zhoushan.cn/image/large/NamibiaQuiverTree_ZH-CN8681522145_1366x768.jpg",
    "downLoadUrl": "https://zhanghao-zhoushan.cn/image/large/NamibiaQuiverTree_ZH-CN8681522145.jpg",
    "url": "http://cdn.nanxiongnandi.com/bing/NamibiaQuiverTree_ZH-CN8681522145_1366x768.jpg",
    "name": "NamibiaQuiverTree_ZH-CN8681522145.jpg",
    "provider": "©Pavel Blažek/500px",
    "copyright": "纳米比亚，基特曼斯胡普附近的箭袋树森林 (© Barry Lewis/Corbis)(Bing China)",
    "Continent": "",
    "Country": "",
    "City": "",
    "Longitude": "",
    "Latitude": ""
  },
  {
    "dateString": "20151206",
    "date": 1449360000000,
    "attribute": "纳米比亚，基特曼斯胡普附近",
    "title": "箭袋树森林",
    "story": [
      {
        "title": "迷人之境",
        "au": "充满野性美的国度",
        "describe": "在浩瀚的沙漠上，璀璨的星空下，苍劲有力的箭袋树如同少兵一般坚韧地挺拔着。它们的姿态曲折而鬼魅，坚韧又妖娆，富有迷人的吸引力。",
        "miniImage": "http://s.cn.bing.net/th?id=OJ.kkQEo4NfSEgeXQ&pid=MSNJVFeeds",
        "miniUrl": "https://zhanghao-zhoushan.cn/image/story/s.OJ.kkQEo4NfSEgeXQ.png"
      },
      {
        "title": "即将消失的原始族群",
        "au": "辛巴族",
        "describe": "辛巴族是在非洲大地上最后一群保持着原生态生活方式的族群。为了不被现代闻名所影响，他们退守丛林，居住在纳米比亚最边远的大自然中。他们至今保持着500多年前的生活方式，成为当地一道非常独特的风景。",
        "miniImage": "http://s.cn.bing.net/th?id=OJ.FV7F5evUTkXYHg&pid=MSNJVFeeds",
        "miniUrl": "https://zhanghao-zhoushan.cn/image/story/s.OJ.FV7F5evUTkXYHg.png"
      },
      {
        "title": "辛巴族的独特传统",
        "au": "一夫多妻制",
        "describe": "因为当地水质和食物的原因，很多男孩都活不过15岁，因此男女比例严重失调。为了保证人口的繁衍，辛巴族的男子一般都会娶三、四个妻子，但仍然面临着人口骤减的现状。",
        "miniImage": "http://s2.cn.bing.net/th?id=OJ.k5BqawwsMieRPQ&pid=MSNJVFeeds",
        "miniUrl": "https://zhanghao-zhoushan.cn/image/story/s2.OJ.k5BqawwsMieRPQ.png"
      }
    ],
    "primaryImageUrl": "http://hpimges.blob.core.chinacloudapi.cn/coverstory/watermark_namibiaquivertree_zh-cn8681522145_1920x1080.jpg",
    "imageUrl": "https://zhanghao-zhoushan.cn/image/large/MourningDoves_ZH-CN10786728372_1366x768.jpg",
    "downLoadUrl": "https://zhanghao-zhoushan.cn/image/large/MourningDoves_ZH-CN10786728372.jpg",
    "url": "http://cdn.nanxiongnandi.com/bing/MourningDoves_ZH-CN10786728372_1366x768.jpg",
    "name": "MourningDoves_ZH-CN10786728372.jpg",
    "provider": "© Barry Lewis/Corbis",
    "copyright": "[今日大雪] 加拿大，新斯科舍省，贝尔河附近的哀鸽 (© Scott Leslie/Minden Pictures)(Bing China)",
    "Continent": "",
    "Country": "纳米比亚",
    "City": "基特曼斯胡",
    "Longitude": "18.1003184",
    "Latitude": "-26.5653342"
  },
  {
    "dateString": "20151207",
    "date": 1449446400000,
    "attribute": "[今日大雪] 加拿大，新斯科舍省",
    "title": "轻盈敏捷的哀鸽",
    "story": [
      {
        "title": "如画的风景",
        "au": "让时间静止",
        "describe": "羽毛光滑亮洁，身体小巧轻盈。栖息在贝尔河畔的哀鸽们时不时扑闪着矫健的翅膀，迎风飞翔。那画面唯美而富有感染力，让人过目不忘。",
        "miniImage": "http://s3.cn.bing.net/th?id=OJ.yxAC8wRSEnFNww&pid=MSNJVFeeds",
        "miniUrl": "https://zhanghao-zhoushan.cn/image/story/s3.OJ.yxAC8wRSEnFNww.png"
      },
      {
        "title": "佳酿产于此",
        "au": "哈利法克斯",
        "describe": "若你是一位啤酒控，那一定要去哈利法克斯探一探。宜人的气候使它成为一个美酒佳酿的制造地，有口皆碑的啤酒AlexanderKeith就是产自这里。",
        "miniImage": "http://s3.cn.bing.net/th?id=OJ.jPBDioYgMU4f2Q&pid=MSNJVFeeds",
        "miniUrl": "https://zhanghao-zhoushan.cn/image/story/s3.OJ.jPBDioYgMU4f2Q.png"
      },
      {
        "title": "五湖四海成一家",
        "au": "移民之省",
        "describe": "新斯科舍是一个移民省份，居住着来自世界各地的人们。居民们大多来自德国、荷兰、波兰和意大利等，多元的文化聚集于此，使这里变得更加迷人、可爱。",
        "miniImage": "http://s2.cn.bing.net/th?id=OJ.Cj7sBGHYTSxW0g&pid=MSNJVFeeds",
        "miniUrl": "https://zhanghao-zhoushan.cn/image/story/s2.OJ.Cj7sBGHYTSxW0g.png"
      }
    ],
    "primaryImageUrl": "http://hpimges.blob.core.chinacloudapi.cn/coverstory/watermark_mourningdoves_zh-cn10786728372_1920x1080.jpg",
    "imageUrl": "https://zhanghao-zhoushan.cn/image/large/GalapagosSealion_ZH-CN11031087950_1366x768.jpg",
    "downLoadUrl": "https://zhanghao-zhoushan.cn/image/large/GalapagosSealion_ZH-CN11031087950.jpg",
    "url": "http://cdn.nanxiongnandi.com/bing/GalapagosSealion_ZH-CN11031087950_1366x768.jpg",
    "name": "GalapagosSealion_ZH-CN11031087950.jpg",
    "provider": "© Scott Leslie/Minden Pictures",
    "copyright": "厄瓜多尔，加拉帕戈群岛，海狮游过鱼群 (© David Fleetham/Visuals Unlimited, Inc.)(Bing China)",
    "Continent": "",
    "Country": "",
    "City": "",
    "Longitude": "",
    "Latitude": ""
  },
  {
    "dateString": "20151208",
    "date": 1449532800000,
    "attribute": "厄瓜多尔，加拉帕戈群岛",
    "title": "潜水胜地",
    "story": [
      {
        "title": "迷人加拉帕戈",
        "au": "与众萌物们亲密接触",
        "describe": "天高云低，空气清新。浩瀚的大海澄澈无比，海水晶莹剔透，是个潜水胜地。当在深海中畅游时，鱼群和海龟从身边游过，让人欣喜不已。",
        "miniImage": "http://s1.cn.bing.net/th?id=OJ.QMoapG2HV0R9sw&pid=MSNJVFeeds",
        "miniUrl": "https://zhanghao-zhoushan.cn/image/story/s1.OJ.QMoapG2HV0R9sw.png"
      },
      {
        "title": "清新味美",
        "au": "柠檬烧虾",
        "describe": "柠檬烧虾是公认的厄瓜多尔美食代表。弹牙的虾肉和清新的柠檬放在一起，非常搭。味美清甜，让人吃了便无法忘怀。",
        "miniImage": "http://s3.cn.bing.net/th?id=OJ.cLP7o5Wa03k7Ug&pid=MSNJVFeeds",
        "miniUrl": "https://zhanghao-zhoushan.cn/image/story/s3.OJ.cLP7o5Wa03k7Ug.png"
      },
      {
        "title": "腊汁肉块",
        "au": "岛上美食",
        "describe": "通常情况下，当地人会把一块大约五公斤的肉块做成腊汁肉，可以储存较长时间。慢慢享用，不用担心会变质。",
        "miniImage": "http://s4.cn.bing.net/th?id=OJ.9n1ULXJirxtycQ&pid=MSNJVFeeds",
        "miniUrl": "https://zhanghao-zhoushan.cn/image/story/s4.OJ.9n1ULXJirxtycQ.png"
      }
    ],
    "primaryImageUrl": "http://hpimges.blob.core.chinacloudapi.cn/coverstory/watermark_galapagossealion_zh-cn11031087950_1920x1080.jpg",
    "imageUrl": "https://zhanghao-zhoushan.cn/image/large/GoatIslandLighthouse_ZH-CN9812058165_1366x768.jpg",
    "downLoadUrl": "https://zhanghao-zhoushan.cn/image/large/GoatIslandLighthouse_ZH-CN9812058165.jpg",
    "url": "http://cdn.nanxiongnandi.com/bing/GoatIslandLighthouse_ZH-CN9812058165_1366x768.jpg",
    "name": "GoatIslandLighthouse_ZH-CN9812058165.jpg",
    "provider": "© David Fleetham/Visuals Unlimited, Inc.",
    "copyright": "美国，罗得岛州，克莱本佩尔新港桥和纽波特港口之光 (© Denis Tangney Jr./Getty Images)(Bing China)",
    "Continent": "",
    "Country": "",
    "City": "",
    "Longitude": "",
    "Latitude": ""
  },
  {
    "dateString": "20151209",
    "date": 1449619200000,
    "attribute": "美国，罗得岛州",
    "title": "纽波特",
    "story": [
      {
        "title": "罗得岛州",
        "au": "感受历史的迷人魅力",
        "describe": "蜿蜒的海岸线幽远绵长，浩瀚的大海涛声阵阵。除了唯美的自然景致，更有历经千年、豪华又雅致的建筑，让这个地方更加可爱迷人。",
        "miniImage": "http://s4.cn.bing.net/th?id=OJ.DLAUF0pEx6Ny8w&pid=MSNJVFeeds",
        "miniUrl": "https://zhanghao-zhoushan.cn/image/story/s4.OJ.DLAUF0pEx6Ny8w.png"
      },
      {
        "title": "美国时尚最奢华别墅",
        "au": "大理石别墅",
        "describe": "这座别墅名副其实，内外均由大理石制造，共五十个房间，耗资一千一百万美元，曾被誉为美国史上最奢华的别墅。",
        "miniImage": "http://s2.cn.bing.net/th?id=OJ.Efwa7okxMvKB8w&pid=MSNJVFeeds",
        "miniUrl": "https://zhanghao-zhoushan.cn/image/story/s2.OJ.Efwa7okxMvKB8w.png"
      },
      {
        "title": "维多利亚风",
        "au": "素梅城堡",
        "describe": "这栋维多利亚式的建筑每一个细节都很迷人。家具、壁纸、甚至屋内的陶瓷装饰，每一处细节都将那个年代的富丽堂皇展现得淋漓尽致。到此参观，一定会让人不虚此行。",
        "miniImage": "http://s.cn.bing.net/th?id=OJ.lzK1YG7JTpDI0A&pid=MSNJVFeeds",
        "miniUrl": "https://zhanghao-zhoushan.cn/image/story/s.OJ.lzK1YG7JTpDI0A.png"
      }
    ],
    "primaryImageUrl": "http://hpimges.blob.core.chinacloudapi.cn/coverstory/watermark_goatislandlighthouse_zh-cn9812058165_1920x1080.jpg",
    "imageUrl": "https://zhanghao-zhoushan.cn/image/large/PalmTreePantanal_ZH-CN12515523449_1366x768.jpg",
    "downLoadUrl": "https://zhanghao-zhoushan.cn/image/large/PalmTreePantanal_ZH-CN12515523449.jpg",
    "url": "http://cdn.nanxiongnandi.com/bing/PalmTreePantanal_ZH-CN12515523449_1366x768.jpg",
    "name": "PalmTreePantanal_ZH-CN12515523449.jpg",
    "provider": "© Denis Tangney Jr./Getty Images",
    "copyright": "巴西，潘塔纳尔，树梢穿过薄雾依次排开 (© Bobby Haas/Getty Images)(Bing China)",
    "Continent": "",
    "Country": "美国",
    "City": "纽波特",
    "Longitude": "-71.3597876",
    "Latitude": "41.486169"
  },
  {
    "dateString": "20151210",
    "date": 1449705600000,
    "attribute": "巴西，潘塔纳尔",
    "title": "潘塔纳尔湿地",
    "story": [
      {
        "title": "神秘莫测",
        "au": "引人入胜",
        "describe": "一望无际的湿地上，尽是纵横交错的溪水河流。一眼望去，浓浓的萧瑟感满溢。这块世界上最大的湿地，地势平坦又有些倾斜，让人望而生畏，却又叫人想要一探究竟。",
        "miniImage": "http://s.cn.bing.net/th?id=OJ.B3fd0SFazodL3A&pid=MSNJVFeeds",
        "miniUrl": "https://zhanghao-zhoushan.cn/image/story/s.OJ.B3fd0SFazodL3A.png"
      },
      {
        "title": "人间天堂",
        "au": "费尔南多-迪诺罗尼亚岛",
        "describe": "说它是人间天堂一点也不为过。海水呈现出如水晶般的蓝色，配着天上朵朵白云实在美不胜收。这里的海豚湾是长嘴海豚定期造访的地方，也因此吸引了不少前来观看海豚的游客。",
        "miniImage": "http://s2.cn.bing.net/th?id=OJ.OhR0Ig7CGYWhaw&pid=MSNJVFeeds",
        "miniUrl": "https://zhanghao-zhoushan.cn/image/story/s2.OJ.OhR0Ig7CGYWhaw.png"
      },
      {
        "title": "富人聚集地",
        "au": "博塔佛戈海滩",
        "describe": "风光优美的博塔佛戈海滩是一个富人聚集地，这里风景迷人，傍晚的日落尤其美。此处治安相对更好一些，海滩附近更有许多咖啡馆和电影院，是一个休闲放松的好去处。",
        "miniImage": "http://s.cn.bing.net/th?id=OJ.vNrQrOk6ZefoSA&pid=MSNJVFeeds",
        "miniUrl": "https://zhanghao-zhoushan.cn/image/story/s.OJ.vNrQrOk6ZefoSA.png"
      }
    ],
    "primaryImageUrl": "http://hpimges.blob.core.chinacloudapi.cn/coverstory/watermark_palmtreepantanal_zh-cn12515523449_1920x1080.jpg",
    "imageUrl": "https://zhanghao-zhoushan.cn/image/large/Echidna_ZH-CN9102258970_1366x768.jpg",
    "downLoadUrl": "https://zhanghao-zhoushan.cn/image/large/Echidna_ZH-CN9102258970.jpg",
    "url": "http://cdn.nanxiongnandi.com/bing/Echidna_ZH-CN9102258970_1366x768.jpg",
    "name": "Echidna_ZH-CN9102258970.jpg",
    "provider": "© Bobby Haas/Getty Images",
    "copyright": "一只正在散步的针鼹鼠 (© John Kirk/Getty Images)(Bing China)",
    "Continent": "",
    "Country": "巴西",
    "City": "潘塔纳尔",
    "Longitude": "-48.8675096",
    "Latitude": "-25.5499585"
  },
  {
    "dateString": "20151211",
    "date": 1449792000000,
    "attribute": "澳大利亚",
    "title": "针鼹鼠",
    "story": [
      {
        "title": "怪异却可爱",
        "au": "那些奇奇怪怪的动物们",
        "describe": "胖乎乎的身体上长满尖刺，乍一看很像大号的刺猬，却又比刺猬多了些憨态可掬的可爱气质。针鼹鼠，虽有让人望而却步的一面，但萌萌的外表又令人对它喜欢不已。",
        "miniImage": "http://s3.cn.bing.net/th?id=OJ.XiPbgaZXlL4YQg&pid=MSNJVFeeds",
        "miniUrl": "https://zhanghao-zhoushan.cn/image/story/s3.OJ.XiPbgaZXlL4YQg.png"
      },
      {
        "title": "喜食蚂蚁",
        "au": "针鼹鼠饮食习惯",
        "describe": "针鼹鼠的主要食物是蚂蚁、白蚁和蠕虫，长长的指甲和鼻子让它们可以方便地捕捉这类食物。",
        "miniImage": "http://s4.cn.bing.net/th?id=OJ.o7r5TWM2Zo5mrA&pid=MSNJVFeeds",
        "miniUrl": "https://zhanghao-zhoushan.cn/image/story/s4.OJ.o7r5TWM2Zo5mrA.png"
      },
      {
        "title": "特殊的繁殖时期",
        "au": "属哺乳动物",
        "describe": "雌性针鼹鼠的腹部有一个腹袋，用来装小鼠蛋。十天之后，孵化完毕，破壳而出的鼠宝宝们就躲在妈妈的腹袋里吮吸奶水。",
        "miniImage": "http://s.cn.bing.net/th?id=OJ.JXRWw4TOGuwvjw&pid=MSNJVFeeds",
        "miniUrl": "https://zhanghao-zhoushan.cn/image/story/s.OJ.JXRWw4TOGuwvjw.png"
      }
    ],
    "primaryImageUrl": "http://hpimges.blob.core.chinacloudapi.cn/coverstory/watermark_echidna_zh-cn9102258970_1920x1080.jpg",
    "imageUrl": "https://zhanghao-zhoushan.cn/image/large/CemoroLawangCrater_ZH-CN10441912392_1366x768.jpg",
    "downLoadUrl": "https://zhanghao-zhoushan.cn/image/large/CemoroLawangCrater_ZH-CN10441912392.jpg",
    "url": "http://cdn.nanxiongnandi.com/bing/CemoroLawangCrater_ZH-CN10441912392_1366x768.jpg",
    "name": "CemoroLawangCrater_ZH-CN10441912392.jpg",
    "provider": "© John Kirk/Getty Images",
    "copyright": "印度尼西亚，靠近东爪哇的喇旺小镇 (© Nat Wimolsiri/REX Shutterstock)(Bing China)",
    "Continent": "",
    "Country": "",
    "City": "",
    "Longitude": "",
    "Latitude": ""
  },
  {
    "dateString": "20151212",
    "date": 1449878400000,
    "attribute": "印度尼西亚，喇旺小镇",
    "title": "神秘爪哇",
    "story": [
      {
        "title": "爪哇岛",
        "au": "一个充满故事的地方",
        "describe": "因为少知，所以迷人。关于爪哇，我们有太多猜想。一个被佛陀福佑的地方，一个经历了千年沉浮的地方，总是让人无限向往。",
        "miniImage": "http://s4.cn.bing.net/th?id=OJ.2O10D0Gv6NxRYQ&pid=MSNJVFeeds",
        "miniUrl": "https://zhanghao-zhoushan.cn/image/story/s4.OJ.2O10D0Gv6NxRYQ.png"
      },
      {
        "title": "东南亚美味",
        "au": "沙爹鸡肉串",
        "describe": "说道爪哇的特色小吃，沙爹鸡肉串是一定不能不提的。嫩嫩的鸡肉被切成小块穿在竹签上，配以特制的沙爹酱，烤出来美味无比。咬在嘴里，唇齿留香。",
        "miniImage": "http://s3.cn.bing.net/th?id=OJ.ZXvXg7rEdLqTZQ&pid=MSNJVFeeds",
        "miniUrl": "https://zhanghao-zhoushan.cn/image/story/s3.OJ.ZXvXg7rEdLqTZQ.png"
      },
      {
        "title": "特制汤水味道美",
        "au": "爪哇面",
        "describe": "将面条放到滚水中充分煮软，捞到碗中，再放入丰富的配菜，最后浇上兰卡威特制汤水，又香又辣，让人欲罢不能。",
        "miniImage": "http://s4.cn.bing.net/th?id=OJ.47V4DV08CNjaRg&pid=MSNJVFeeds",
        "miniUrl": "https://zhanghao-zhoushan.cn/image/story/s4.OJ.47V4DV08CNjaRg.png"
      }
    ],
    "primaryImageUrl": "http://hpimges.blob.core.chinacloudapi.cn/coverstory/watermark_cemorolawangcrater_zh-cn10441912392_1920x1080.jpg",
    "imageUrl": "https://zhanghao-zhoushan.cn/image/large/LotusLeaf_ZH-CN9424974136_1366x768.jpg",
    "downLoadUrl": "https://zhanghao-zhoushan.cn/image/large/LotusLeaf_ZH-CN9424974136.jpg",
    "url": "http://cdn.nanxiongnandi.com/bing/LotusLeaf_ZH-CN9424974136_1366x768.jpg",
    "name": "LotusLeaf_ZH-CN9424974136.jpg",
    "provider": "© Nat Wimolsiri/REX Shutterstock",
    "copyright": "中国，上海，荷叶 (© Sino Images/Getty Images)(Bing China)",
    "Continent": "",
    "Country": "印度尼西亚",
    "City": "喇旺小镇",
    "Longitude": "112.9248742",
    "Latitude": "-7.9725927"
  },
  {
    "dateString": "20151213",
    "date": 1449964800000,
    "attribute": "上海",
    "title": "荷叶田田荷花香",
    "story": [
      {
        "title": "大上海",
        "au": "可以静若处子 亦可以动如脱兔",
        "describe": "入冬后，上海的池塘失去了夏日独有的活力与色彩，没有了前来纳凉的人群，唯有荷叶仍然安静地躺在湖面上，即便没有观众，也静静地展现着它的生命。",
        "miniImage": "http://s1.cn.bing.net/th?id=OJ.gblyX8aisuUC0w&pid=MSNJVFeeds",
        "miniUrl": "https://zhanghao-zhoushan.cn/image/story/s1.OJ.gblyX8aisuUC0w.png"
      },
      {
        "title": "生活气息浓厚的法租界",
        "au": "老上海的新元素",
        "describe": "若要想逛特色小店，或是在梧桐树下和朋友喝个小资的下午茶，那去法租界。这里云集了许多潮店、咖啡店和各大人气餐厅，绝对是和朋友小聚的好去处。",
        "miniImage": "http://s4.cn.bing.net/th?id=OJ.0NVR7NcwC7FUog&pid=MSNJVFeeds",
        "miniUrl": "https://zhanghao-zhoushan.cn/image/story/s4.OJ.0NVR7NcwC7FUog.png"
      },
      {
        "title": "人气餐厅聚集地",
        "au": "张园",
        "describe": "这座曾经的私家花园如今已化身成为一个人气餐厅聚集地，汇聚了各国美味。餐厅、酒吧、咖啡店应有尽有，成为沪上潮人们最喜爱的聚会地点之一。",
        "miniImage": "http://s3.cn.bing.net/th?id=OJ.ehv0YjDId9MdgQ&pid=MSNJVFeeds",
        "miniUrl": "https://zhanghao-zhoushan.cn/image/story/s3.OJ.ehv0YjDId9MdgQ.png"
      }
    ],
    "primaryImageUrl": "http://hpimges.blob.core.chinacloudapi.cn/coverstory/watermark_lotusleaf_zh-cn9424974136_1920x1080.jpg",
    "imageUrl": "https://zhanghao-zhoushan.cn/image/large/CorfeCastle_ZH-CN10618481964_1366x768.jpg",
    "downLoadUrl": "https://zhanghao-zhoushan.cn/image/large/CorfeCastle_ZH-CN10618481964.jpg",
    "url": "http://cdn.nanxiongnandi.com/bing/CorfeCastle_ZH-CN10618481964_1366x768.jpg",
    "name": "CorfeCastle_ZH-CN10618481964.jpg",
    "provider": "© Sino Images/Getty Images",
    "copyright": "英格兰，多塞特郡，薄雾笼罩在日出时分的科夫堡 (© Mark Bauer/LOOP IMAGES/Loop Images/Corbis)(Bing China)",
    "Continent": "",
    "Country": "",
    "City": "",
    "Longitude": "",
    "Latitude": ""
  },
  {
    "dateString": "20151214",
    "date": 1450051200000,
    "attribute": "英格兰，多塞特郡",
    "title": "日出时的科夫堡",
    "story": [
      {
        "title": "历史的沉淀",
        "au": "荒芜却有内涵",
        "describe": "通往城堡大门的那座石桥上，曾有千军万马奔腾于此，它见证了无数历史，承载了现代人对往昔的回忆与追寻。当早晨第一缕阳光洒向这片断垣残壁时，仿佛它又有了新的生命。",
        "miniImage": "http://s.cn.bing.net/th?id=OJ.GotpN7ZD8ZnsQA&pid=MSNJVFeeds",
        "miniUrl": "https://zhanghao-zhoushan.cn/image/story/s.OJ.GotpN7ZD8ZnsQA.png"
      },
      {
        "title": "唯美浪漫",
        "au": "科夫堡的日出",
        "describe": "在科夫堡，一天中最美的时候就是早晨日出之时。温暖的阳光洒向城堡，为它平添了些许柔和的魅力。",
        "miniImage": "http://s3.cn.bing.net/th?id=OJ.hMovYWfPw0vFdw&pid=MSNJVFeeds",
        "miniUrl": "https://zhanghao-zhoushan.cn/image/story/s3.OJ.hMovYWfPw0vFdw.png"
      },
      {
        "title": "户外爱好者最喜爱的地方",
        "au": "徒步天堂",
        "describe": "这里车少人少，自然风光无比优美。无论是海边、山间还是古老的村落，都十分适合徒步或者露营。",
        "miniImage": "http://s.cn.bing.net/th?id=OJ.AgSA74A3v5mMVA&pid=MSNJVFeeds",
        "miniUrl": "https://zhanghao-zhoushan.cn/image/story/s.OJ.AgSA74A3v5mMVA.png"
      }
    ],
    "primaryImageUrl": "http://hpimges.blob.core.chinacloudapi.cn/coverstory/watermark_corfecastle_zh-cn10618481964_1920x1080.jpg",
    "imageUrl": "https://zhanghao-zhoushan.cn/image/large/NorrisGeyserBasin_ZH-CN10944194381_1366x768.jpg",
    "downLoadUrl": "https://zhanghao-zhoushan.cn/image/large/NorrisGeyserBasin_ZH-CN10944194381.jpg",
    "url": "http://cdn.nanxiongnandi.com/bing/NorrisGeyserBasin_ZH-CN10944194381_1366x768.jpg",
    "name": "NorrisGeyserBasin_ZH-CN10944194381.jpg",
    "provider": "© Mark Bauer/LOOP IMAGES/Loop Images/Corbis",
    "copyright": "美国，怀俄明州，黄石国家公园，诺里斯间歇泉盆地 (© Gerald & Buff Corsi/Visuals Unlimited, Inc.)(Bing China)",
    "Continent": "",
    "Country": "英格兰",
    "City": "多塞特郡",
    "Longitude": "-2.6018026",
    "Latitude": "50.7971336"
  },
  {
    "dateString": "20151215",
    "date": 1450137600000,
    "attribute": "美国，怀俄明州",
    "title": "诺里斯间歇泉盆地",
    "story": [
      {
        "title": "壮美景色尽在怀俄明",
        "au": "看遍壮观自然景致",
        "describe": "湖面上时时冒着白茫茫的热气，不经意间，沉寂了一段时间的温泉突然喷发，水柱直冲上天。在诺里斯间歇泉盆地，总会被这壮观场面所震撼。",
        "miniImage": "http://s4.cn.bing.net/th?id=OJ.Q99vZzFOq6C03g&pid=MSNJVFeeds",
        "miniUrl": "https://zhanghao-zhoushan.cn/image/story/s4.OJ.Q99vZzFOq6C03g.png"
      },
      {
        "title": "彩虹温泉",
        "au": "大棱镜温泉",
        "describe": "这座全美第一大温泉被誉为“地球最美丽的表面”，泉水的颜色会随着季节的变化而变化，奇特而美丽。温泉水温高达85摄氏度，每分钟会涌出约2000升泉水，美国最大的温泉实在名不虚传。",
        "miniImage": "http://s4.cn.bing.net/th?id=OJ.HWSpDgo7vPACsA&pid=MSNJVFeeds",
        "miniUrl": "https://zhanghao-zhoushan.cn/image/story/s4.OJ.HWSpDgo7vPACsA.png"
      },
      {
        "title": "气势恢宏",
        "au": "猛犸温泉",
        "describe": "放眼望去，一片高低起伏、富有层次感的河流冒着腾腾热气，如同仙境。泉水来自于诺里斯间歇泉盆地，里面生活着很多藻类，使得温泉的颜色呈现出棕色、红色和绿色。",
        "miniImage": "http://s3.cn.bing.net/th?id=OJ.m6oGgO3DwJJLkw&pid=MSNJVFeeds",
        "miniUrl": "https://zhanghao-zhoushan.cn/image/story/s3.OJ.m6oGgO3DwJJLkw.png"
      }
    ],
    "primaryImageUrl": "http://hpimges.blob.core.chinacloudapi.cn/coverstory/watermark_norrisgeyserbasin_zh-cn10944194381_1920x1080.jpg",
    "imageUrl": "https://zhanghao-zhoushan.cn/image/large/SalzburgOldTown_ZH-CN8279522266_1366x768.jpg",
    "downLoadUrl": "https://zhanghao-zhoushan.cn/image/large/SalzburgOldTown_ZH-CN8279522266.jpg",
    "url": "http://cdn.nanxiongnandi.com/bing/SalzburgOldTown_ZH-CN8279522266_1366x768.jpg",
    "name": "SalzburgOldTown_ZH-CN8279522266.jpg",
    "provider": "© Gerald & Buff Corsi/Visuals Unlimited, Inc.",
    "copyright": "奥地利，萨尔茨堡老城 (© Jochen Tack/age fotostock)(Bing China)",
    "Continent": "",
    "Country": "美国",
    "City": "怀俄明州",
    "Longitude": "-109.7972285",
    "Latitude": "42.9824496"
  },
  {
    "dateString": "20151216",
    "date": 1450224000000,
    "attribute": "奥地利，萨尔茨堡老城",
    "title": "莫扎特的出生地",
    "story": [
      {
        "title": "童话世界",
        "au": "一个浪漫的音乐王国",
        "describe": "整个萨尔茨堡被群山环绕，狭长的胡同里尽显中世纪风情。莫扎特出生的地方“粮食胡同”如今仍挂满了古老的商店招牌，古色古香，无比迷人。",
        "miniImage": "http://s4.cn.bing.net/th?id=OJ.xRHA6da218L20Q&pid=MSNJVFeeds",
        "miniUrl": "https://zhanghao-zhoushan.cn/image/story/s4.OJ.xRHA6da218L20Q.png"
      },
      {
        "title": "奥地利的女神",
        "au": "茜茜公主",
        "describe": "茜茜公主是巴伐利亚公爵家的女儿，因为有个喜欢写诗、弹琴，信奉共和主义和平民意识的父亲，因此从小生活得自由愉快，形成了活泼开朗、乐观善良的性格。茜茜公主在嫁给奥地利国王后，深受当地人民的爱戴，她的故事更被拍摄成电影，成为最受欢迎的电影之一。",
        "miniImage": "http://s3.cn.bing.net/th?id=OJ.26WHwNPJrsT3eQ&pid=MSNJVFeeds",
        "miniUrl": "https://zhanghao-zhoushan.cn/image/story/s3.OJ.26WHwNPJrsT3eQ.png"
      },
      {
        "title": "一个艺术气息无比浓厚的地方",
        "au": "音乐之国",
        "describe": "奥地利历史上产生了许多名扬世界的音乐家，如海顿、莫扎特、舒伯特等，贝多芬虽出生在德国，却是在奥地利长大。这些音乐大师们的出现，为整个国家留下了极为丰厚的文化遗产。",
        "miniImage": "http://s.cn.bing.net/th?id=OJ.XWsoTjQx0qa0Wg&pid=MSNJVFeeds",
        "miniUrl": "https://zhanghao-zhoushan.cn/image/story/s.OJ.XWsoTjQx0qa0Wg.png"
      }
    ],
    "primaryImageUrl": "http://hpimges.blob.core.chinacloudapi.cn/coverstory/watermark_salzburgoldtown_zh-cn8279522266_1920x1080.jpg",
    "imageUrl": "https://zhanghao-zhoushan.cn/image/large/HudsonBayPolars_ZH-CN10500767857_1366x768.jpg",
    "downLoadUrl": "https://zhanghao-zhoushan.cn/image/large/HudsonBayPolars_ZH-CN10500767857.jpg",
    "url": "http://cdn.nanxiongnandi.com/bing/HudsonBayPolars_ZH-CN10500767857_1366x768.jpg",
    "name": "HudsonBayPolars_ZH-CN10500767857.jpg",
    "provider": "© Jochen Tack/age fotostock",
    "copyright": "加拿大，结冰的哈德逊湾，北极熊妈妈和她的宝宝  (© Kike Calvo/Corbis)(Bing China)",
    "Continent": "",
    "Country": "奥地利",
    "City": "萨尔茨堡老城",
    "Longitude": "13.0214107",
    "Latitude": "47.8028623"
  },
  {
    "dateString": "20151217",
    "date": 1450310400000,
    "attribute": "加拿大",
    "title": "结冰的哈德逊湾",
    "story": [
      {
        "title": "迷人加拿大",
        "au": "沉浸在绝美大自然中",
        "describe": "当水流不在再流动，暖意不再停留，留下的不一定只有萧瑟和寒冷。当北极熊妈妈与熊宝宝在一旁嬉戏时，在即便是在冰天雪地中，也让人觉得温馨无比。",
        "miniImage": "http://s1.cn.bing.net/th?id=OJ.nEXGuVG7jfulYw&pid=MSNJVFeeds",
        "miniUrl": "https://zhanghao-zhoushan.cn/image/story/s1.OJ.nEXGuVG7jfulYw.png"
      },
      {
        "title": "感受冰的魔法",
        "au": "国际冰雕节",
        "describe": "每年一月下旬将在班夫国家公园举办炫酷的国际冰雕节。到时候，来自世界各地的冰雕大师们将会聚集于此，向人们展示他们精湛的手艺。",
        "miniImage": "http://s4.cn.bing.net/th?id=OJ.QgsBr7490c8wvg&pid=MSNJVFeeds",
        "miniUrl": "https://zhanghao-zhoushan.cn/image/story/s4.OJ.QgsBr7490c8wvg.png"
      },
      {
        "title": "寒冬里的热闹庆典",
        "au": "班夫冬季庆典",
        "describe": "对于那些喜欢刺激的游客们来说，班夫冬季庆典就是一个开心的大派对。到时候可以参加越野滑雪环路赛或纸板雪橇公开赛，甚至还有烹饪比赛和拼字游戏，大人小孩们都会玩得不亦乐乎。",
        "miniImage": "http://s.cn.bing.net/th?id=OJ.xMWuIVnFra15nQ&pid=MSNJVFeeds",
        "miniUrl": "https://zhanghao-zhoushan.cn/image/story/s.OJ.xMWuIVnFra15nQ.png"
      }
    ],
    "primaryImageUrl": "http://hpimges.blob.core.chinacloudapi.cn/coverstory/watermark_hudsonbaypolars_zh-cn10500767857_1920x1080.jpg",
    "imageUrl": "https://zhanghao-zhoushan.cn/image/large/ZionvilleXmasTrees_ZH-CN7637280983_1366x768.jpg",
    "downLoadUrl": "https://zhanghao-zhoushan.cn/image/large/ZionvilleXmasTrees_ZH-CN7637280983.jpg",
    "url": "http://cdn.nanxiongnandi.com/bing/ZionvilleXmasTrees_ZH-CN7637280983_1366x768.jpg",
    "name": "ZionvilleXmasTrees_ZH-CN7637280983.jpg",
    "provider": "© Kike Calvo/Corbis",
    "copyright": "美国，北卡罗来纳州，宰恩斯维尔的圣诞树农场 (© Coke Whitworth/Aurora Photos)(Bing China)",
    "Continent": "",
    "Country": "",
    "City": "",
    "Longitude": "",
    "Latitude": ""
  },
  {
    "dateString": "20151218",
    "date": 1450396800000,
    "attribute": "美国，宰恩斯维尔",
    "title": "奇妙圣诞树的诞生地",
    "story": [
      {
        "title": "北卡罗莱纳州",
        "au": "自然人文皆美的地方",
        "describe": "放眼望去，一片茂密的松树林近在眼前。一棵棵高耸的大树将要被人们带回家，装点上彩灯和各种闪亮的圣诞饰品，好好打扮一番，迎接一年中最温馨的圣诞节。",
        "miniImage": "http://s3.cn.bing.net/th?id=OJ.TOVFwyHGLaNt3g&pid=MSNJVFeeds",
        "miniUrl": "https://zhanghao-zhoushan.cn/image/story/s3.OJ.TOVFwyHGLaNt3g.png"
      },
      {
        "title": "气势恢宏的豪宅",
        "au": "比尔摩庄园",
        "describe": "比尔摩庄园被誉为“美国第一豪宅”，最初由铁路大王CorneliusVanderbilt的孙子建造。整栋楼有4层，楼内共有250个房间，43间浴室65座壁炉，3间厨房，1个室内泳池，甚至还有一个保龄球场。庄园现在对外开放，游客可以进去参观，体验一把上世纪美国上流社会的奢华生活。",
        "miniImage": "http://s3.cn.bing.net/th?id=OJ.aCsrhOY5pHJCkw&pid=MSNJVFeeds",
        "miniUrl": "https://zhanghao-zhoushan.cn/image/story/s3.OJ.aCsrhOY5pHJCkw.png"
      },
      {
        "title": "莘莘学子梦寐以求的地方",
        "au": "杜克大学",
        "describe": "这座建于19世纪末的大学是不少学生们梦想要来到的地方。它的前身为三一学院，在美国排名第8，图书馆藏仅次于哈佛。校园里风景优美，校舍总体来说很古老，学生宿舍很像哈利波特里的霍格沃兹魔城堡。校园里绿树成荫，草坪遍布，光是在这里散散步，都会让人心情大好。",
        "miniImage": "http://s.cn.bing.net/th?id=OJ.7uWECgHB2BALsA&pid=MSNJVFeeds",
        "miniUrl": "https://zhanghao-zhoushan.cn/image/story/s.OJ.7uWECgHB2BALsA.png"
      }
    ],
    "primaryImageUrl": "http://hpimges.blob.core.chinacloudapi.cn/coverstory/watermark_zionvillexmastrees_zh-cn7637280983_1920x1080.jpg",
    "imageUrl": "https://zhanghao-zhoushan.cn/image/large/JasperTrees_ZH-CN10000830186_1366x768.jpg",
    "downLoadUrl": "https://zhanghao-zhoushan.cn/image/large/JasperTrees_ZH-CN10000830186.jpg",
    "url": "http://cdn.nanxiongnandi.com/bing/JasperTrees_ZH-CN10000830186_1366x768.jpg",
    "name": "JasperTrees_ZH-CN10000830186.jpg",
    "provider": "© Coke Whitworth/Aurora Photos",
    "copyright": "加拿大，艾伯塔省，贾斯珀国家公园 (© Daryl Benson/Corbis)(Bing China)",
    "Continent": "",
    "Country": "美国",
    "City": "宰恩斯维尔",
    "Longitude": "-86.2966531",
    "Latitude": "39.9609211"
  },
  {
    "dateString": "20151219",
    "date": 1450483200000,
    "attribute": "加拿大，贾斯珀国家公园",
    "title": "贾斯珀国家公园",
    "story": [
      {
        "title": "冰雪世界",
        "au": "充满童话色彩的地方",
        "describe": "天空是醉人的蓝，高峻的山脉上依稀覆盖着皑皑白雪，湖水澄澈平静，在阳光的照耀下依稀泛出蓝光…… 贾斯珀国家公园，是一个随便拍拍都是大片的好地方。",
        "miniImage": "http://s3.cn.bing.net/th?id=OJ.FbFDk6bLd5o0QA&pid=MSNJVFeeds",
        "miniUrl": "https://zhanghao-zhoushan.cn/image/story/s3.OJ.FbFDk6bLd5o0QA.png"
      },
      {
        "title": "世界上最大的冰原遗迹",
        "au": "哥伦比亚冰原",
        "describe": "除了北极圈外，世界上最大的冰原遗迹就是哥伦比亚冰原了。它面积325平方公里，冰的深度最深达到300公尺，是个欣赏冰川奇景的胜地。冰河水在阳光的照耀下闪烁着迷人的蓝光，和周围银装素裹的冰山相映成趣，景色美不胜收。",
        "miniImage": "http://s.cn.bing.net/th?id=OJ.8YWt64vN23mFVA&pid=MSNJVFeeds",
        "miniUrl": "https://zhanghao-zhoushan.cn/image/story/s.OJ.8YWt64vN23mFVA.png"
      },
      {
        "title": "落基山最壮丽的峡谷",
        "au": "玛琳峡谷",
        "describe": "玛琳峡谷是洛基山脉中最壮丽、最狭长的峡谷。整个峡谷由玛琳河侵蚀而成，深谷只有1公里宽，却有5.5公里深。在大约4公里长的步道上，设有数个瞭望台，站在上面，可将壮丽的峡谷景致尽收眼底。",
        "miniImage": "http://s.cn.bing.net/th?id=OJ.d0sCZWw1pxvMdw&pid=MSNJVFeeds",
        "miniUrl": "https://zhanghao-zhoushan.cn/image/story/s.OJ.d0sCZWw1pxvMdw.png"
      }
    ],
    "primaryImageUrl": "http://hpimges.blob.core.chinacloudapi.cn/coverstory/watermark_jaspertrees_zh-cn10000830186_1920x1080.jpg",
    "imageUrl": "https://zhanghao-zhoushan.cn/image/large/BraunschweigXmasMarket_ZH-CN10208061180_1366x768.jpg",
    "downLoadUrl": "https://zhanghao-zhoushan.cn/image/large/BraunschweigXmasMarket_ZH-CN10208061180.jpg",
    "url": "http://cdn.nanxiongnandi.com/bing/BraunschweigXmasMarket_ZH-CN10208061180_1366x768.jpg",
    "name": "BraunschweigXmasMarket_ZH-CN10208061180.jpg",
    "provider": "© Daryl Benson/Corbis",
    "copyright": "德国，不伦瑞克的圣诞市场 (© Patrice von Collani/plainpicture)(Bing China)",
    "Continent": "",
    "Country": "加拿大",
    "City": "贾斯珀国家公园",
    "Longitude": "-117.9564826",
    "Latitude": "52.8733862"
  },
  {
    "dateString": "20151220",
    "date": 1450569600000,
    "attribute": "德国，不伦瑞克",
    "title": "气氛浓厚的圣诞市场",
    "story": [
      {
        "title": "魅力之都",
        "au": "充满德国风情的城市",
        "describe": "又是一年圣诞季，传统的圣诞集市最是这个时候不可错过的人文风景。小贩们纷纷将摊铺布置得充满圣诞气氛。喷香的香肠热狗、带着肉桂香的热红酒、以及满街琳琅满目的小饰品，都让人欣喜不已。",
        "miniImage": "http://s2.cn.bing.net/th?id=OJ.QRki9MnTE4E1YQ&pid=MSNJVFeeds",
        "miniUrl": "https://zhanghao-zhoushan.cn/image/story/s2.OJ.QRki9MnTE4E1YQ.png"
      },
      {
        "title": "圣诞集市上的经典小吃",
        "au": "油煎香肠",
        "describe": "当你穿梭在德国的圣诞集市上，总会闻到那一阵阵诱人的油煎香肠的味道。一根香肠配上番茄酱、酸菜或是土豆泥，一口一口，满嘴香。",
        "miniImage": "http://s2.cn.bing.net/th?id=OJ.RppNbXwEMA36Ag&pid=MSNJVFeeds",
        "miniUrl": "https://zhanghao-zhoushan.cn/image/story/s2.OJ.RppNbXwEMA36Ag.png"
      },
      {
        "title": "寒冬里的暖意",
        "au": "热红酒",
        "describe": "每到圣诞，热红酒便是欧洲各家各户桌上最受欢迎的饮料。将红酒放在锅中煮热，加入橙子、桂皮等香料，口味偏甜的人可以加一些糖。盛入杯中，拿在手里暖暖的，喝进嘴里更是酒香无比。",
        "miniImage": "http://s3.cn.bing.net/th?id=OJ.wFTi45v8TG0zIQ&pid=MSNJVFeeds",
        "miniUrl": "https://zhanghao-zhoushan.cn/image/story/s3.OJ.wFTi45v8TG0zIQ.png"
      }
    ],
    "primaryImageUrl": "http://hpimges.blob.core.chinacloudapi.cn/coverstory/watermark_braunschweigxmasmarket_zh-cn10208061180_1920x1080.jpg",
    "imageUrl": "https://zhanghao-zhoushan.cn/image/large/BCVanDusenLights_ZH-CN8651218193_1366x768.jpg",
    "downLoadUrl": "https://zhanghao-zhoushan.cn/image/large/BCVanDusenLights_ZH-CN8651218193.jpg",
    "url": "http://cdn.nanxiongnandi.com/bing/BCVanDusenLights_ZH-CN8651218193_1366x768.jpg",
    "name": "BCVanDusenLights_ZH-CN8651218193.jpg",
    "provider": "© Patrice von Collani/plainpicture",
    "copyright": "加拿大，温哥华，不列颠哥伦比亚，温哥华植物园的圣诞赏灯 (© Michael Wheatley/age fotostock)(Bing China)",
    "Continent": "",
    "Country": "德国",
    "City": "不伦瑞克",
    "Longitude": "10.4578458",
    "Latitude": "52.2722767"
  },
  {
    "dateString": "20151221",
    "date": 1450656000000,
    "attribute": "加拿大，温哥华植物园",
    "title": "被仙女灯装点的植物园",
    "story": [
      {
        "title": "魅力温哥华",
        "au": "美丽亦精彩",
        "describe": "湖泊、溪水、小桥、凉亭，这一切构成了这个清新脱俗的花园。一年四季，百花齐放，到了圣诞节期间，闪亮的仙女灯挂在植物上，那场景如梦如幻。",
        "miniImage": "http://s2.cn.bing.net/th?id=OJ.GE0kpE7eSbhm0w&pid=MSNJVFeeds",
        "miniUrl": "https://zhanghao-zhoushan.cn/image/story/s2.OJ.GE0kpE7eSbhm0w.png"
      },
      {
        "title": "城市中的清静地",
        "au": "斯坦利公园",
        "describe": "这座占地一千英亩的公园是北美最大的城市公园。这里有3个大沙滩，还有动物园、水族馆、高尔夫球场等。松鼠们在林间跳跃，天鹅在湖面悠游，整个画面静谧而美丽。",
        "miniImage": "http://s2.cn.bing.net/th?id=OJ.3zTLAhHwTwY9xQ&pid=MSNJVFeeds",
        "miniUrl": "https://zhanghao-zhoushan.cn/image/story/s2.OJ.3zTLAhHwTwY9xQ.png"
      },
      {
        "title": "知名滑雪胜地",
        "au": "惠斯勒",
        "describe": "惠斯勒是世界知名的滑雪胜地，也是2010年度冬季奥运会的举办地。其中惠斯勒山和黑梳山是北美两大滑雪场，更是国际级的滑雪场地，有着世界上最顶级的雪道和滑雪设施，每年都吸引着世界各地的探险爱好者前往。",
        "miniImage": "http://s.cn.bing.net/th?id=OJ.WfpkjPYIM2R05g&pid=MSNJVFeeds",
        "miniUrl": "https://zhanghao-zhoushan.cn/image/story/s.OJ.WfpkjPYIM2R05g.png"
      }
    ],
    "primaryImageUrl": "http://hpimges.blob.core.chinacloudapi.cn/coverstory/watermark_bcvandusenlights_zh-cn8651218193_1920x1080.jpg",
    "imageUrl": "https://zhanghao-zhoushan.cn/image/large/SichuanEmeishan_ZH-CN12735175923_1366x768.jpg",
    "downLoadUrl": "https://zhanghao-zhoushan.cn/image/large/SichuanEmeishan_ZH-CN12735175923.jpg",
    "url": "http://cdn.nanxiongnandi.com/bing/SichuanEmeishan_ZH-CN12735175923_1366x768.jpg",
    "name": "SichuanEmeishan_ZH-CN12735175923.jpg",
    "provider": "© Michael Wheatley/age fotostock",
    "copyright": "[冬至快乐] 四川省，乐山市，峨眉山云海 (© lop5712/iStock/Getty Images)(Bing China)",
    "Continent": "",
    "Country": "加拿大",
    "City": "温哥华植物园",
    "Longitude": "-123.1311247",
    "Latitude": "49.2384475"
  },
  {
    "dateString": "20151222",
    "date": 1450742400000,
    "attribute": "中国，四川省，峨眉山",
    "title": "以食养身",
    "story": [
      {
        "title": "冬至养生",
        "au": "以食来补",
        "describe": "冬至，是北半球与阳光接触时间最短的一天。天气严寒，最少要注重保暖养生，以食补身千百年来一直最受重视。这一日，吃下暖暖的传统食物，养精蓄锐，以迎接即将到来的新开始。",
        "miniImage": "http://s4.cn.bing.net/th?id=OJ.noOLKqkmNdov3A&pid=MSNJVFeeds",
        "miniUrl": "https://zhanghao-zhoushan.cn/image/story/s4.OJ.noOLKqkmNdov3A.png"
      },
      {
        "title": "祛寒暖身",
        "au": "苏州酿酒",
        "describe": "在苏州，历来有着“冬至如大年”的说法，会为此精心酿制冬酿酒。在米酒中加入桂花酿造，香气宜人，喝进肚中更是沁人心脾。",
        "miniImage": "http://s1.cn.bing.net/th?id=OJ.GfXlzMgCXTLIDA&pid=MSNJVFeeds",
        "miniUrl": "https://zhanghao-zhoushan.cn/image/story/s1.OJ.GfXlzMgCXTLIDA.png"
      },
      {
        "title": "寓意“团圆”",
        "au": "潮汕汤圆",
        "describe": "潮汕是一个很传统的地方，非常重视中国传统文化的继承和发扬，因此冬至对他们来说同样是一个重要的节日。冬至这天，他们常常会把它当作团圆节来过，要和家人一起吃汤圆，寓意“团团圆圆”。",
        "miniImage": "http://s.cn.bing.net/th?id=OJ.nztKQi06IVCBLw&pid=MSNJVFeeds",
        "miniUrl": "https://zhanghao-zhoushan.cn/image/story/s.OJ.nztKQi06IVCBLw.png"
      }
    ],
    "primaryImageUrl": "http://hpimges.blob.core.chinacloudapi.cn/coverstory/watermark_sichuanemeishan_zh-cn12735175923_1920x1080.jpg",
    "imageUrl": "https://zhanghao-zhoushan.cn/image/large/SnowySquirrel_ZH-CN13973676590_1366x768.jpg",
    "downLoadUrl": "https://zhanghao-zhoushan.cn/image/large/SnowySquirrel_ZH-CN13973676590.jpg",
    "url": "http://cdn.nanxiongnandi.com/bing/SnowySquirrel_ZH-CN13973676590_1366x768.jpg",
    "name": "SnowySquirrel_ZH-CN13973676590.jpg",
    "provider": "© lop5712/iStock/Getty Images",
    "copyright": "日本，北海道，欧亚红松鼠 (© stock_shot/Shutterstock)(Bing China)",
    "Continent": "",
    "Country": "中国",
    "City": "峨眉山",
    "Longitude": "103.2597685",
    "Latitude": "29.4956428"
  },
  {
    "dateString": "20151223",
    "date": 1450828800000,
    "attribute": "日本，北海道",
    "title": "欧亚红松鼠",
    "story": [
      {
        "title": "北海道精灵",
        "au": "人杰地灵之地",
        "describe": "幼小灵动的身体，毛茸茸的大尾巴左右摇摆着，一双耳朵直溜溜地立在小脑袋上，甚是可爱。北海道的欧亚红松鼠，萌萌的样子非常招人爱。",
        "miniImage": "http://s3.cn.bing.net/th?id=OJ.x9eNei4rb0N8Qg&pid=MSNJVFeeds",
        "miniUrl": "https://zhanghao-zhoushan.cn/image/story/s3.OJ.x9eNei4rb0N8Qg.png"
      },
      {
        "title": "肉质上乘",
        "au": "北海道蟹",
        "describe": "北海道位置偏北，周围海水温度较低，且污染很小，因此是个产蟹胜地。这里盛产鳕场蟹、毛蟹和花蟹，色泽鲜红，肉质上乘。",
        "miniImage": "http://s1.cn.bing.net/th?id=OJ.gFtjo6X2IjkPyw&pid=MSNJVFeeds",
        "miniUrl": "https://zhanghao-zhoushan.cn/image/story/s1.OJ.gFtjo6X2IjkPyw.png"
      },
      {
        "title": "异常爽口",
        "au": "札幌啤酒",
        "describe": "北海道的札幌啤酒可以说是当地的一张名片，是日本最具代表性的啤酒生产企业之一。它非常爽口，清凉，尤其在夏天喝非常沁入心脾。",
        "miniImage": "http://s2.cn.bing.net/th?id=OJ.BpXMLUIOXltG6A&pid=MSNJVFeeds",
        "miniUrl": "https://zhanghao-zhoushan.cn/image/story/s2.OJ.BpXMLUIOXltG6A.png"
      }
    ],
    "primaryImageUrl": "http://hpimges.blob.core.chinacloudapi.cn/coverstory/watermark_snowysquirrel_zh-cn13973676590_1920x1080.jpg",
    "imageUrl": "https://zhanghao-zhoushan.cn/image/large/JuneauXmas_ZH-CN13726790431_1366x768.jpg",
    "downLoadUrl": "https://zhanghao-zhoushan.cn/image/large/JuneauXmas_ZH-CN13726790431.jpg",
    "url": "http://cdn.nanxiongnandi.com/bing/JuneauXmas_ZH-CN13726790431_1366x768.jpg",
    "name": "JuneauXmas_ZH-CN13726790431.jpg",
    "provider": "© stock_shot/Shutterstock",
    "copyright": "美国，阿拉斯加，靠近朱诺的Amalga港 (© Mark Kelley/Tandem Stills + Motion)(Bing China)",
    "Continent": "",
    "Country": "",
    "City": "",
    "Longitude": "",
    "Latitude": ""
  },
  {
    "dateString": "20151224",
    "date": 1450915200000,
    "attribute": "美国，阿拉斯加",
    "title": "人间净土",
    "story": [
      {
        "title": "阿拉斯加",
        "au": "一个带给人震撼的地方",
        "describe": "阿拉斯加，最不乏的就是冰城雪原般的醉人景致。这里处处可见澄澈的海湾、皑皑冰川、澄澈的溪流和湖泊。这一切让人见了以后都难以忘怀。",
        "miniImage": "http://s.cn.bing.net/th?id=OJ.kh7UN2bXzB69mg&pid=MSNJVFeeds",
        "miniUrl": "https://zhanghao-zhoushan.cn/image/story/s.OJ.kh7UN2bXzB69mg.png"
      },
      {
        "title": "漂亮的入海冰川",
        "au": "马杰瑞冰川",
        "describe": "这座冰川位于海湾国家公园内，是一座漂亮的入海冰川，也是一条前进的冰河。这座冰川长达21英里，高达350英尺，放眼望去一片雪白，非常壮观。",
        "miniImage": "http://s.cn.bing.net/th?id=OJ.0EQdLhUJ6nOeHg&pid=MSNJVFeeds",
        "miniUrl": "https://zhanghao-zhoushan.cn/image/story/s.OJ.0EQdLhUJ6nOeHg.png"
      },
      {
        "title": "纯净的天堂",
        "au": "威廉王子湾",
        "describe": "天空是醉人的蓝，柔白的云朵点缀其间，甚为好看。天空之下是纯净的海湾，澄澈的海水清透无比，四周雪山环绕，宛若仙境。",
        "miniImage": "http://s.cn.bing.net/th?id=OJ.foqyoPLxlhHXPQ&pid=MSNJVFeeds",
        "miniUrl": "https://zhanghao-zhoushan.cn/image/story/s.OJ.foqyoPLxlhHXPQ.png"
      }
    ],
    "primaryImageUrl": "http://hpimges.blob.core.chinacloudapi.cn/coverstory/watermark_juneauxmas_zh-cn13726790431_1920x1080.jpg",
    "imageUrl": "https://zhanghao-zhoushan.cn/image/large/OuluReindeers_ZH-CN7661208993_1366x768.jpg",
    "downLoadUrl": "https://zhanghao-zhoushan.cn/image/large/OuluReindeers_ZH-CN7661208993.jpg",
    "url": "http://cdn.nanxiongnandi.com/bing/OuluReindeers_ZH-CN7661208993_1366x768.jpg",
    "name": "OuluReindeers_ZH-CN7661208993.jpg",
    "provider": "© Mark Kelley/Tandem Stills + Motion",
    "copyright": "芬兰，靠近奥卢的驯鹿 (© Juan Carlos Muñoz/age fotostock)(Bing China)",
    "Continent": "",
    "Country": "美国",
    "City": "阿拉斯加",
    "Longitude": "-176.411441",
    "Latitude": "60.1460515"
  },
  {
    "dateString": "20151225",
    "date": 1451001600000,
    "attribute": "芬兰，靠近奥卢的驯鹿",
    "title": "童话里的主角",
    "story": [
      {
        "title": "童话王国",
        "au": "唯美的冰雪世界",
        "describe": "每到圣诞季，总忍不住想象圣诞老人乘着驯鹿拉的雪橇从天而降，去到每家每户为小孩子们送上期待了一整年的礼物。圣诞，是每个小朋友的期待，也是每个大人心中灭不掉的浪漫情结。",
        "miniImage": "http://s2.cn.bing.net/th?id=OJ.y0rSZ0HalifuBA&pid=MSNJVFeeds",
        "miniUrl": "https://zhanghao-zhoushan.cn/image/story/s2.OJ.y0rSZ0HalifuBA.png"
      },
      {
        "title": "看极光的胜地",
        "au": "拉普兰",
        "describe": "在拉普兰，整个12月和1月都是黑夜，在这样漆黑的夜晚，最是看极光的好时候。天空中，变幻莫测的极光大放异彩，梦幻无比。",
        "miniImage": "http://s4.cn.bing.net/th?id=OJ.YeqbQXj9lXhZ2Q&pid=MSNJVFeeds",
        "miniUrl": "https://zhanghao-zhoushan.cn/image/story/s4.OJ.YeqbQXj9lXhZ2Q.png"
      },
      {
        "title": "圣诞老人的故乡",
        "au": "罗瓦涅米",
        "describe": "罗瓦涅米是芬兰北部的一座城市，位于北极圈上，是圣诞老人的故乡，闻名世界的圣诞老人村就在市郊，每年都能吸引无数小朋友前往。这里的自然环境非常纯净，宛若一个童话王国。",
        "miniImage": "http://s2.cn.bing.net/th?id=OJ.5yQ0z58F6RoQ0g&pid=MSNJVFeeds",
        "miniUrl": "https://zhanghao-zhoushan.cn/image/story/s2.OJ.5yQ0z58F6RoQ0g.png"
      }
    ],
    "primaryImageUrl": "http://hpimges.blob.core.chinacloudapi.cn/coverstory/watermark_oulureindeers_zh-cn7661208993_1920x1080.jpg",
    "imageUrl": "https://zhanghao-zhoushan.cn/image/large/Knaresborough_ZH-CN11690958280_1366x768.jpg",
    "downLoadUrl": "https://zhanghao-zhoushan.cn/image/large/Knaresborough_ZH-CN11690958280.jpg",
    "url": "http://cdn.nanxiongnandi.com/bing/Knaresborough_ZH-CN11690958280_1366x768.jpg",
    "name": "Knaresborough_ZH-CN11690958280.jpg",
    "provider": "© Juan Carlos Muñoz/age fotostock",
    "copyright": "英格兰，纳尔斯伯勒 (© Steven Hunt/Alamy)(Bing China)",
    "Continent": "",
    "Country": "",
    "City": "",
    "Longitude": "",
    "Latitude": ""
  },
  {
    "dateString": "20151226",
    "date": 1451088000000,
    "attribute": "英格兰，纳尔斯伯勒",
    "title": "平静小镇",
    "story": [
      {
        "title": "英伦慢旅行",
        "au": "那些迷人的小城",
        "describe": "没有如织的游客，没有繁忙的车流，这里只有平静的湖水、静谧的小村庄、茂密的森林和朴实善良的居民们。漫步在这样一个无人打扰的地方，每一刻都是难忘舒适的。",
        "miniImage": "http://s2.cn.bing.net/th?id=OJ.TYR96QYi6kWnJw&pid=MSNJVFeeds",
        "miniUrl": "https://zhanghao-zhoushan.cn/image/story/s2.OJ.TYR96QYi6kWnJw.png"
      },
      {
        "title": "绝不那么简单",
        "au": "炸鱼薯条",
        "describe": "一说到英国菜，大多数人立刻会想到经典的炸鱼薯条，看起来很简单的一道菜，烹饪起来却也大有学问。越是简单的菜，对食材的新鲜度和质感就越有要求，鱼的种类不同，也会影响整道菜的风味和口感。",
        "miniImage": "http://s3.cn.bing.net/th?id=OJ.pyu1j6EPh0ysEA&pid=MSNJVFeeds",
        "miniUrl": "https://zhanghao-zhoushan.cn/image/story/s3.OJ.pyu1j6EPh0ysEA.png"
      },
      {
        "title": "让你一天元气满满",
        "au": "英式早点",
        "describe": "传统的英式早餐最适合当Brunch，内容丰富，一般会有香肠、炒蛋、炒蘑菇、茄汁焗豆、培根和土司等。再配上一杯咖啡，和好友一起边吃边聊，为新的一天注入满满元气。",
        "miniImage": "http://s.cn.bing.net/th?id=OJ.IeUaAUb30y7lMw&pid=MSNJVFeeds",
        "miniUrl": "https://zhanghao-zhoushan.cn/image/story/s.OJ.IeUaAUb30y7lMw.png"
      }
    ],
    "primaryImageUrl": "http://hpimges.blob.core.chinacloudapi.cn/coverstory/watermark_knaresborough_zh-cn11690958280_1920x1080.jpg",
    "imageUrl": "https://zhanghao-zhoushan.cn/image/large/MercantourNight_ZH-CN7018234063_1366x768.jpg",
    "downLoadUrl": "https://zhanghao-zhoushan.cn/image/large/MercantourNight_ZH-CN7018234063.jpg",
    "url": "http://cdn.nanxiongnandi.com/bing/MercantourNight_ZH-CN7018234063_1366x768.jpg",
    "name": "MercantourNight_ZH-CN7018234063.jpg",
    "provider": "© Steven Hunt/Alamy",
    "copyright": "法国，穿过梅康图尔国家公园的Col de la山 (© Mathieu Rivrin/Getty Images)(Bing China)",
    "Continent": "",
    "Country": "英格兰",
    "City": "纳尔斯伯勒",
    "Longitude": "-1.4866138",
    "Latitude": "54.0072993"
  },
  {
    "dateString": "20151227",
    "date": 1451174400000,
    "attribute": "法国，梅康图尔国家公园",
    "title": "梅康图尔国家公园",
    "story": [
      {
        "title": "风光无限的法国",
        "au": "人文美，自然更美",
        "describe": "延绵的山丘浩浩荡荡，山上树林茂密，山下湖水清透，在这里，每一口呼吸都是那么沁人心脾。梅康图尔国家公园的每一个角落都是醉人美景。",
        "miniImage": "http://s3.cn.bing.net/th?id=OJ.FNB7uYEvsHz0uQ&pid=MSNJVFeeds",
        "miniUrl": "https://zhanghao-zhoushan.cn/image/story/s3.OJ.FNB7uYEvsHz0uQ.png"
      },
      {
        "title": "让人幸福的国度",
        "au": "甜点天堂",
        "describe": "众所周知，法国是一个甜点天堂，尤其在巴黎，大街小巷的咖啡店、甜点店里总是摆放着琳琅满目种类丰富的甜点。无论是闪电泡芙、马卡龙还是玛德林，都让人看了立刻馋涎欲滴。",
        "miniImage": "http://s4.cn.bing.net/th?id=OJ.PoUz4Mz70Edr1w&pid=MSNJVFeeds",
        "miniUrl": "https://zhanghao-zhoushan.cn/image/story/s4.OJ.PoUz4Mz70Edr1w.png"
      },
      {
        "title": "时装精们的朝圣地",
        "au": "时装殿堂",
        "describe": "法国，这个浪漫的国度，总与“美”有着千丝万缕的联系。时装界的鼻祖香奈儿在此诞生，爱马仕在此出现，圣罗兰也正是在此创立。这个充满无限灵感的地方，孕育了时装界最经典的品牌，是名副其实的时装殿堂。",
        "miniImage": "http://s.cn.bing.net/th?id=OJ.uEucbisDhCUi9A&pid=MSNJVFeeds",
        "miniUrl": "https://zhanghao-zhoushan.cn/image/story/s.OJ.uEucbisDhCUi9A.png"
      }
    ],
    "primaryImageUrl": "http://hpimges.blob.core.chinacloudapi.cn/coverstory/watermark_mercantournight_zh-cn7018234063_1920x1080.jpg",
    "imageUrl": "https://zhanghao-zhoushan.cn/image/large/KyotoBamboo_ZH-CN7740124234_1366x768.jpg",
    "downLoadUrl": "https://zhanghao-zhoushan.cn/image/large/KyotoBamboo_ZH-CN7740124234.jpg",
    "url": "http://cdn.nanxiongnandi.com/bing/KyotoBamboo_ZH-CN7740124234_1366x768.jpg",
    "name": "KyotoBamboo_ZH-CN7740124234.jpg",
    "provider": "© Mathieu Rivrin/Getty Images",
    "copyright": "日本，京都，岚山，嵯峨野竹林 (© JTB Photo Communications, Inc./age fotostock)(Bing China)",
    "Continent": "",
    "Country": "法国",
    "City": "梅康图尔国家公园",
    "Longitude": "6.9992229",
    "Latitude": "44.1521572"
  },
  {
    "dateString": "20151228",
    "date": 1451260800000,
    "attribute": "日本，京都",
    "title": "岚山",
    "story": [
      {
        "title": "迷人京都",
        "au": "精致典雅",
        "describe": "嵯峨野竹林是日本最著名的竹林，位于京都的国家指定古迹——岚山。从林中穿过，可以听到风吹过竹叶发出的天籁之音，这个声音还被评为日本100种最值得保留的声音之一。",
        "miniImage": "http://s2.cn.bing.net/th?id=OJ.iiRrDfg0P5eYFw&pid=MSNJVFeeds",
        "miniUrl": "https://zhanghao-zhoushan.cn/image/story/s2.OJ.iiRrDfg0P5eYFw.png"
      },
      {
        "title": "思索人生的地方",
        "au": "哲学之道",
        "describe": "这条沿河小道南起熊野王子神社，北至银阁寺，因哲学家西田几多郎曾在这里一边散步一边思考人生而得名。小道两旁沿途种了很多樱花树和枫树，每到春秋两季风景就特别美丽。",
        "miniImage": "http://s3.cn.bing.net/th?id=OJ.Oifs664ehPAyOg&pid=MSNJVFeeds",
        "miniUrl": "https://zhanghao-zhoushan.cn/image/story/s3.OJ.Oifs664ehPAyOg.png"
      },
      {
        "title": "日本最长的木造建筑之一",
        "au": "三十三间堂",
        "describe": "三十三间堂又叫莲华王院，其主殿是全日本最长的木造建筑之一，由33根立柱隔开，名字便由此而来。建筑外观朴素古老，内里却十分震撼，需脱鞋才能进去参观。",
        "miniImage": "http://s2.cn.bing.net/th?id=OJ.vOlDZUnm0JJ7GQ&pid=MSNJVFeeds",
        "miniUrl": "https://zhanghao-zhoushan.cn/image/story/s2.OJ.vOlDZUnm0JJ7GQ.png"
      }
    ],
    "primaryImageUrl": "http://hpimges.blob.core.chinacloudapi.cn/coverstory/watermark_kyotobamboo_zh-cn7740124234_1920x1080.jpg",
    "imageUrl": "https://zhanghao-zhoushan.cn/image/large/MLCubs_ZH-CN10166297846_1366x768.jpg",
    "downLoadUrl": "https://zhanghao-zhoushan.cn/image/large/MLCubs_ZH-CN10166297846.jpg",
    "url": "http://cdn.nanxiongnandi.com/bing/MLCubs_ZH-CN10166297846_1366x768.jpg",
    "name": "MLCubs_ZH-CN10166297846.jpg",
    "provider": "© JTB Photo Communications, Inc./age fotostock",
    "copyright": "美国，犹他州，尤因国家森林公园的美洲狮幼崽 (© Kevin Schafer/Minden Pictures)(Bing China)",
    "Continent": "",
    "Country": "日本",
    "City": "京都",
    "Longitude": "135.7259306",
    "Latitude": "35.0061653"
  },
  {
    "dateString": "20151229",
    "date": 1451347200000,
    "attribute": "美国，犹他州",
    "title": "美国西部的野性美",
    "story": [
      {
        "title": "美国犹他州",
        "au": "一个让人震撼的地方",
        "describe": "在茂密的森林中，崇山峻岭，溪水潺潺，四季皆是美景。可爱的山狮幼崽在草地上悠然散步，为这片秀丽的山水增添了野性美。",
        "miniImage": "http://s1.cn.bing.net/th?id=OJ.03BtXX85Za7LiQ&pid=MSNJVFeeds",
        "miniUrl": "https://zhanghao-zhoushan.cn/image/story/s1.OJ.03BtXX85Za7LiQ.png"
      },
      {
        "title": "湖光山色相映成趣",
        "au": "大盐湖",
        "describe": "它是世界上仅次于死海盐分最高的地区，也是整个盐湖城最具吸引力的一个参观圣地。这里湖水密度很大，跳到水中不会下沉，每到夏天都会有很多人来此戏水。",
        "miniImage": "http://s4.cn.bing.net/th?id=OJ.o4lqhMPq00v10Q&pid=MSNJVFeeds",
        "miniUrl": "https://zhanghao-zhoushan.cn/image/story/s4.OJ.o4lqhMPq00v10Q.png"
      },
      {
        "title": "美国西部地貌的象征",
        "au": "纪念碑谷",
        "describe": "一幢幢红色的平顶山矗立在荒芜的沙漠中，放眼望去蔚为壮观。其中最大的孤峰大约有300米高，景色壮丽，令人惊艳。",
        "miniImage": "http://s1.cn.bing.net/th?id=OJ.JUfFCiQSh5m83g&pid=MSNJVFeeds",
        "miniUrl": "https://zhanghao-zhoushan.cn/image/story/s1.OJ.JUfFCiQSh5m83g.png"
      }
    ],
    "primaryImageUrl": "http://hpimges.blob.core.chinacloudapi.cn/coverstory/watermark_mlcubs_zh-cn10166297846_1920x1080.jpg",
    "imageUrl": "https://zhanghao-zhoushan.cn/image/large/HarzerSchmalspurbahnen_ZH-CN14210913008_1366x768.jpg",
    "downLoadUrl": "https://zhanghao-zhoushan.cn/image/large/HarzerSchmalspurbahnen_ZH-CN14210913008.jpg",
    "url": "http://cdn.nanxiongnandi.com/bing/HarzerSchmalspurbahnen_ZH-CN14210913008_1366x768.jpg",
    "name": "HarzerSchmalspurbahnen_ZH-CN14210913008.jpg",
    "provider": "© Kevin Schafer/Minden Pictures",
    "copyright": "德国， 哈尔茨山脉的布罗肯铁路 (© Rudi Sebastian/age fotostock)(Bing China)",
    "Continent": "",
    "Country": "",
    "City": "",
    "Longitude": "",
    "Latitude": ""
  },
  {
    "dateString": "20151230",
    "date": 1451433600000,
    "attribute": "德国， 哈尔茨山脉",
    "title": "小阿尔卑斯山",
    "story": [
      {
        "title": "迷人景致，浪漫文化",
        "au": "环游汉诺威",
        "describe": "在梦幻古老的汉诺威城周围，葱茏的山脉延绵起伏。哈尔茨山脉素有小阿尔卑斯山之称，德国著名诗人海涅就曾热情地赞颂过这里旖旎的自然风光。",
        "miniImage": "http://s2.cn.bing.net/th?id=OJ.2Lekm6QnbIrypg&pid=MSNJVFeeds",
        "miniUrl": "https://zhanghao-zhoushan.cn/image/story/s2.OJ.2Lekm6QnbIrypg.png"
      },
      {
        "title": "老城中的创意元素",
        "au": "KUBUS艺术廊",
        "describe": "古老的汉诺威城中不乏各式各样的人气艺廊，KUBUS就是其中之一。每年会有8个艺术展在此举办，展出许多当地艺术家的作品，吸引不少艺术爱好者前来参观。",
        "miniImage": "http://s2.cn.bing.net/th?id=OJ.iGEPSEQZ0IzVZQ&pid=MSNJVFeeds",
        "miniUrl": "https://zhanghao-zhoushan.cn/image/story/s2.OJ.iGEPSEQZ0IzVZQ.png"
      },
      {
        "title": "迷人老街区",
        "au": "AmHohenUfer街区",
        "describe": "由于此地远离洪水泛滥区，因此很早就有人在此居住。在这个迷人的历史中心，有教堂、博物馆和各类跳蚤市场，是当地人和游客都喜爱光顾的景点之一。",
        "miniImage": "http://s.cn.bing.net/th?id=OJ.Dq0gxqPhrO6cRg&pid=MSNJVFeeds",
        "miniUrl": "https://zhanghao-zhoushan.cn/image/story/s.OJ.Dq0gxqPhrO6cRg.png"
      }
    ],
    "primaryImageUrl": "http://hpimges.blob.core.chinacloudapi.cn/coverstory/watermark_harzerschmalspurbahnen_zh-cn14210913008_1920x1080.jpg",
    "imageUrl": "https://zhanghao-zhoushan.cn/image/large/SalzburgFireworks_ZH-CN12027615955_1366x768.jpg",
    "downLoadUrl": "https://zhanghao-zhoushan.cn/image/large/SalzburgFireworks_ZH-CN12027615955.jpg",
    "url": "http://cdn.nanxiongnandi.com/bing/SalzburgFireworks_ZH-CN12027615955_1366x768.jpg",
    "name": "SalzburgFireworks_ZH-CN12027615955.jpg",
    "provider": "© Rudi Sebastian/age fotostock",
    "copyright": "奥地利，萨尔兹堡的烟花和雾气 (© Franz Pritz/Getty Images)(Bing China)",
    "Continent": "",
    "Country": "德国",
    "City": "哈尔茨山脉",
    "Longitude": "10.6245782",
    "Latitude": "51.7500124"
  },
  {
    "dateString": "20151231",
    "date": 1451520000000,
    "attribute": "奥地利，萨尔兹堡",
    "title": "走进童话中",
    "story": [
      {
        "title": "萨尔茨堡",
        "au": "古典音乐之都",
        "describe": "葱茏延绵的山脉之下，迷人古老的巴洛克风格建筑散落分布，这里就是古典韵味十足的魅力老城萨尔兹堡。入夜，灿烂烟花划过黑暗夜空，如梦如幻，恍若走进童话世界。",
        "miniImage": "http://s1.cn.bing.net/th?id=OJ.geOiyyMqNrOhOA&pid=MSNJVFeeds",
        "miniUrl": "https://zhanghao-zhoushan.cn/image/story/s1.OJ.geOiyyMqNrOhOA.png"
      },
      {
        "title": "萨尔茨堡的“爱桥”",
        "au": "巴克小桥",
        "describe": "巴克小桥横跨萨尔察赫河，是一座人行桥。恋人们常常来到这里，将代表爱情的锁挂在桥上，成为城中一道靓丽的风景。",
        "miniImage": "http://s3.cn.bing.net/th?id=OJ.Ec0JJyntr4cSog&pid=MSNJVFeeds",
        "miniUrl": "https://zhanghao-zhoushan.cn/image/story/s3.OJ.Ec0JJyntr4cSog.png"
      },
      {
        "title": "又一个《音乐之声》取景地",
        "au": "农贝格女修道院",
        "describe": "农贝格女修道院位于城市以东的山上，也是《音乐之声》的取景地之一，电影中玛丽首次出现就是在这里。修道院建于714年，是德语国家中最古老的女子修道院。",
        "miniImage": "http://s2.cn.bing.net/th?id=OJ.lwEmqc4V00VbgQ&pid=MSNJVFeeds",
        "miniUrl": "https://zhanghao-zhoushan.cn/image/story/s2.OJ.lwEmqc4V00VbgQ.png"
      }
    ],
    "primaryImageUrl": "http://hpimges.blob.core.chinacloudapi.cn/coverstory/watermark_salzburgfireworks_zh-cn12027615955_1920x1080.jpg",
    "imageUrl": "",
    "downLoadUrl": "",
    "provider": "© Franz Pritz/Getty Images",
    "Continent": "",
    "Country": "奥地利",
    "City": "萨尔兹堡",
    "Longitude": "13.0214107",
    "Latitude": "47.8028623"
  }
]