[
  {
    "dateString": "20160201",
    "date": 1454284800000,
    "attribute": "中国",
    "title": "小年",
    "story": [
      {
        "title": "小年习俗",
        "au": "新年的前奏",
        "describe": "小年，在各个地方都有不同日期，北方是腊月二十三，南方大部分是腊月二十四。一到此时，大家都纷纷开始置备年货，为即将到来的春节做准备。",
        "miniImage": "http://s4.cn.bing.net/th?id=OJ.VvIIqnmwQlyTgA&pid=MSNJVFeeds",
        "miniUrl": "https://zhanghao-zhoushan.cn/image/story/s4.OJ.VvIIqnmwQlyTgA.png"
      },
      {
        "title": "清新过年",
        "au": "洗脚",
        "describe": "古时候的吕梁地区有腊月二十七日洗脚的讲究，这天傍晚，所有女性都要用温水洗脚，不留一点污渍，有“一个不洗脚，流脓害水七个月”的说法。",
        "miniImage": "http://s2.cn.bing.net/th?id=OJ.0Vcv9xASAc0biQ&pid=MSNJVFeeds",
        "miniUrl": "https://zhanghao-zhoushan.cn/image/story/s2.OJ.0Vcv9xASAc0biQ.png"
      },
      {
        "title": "嫁娶的好日子",
        "au": "婚嫁",
        "describe": "过了腊月二十三，诸神上了天，于是这段日子百无禁忌，最适合嫁娶。这段时间，娶媳妇、嫁闺女都不用挑选日子，称为赶乱婚。",
        "miniImage": "http://s2.cn.bing.net/th?id=OJ.f5mAeffqfa9Sqg&pid=MSNJVFeeds",
        "miniUrl": "https://zhanghao-zhoushan.cn/image/story/s2.OJ.f5mAeffqfa9Sqg.png"
      }
    ],
    "primaryImageUrl": "http://hpimges.blob.core.chinacloudapi.cn/coverstory/watermark_farmsnowvillage_zh-cn11121852629_1920x1080.jpg",
    "imageUrl": "https://zhanghao-zhoushan.cn/image/large/UpsideDown_ZH-CN11824550636_1366x768.jpg",
    "downLoadUrl": "https://zhanghao-zhoushan.cn/image/large/UpsideDown_ZH-CN11824550636.jpg",
    "url": "http://cdn.nanxiongnandi.com/bing/UpsideDown_ZH-CN11824550636_1366x768.jpg",
    "name": "UpsideDown_ZH-CN11824550636.jpg",
    "provider": "© Libby Zhang/500px",
    "copyright": "欧洲地松鼠 (© Gerard Kummer/500px)(Bing China)",
    "Continent": "",
    "Country": "",
    "City": "",
    "Longitude": "",
    "Latitude": ""
  },
  {
    "dateString": "20160202",
    "date": 1454371200000,
    "attribute": "欧洲",
    "title": "欧洲地松鼠",
    "story": [
      {
        "title": "大尾巴鼠",
        "au": "在林中穿梭",
        "describe": "小小的身体灵气十足，走哪都带着毛茸茸的大尾巴，样子非常惹人喜爱。欧洲地松鼠们不象其它松鼠那样有很强的攀爬本领，因此大多都栖息在陆地上。",
        "miniImage": "http://s2.cn.bing.net/th?id=OJ.ZM00HjKhTav1vA&pid=MSNJVFeeds",
        "miniUrl": "https://zhanghao-zhoushan.cn/image/story/s2.OJ.ZM00HjKhTav1vA.png"
      },
      {
        "title": "旷野上的小精灵",
        "au": "草原鼠",
        "describe": "草原鼠最初生长于北美洲，以吃植物为主。它们体型矮胖，行动却很敏捷，身体以褐色为主。它们喜欢做站立和坐下的动作，非常可爱、讨人喜欢。",
        "miniImage": "http://s.cn.bing.net/th?id=OJ.JSqGs99YTphpUQ&pid=MSNJVFeeds",
        "miniUrl": "https://zhanghao-zhoushan.cn/image/story/s.OJ.JSqGs99YTphpUQ.png"
      },
      {
        "title": "可爱小飞鼠",
        "au": "日本小鼯鼠",
        "describe": "背面为褐色，腹部是白色，四肢之间有皮膜相连，可以在空中滑行，又酷又可爱。它们喜欢在夜间活动，白天则是睡觉时间，养在家里时可放出笼外在屋里滑翔。",
        "miniImage": "http://s3.cn.bing.net/th?id=OJ.o0QpPTigMvogcg&pid=MSNJVFeeds",
        "miniUrl": "https://zhanghao-zhoushan.cn/image/story/s3.OJ.o0QpPTigMvogcg.png"
      }
    ],
    "primaryImageUrl": "http://hpimges.blob.core.chinacloudapi.cn/coverstory/watermark_upsidedown_zh-cn11824550636_1920x1080.jpg",
    "imageUrl": "https://zhanghao-zhoushan.cn/image/large/BangkokVideo_ZH-CN8369071701_1366x768.jpg",
    "downLoadUrl": "https://zhanghao-zhoushan.cn/image/large/BangkokVideo_ZH-CN8369071701.jpg",
    "url": "http://cdn.nanxiongnandi.com/bing/BangkokVideo_ZH-CN8369071701_1366x768.jpg",
    "name": "BangkokVideo_ZH-CN8369071701.jpg",
    "provider": "© Gerard Kummer/500px",
    "copyright": "泰国，曼谷，高速公路延时摄影 (© Imaake/Shutterstock)(Bing China)",
    "Continent": "",
    "Country": "",
    "City": "",
    "Longitude": "",
    "Latitude": ""
  },
  {
    "dateString": "20160203",
    "date": 1454457600000,
    "attribute": "泰国，曼谷",
    "title": "天使之城",
    "story": [
      {
        "title": "风情之都",
        "au": "一个魅力四射的地方",
        "describe": "曼谷是泰国最大的城市，它既有厚重的历史，又有迷人的现代化风情。在这里，既可以沉浸在深厚的历史、文化、艺术中，又可以在喧闹的暹罗广场体验无限的活力。无论你追求什么，这座“天使之城”都不会让你失望。",
        "miniImage": "http://s.cn.bing.net/th?id=OJ.iWihdBlFZAeJPQ&pid=MSNJVFeeds",
        "miniUrl": "https://zhanghao-zhoushan.cn/image/story/s.OJ.iWihdBlFZAeJPQ.png"
      },
      {
        "title": "夜生活胜地",
        "au": "考山路",
        "describe": "熟悉曼谷的人，大多都知道考山路。它是背包客的大本营，也是著名的夜生活胜地。临街酒店、店铺遍布，更不乏酒吧和夜店。由于生活、娱乐都很方便，因此成为一个颇受游客欢迎的地方。",
        "miniImage": "http://s.cn.bing.net/th?id=OJ.zyPD0nu1jImx4w&pid=MSNJVFeeds",
        "miniUrl": "https://zhanghao-zhoushan.cn/image/story/s.OJ.zyPD0nu1jImx4w.png"
      },
      {
        "title": "最繁华商业区之一",
        "au": "曼谷唐人街",
        "describe": "唐人街是曼谷最繁华的商业区之一，已有200年历史。这里的房屋大都古旧，但商业非常繁荣，商铺几乎都有华人经营，对于前往此地旅游的华人来说，是个非常亲切的地方。",
        "miniImage": "http://s4.cn.bing.net/th?id=OJ.Se1sXJxN8Ov4wA&pid=MSNJVFeeds",
        "miniUrl": "https://zhanghao-zhoushan.cn/image/story/s4.OJ.Se1sXJxN8Ov4wA.png"
      }
    ],
    "primaryImageUrl": "http://hpimges.blob.core.chinacloudapi.cn/coverstory/watermark_bangkokvideo_zh-cn8369071701_1920x1080.jpg",
    "imageUrl": "https://zhanghao-zhoushan.cn/image/large/WillersleyCastle_ZH-CN9891472014_1366x768.jpg",
    "downLoadUrl": "https://zhanghao-zhoushan.cn/image/large/WillersleyCastle_ZH-CN9891472014.jpg",
    "url": "http://cdn.nanxiongnandi.com/bing/WillersleyCastle_ZH-CN9891472014_1366x768.jpg",
    "name": "WillersleyCastle_ZH-CN9891472014.jpg",
    "provider": "© Imaake/Shutterstock",
    "copyright": "英格兰，德比郡，克隆福德，韦勒斯利城堡内景 (© Design Pics/plainpicture)(Bing China)",
    "Continent": "",
    "Country": "泰国",
    "City": "曼谷",
    "Longitude": "100.3529229",
    "Latitude": "13.7251097"
  },
  {
    "dateString": "20160204",
    "date": 1454544000000,
    "attribute": "英国，德比郡，克隆福德",
    "title": "韦勒斯利城堡",
    "story": [
      {
        "title": "英国的那些古堡酒店",
        "au": "体验英伦贵族生活",
        "describe": "这座历史悠久的古堡坐落在山顶区国家公园的边缘，是一栋历史悠久的建筑。1782年，英国工程师理查得·雅克怀特先生将它买下，用作私人住宅，后来又在二战时期充当着医院的角色，如今却摇身变成一幢神秘的古堡酒店。",
        "miniImage": "http://s.cn.bing.net/th?id=OJ.aFLrA01QtG9n0g&pid=MSNJVFeeds",
        "miniUrl": "https://zhanghao-zhoushan.cn/image/story/s.OJ.aFLrA01QtG9n0g.png"
      },
      {
        "title": "婚礼热门地",
        "au": "达尔豪西古堡",
        "describe": "达尔豪西古堡位于美丽的爱丁堡，厚实的墙体和风格鲜明的屋顶让它散发着迷人气息。这里环境优雅、私密，房间内的立柱和华丽的帷幔让整个氛围浪漫无比，因此也成为不少人举办婚礼的首选。",
        "miniImage": "http://s2.cn.bing.net/th?id=OJ.f7ay3WKx2FWX7g&pid=MSNJVFeeds",
        "miniUrl": "https://zhanghao-zhoushan.cn/image/story/s2.OJ.f7ay3WKx2FWX7g.png"
      },
      {
        "title": "庄重神秘",
        "au": "安伯利古堡",
        "describe": "安伯利古堡拥有900年的历史，庄重感十足。白天对外开放，游客可以前往参观，到了夜晚则变身为一间私密的酒店，客人可以尽情体会与世隔绝的宁静之感。",
        "miniImage": "http://s1.cn.bing.net/th?id=OJ.0XgdU4VJpDfezQ&pid=MSNJVFeeds",
        "miniUrl": "https://zhanghao-zhoushan.cn/image/story/s1.OJ.0XgdU4VJpDfezQ.png"
      }
    ],
    "primaryImageUrl": "http://hpimges.blob.core.chinacloudapi.cn/coverstory/watermark_willersleycastle_zh-cn9891472014_1920x1080.jpg",
    "imageUrl": "https://zhanghao-zhoushan.cn/image/large/PondHockey_ZH-CN10274758143_1366x768.jpg",
    "downLoadUrl": "https://zhanghao-zhoushan.cn/image/large/PondHockey_ZH-CN10274758143.jpg",
    "url": "http://cdn.nanxiongnandi.com/bing/PondHockey_ZH-CN10274758143_1366x768.jpg",
    "name": "PondHockey_ZH-CN10274758143.jpg",
    "provider": "© Design Pics/plainpicture",
    "copyright": "美国，威斯康星州，在鹰河镇金湖上举办的美国池塘曲棍球全国锦标赛 (© George Steinmetz/Corbis)(Bing China)",
    "Continent": "",
    "Country": "英国",
    "City": "德比郡",
    "Longitude": "-2.1606847",
    "Latitude": "53.1179764"
  },
  {
    "dateString": "20160205",
    "date": 1454630400000,
    "attribute": "美国，威斯康星州",
    "title": "池塘曲棍球",
    "story": [
      {
        "title": "全美四大联盟",
        "au": "活力十足的国度",
        "describe": "\"池塘曲棍球全国锦标赛\"是美国的一项重要运动赛事，每年冬季都会在威斯康星州的鹰河举行。这天，会有超过300只球队争相竞技，虽是严冬，但场面热闹非凡。",
        "miniImage": "http://s1.cn.bing.net/th?id=OJ.MQbtU3pd7lY0ZA&pid=MSNJVFeeds",
        "miniUrl": "https://zhanghao-zhoushan.cn/image/story/s1.OJ.MQbtU3pd7lY0ZA.png"
      },
      {
        "title": "冰上的精灵",
        "au": "花样滑冰",
        "describe": "花样滑冰虽不是人人皆宜的运动，但作为冬季奥运会的比赛项目，仍有一大批忠实粉丝。旋转和跳跃是花样滑冰的主要动作，有空中旋转和组合跳跃，看得人连连称赞。",
        "miniImage": "http://s2.cn.bing.net/th?id=OJ.ZIxET9dinnfC2w&pid=MSNJVFeeds",
        "miniUrl": "https://zhanghao-zhoushan.cn/image/story/s2.OJ.ZIxET9dinnfC2w.png"
      },
      {
        "title": "冰上溜石",
        "au": "冰壶",
        "describe": "冰壶又称“冰上溜石”，是一种以队为单位的投掷性项目，也是冬奥会的比赛项目之一。冰壶为圆壶状，由苏格兰花岗岩制成，重量最大可达将近20公斤。",
        "miniImage": "http://s1.cn.bing.net/th?id=OJ.4kLrwTCa4hWL0A&pid=MSNJVFeeds",
        "miniUrl": "https://zhanghao-zhoushan.cn/image/story/s1.OJ.4kLrwTCa4hWL0A.png"
      }
    ],
    "primaryImageUrl": "http://hpimges.blob.core.chinacloudapi.cn/coverstory/watermark_pondhockey_zh-cn10274758143_1920x1080.jpg",
    "imageUrl": "https://zhanghao-zhoushan.cn/image/large/PiandiGembro_ZH-CN12053478103_1366x768.jpg",
    "downLoadUrl": "https://zhanghao-zhoushan.cn/image/large/PiandiGembro_ZH-CN12053478103.jpg",
    "url": "http://cdn.nanxiongnandi.com/bing/PiandiGembro_ZH-CN12053478103_1366x768.jpg",
    "name": "PiandiGembro_ZH-CN12053478103.jpg",
    "provider": "© George Steinmetz/Corbis",
    "copyright": "意大利，靠近阿普里卡，Pian Gembro 自然保护区的迷雾沼泽 (© Robert Harding World Imagery/Offset)(Bing China)",
    "Continent": "",
    "Country": "美国",
    "City": "威斯康星州",
    "Longitude": "-92.0694187",
    "Latitude": "44.7682484"
  },
  {
    "dateString": "20160206",
    "date": 1454716800000,
    "attribute": "意大利",
    "title": "Pian di Gembro自然保护区",
    "story": [
      {
        "title": "欧洲的宝石",
        "au": "醉人的自然美景",
        "describe": "Pian di Gembro位于瑞士和意大利的边境处，是一片荒芜的天然沼泽地。隐藏在山间，植被茂密，若是运气好的话，能看见朦胧雾气附着于深灰色的沼泽地上。",
        "miniImage": "http://s2.cn.bing.net/th?id=OJ.t8hC3Z2lkjR9Rw&pid=MSNJVFeeds",
        "miniUrl": "https://zhanghao-zhoushan.cn/image/story/s2.OJ.t8hC3Z2lkjR9Rw.png"
      },
      {
        "title": "悬崖上的浪漫",
        "au": "福莱甘兹罗斯小镇",
        "describe": "位于希腊基克拉迪群岛上，这里没有两层楼以上的建筑，没有琳琅满目的商铺和密密麻麻的游人，有的只是闲适的浪漫。波涛拍打着岸边的卵石，羊群在山丘上散步，让人无比希望时光能永远停留在此刻。",
        "miniImage": "http://s4.cn.bing.net/th?id=OJ.ScJe0AkWVRE9hA&pid=MSNJVFeeds",
        "miniUrl": "https://zhanghao-zhoushan.cn/image/story/s4.OJ.ScJe0AkWVRE9hA.png"
      },
      {
        "title": "教皇出生地",
        "au": "皮恩扎小镇",
        "describe": "皮恩扎小镇位于奥尔恰山谷腹地，是教皇皮乌斯二世的出生地。城市围绕着皮乌斯二世广场为中心展开，如宝石一般镶嵌在奥尔恰山谷绵延起伏的风光中。",
        "miniImage": "http://s4.cn.bing.net/th?id=OJ.zwzxdu7uKXN0pw&pid=MSNJVFeeds",
        "miniUrl": "https://zhanghao-zhoushan.cn/image/story/s4.OJ.zwzxdu7uKXN0pw.png"
      }
    ],
    "primaryImageUrl": "http://hpimges.blob.core.chinacloudapi.cn/coverstory/watermark_piandigembro_zh-cn12053478103_1920x1080.jpg",
    "imageUrl": "https://zhanghao-zhoushan.cn/image/large/TraditionalBanners_ZH-CN8428576502_1366x768.jpg",
    "downLoadUrl": "https://zhanghao-zhoushan.cn/image/large/TraditionalBanners_ZH-CN8428576502.jpg",
    "url": "http://cdn.nanxiongnandi.com/bing/TraditionalBanners_ZH-CN8428576502_1366x768.jpg",
    "name": "TraditionalBanners_ZH-CN8428576502.jpg",
    "provider": "© Robert Harding World Imagery/Offset",
    "copyright": "[今日除夕]中国，香港，农历新年贴门联 (© Ulana Switucha/Alamy Stock Photo)(Bing China)",
    "Continent": "",
    "Country": "意大利",
    "City": "阿普里卡",
    "Longitude": "10.1051235",
    "Latitude": "46.1265842"
  },
  {
    "dateString": "20160207",
    "date": 1454803200000,
    "attribute": "中国",
    "title": "除夕 福到",
    "story": [
      {
        "title": "除夕之夜",
        "au": "一年中最幸福的日子",
        "describe": "又是一年除夕夜，和家人一起，将“福”字贴在门上，年味儿又更浓了。将“福”字倒过来贴，寓意福气已到，愿家中的每个人来年都能顺顺利利、福气满满。",
        "miniImage": "http://s2.cn.bing.net/th?id=OJ.Wm9Xt7ZBu5gBxg&pid=MSNJVFeeds",
        "miniUrl": "https://zhanghao-zhoushan.cn/image/story/s2.OJ.Wm9Xt7ZBu5gBxg.png"
      },
      {
        "title": "祛“年”迎新",
        "au": "熬年守岁",
        "describe": "守岁就是除夕当晚熬夜不睡觉，迎接新一年的来临。关于守岁的来历有一个传说，相传在太古时期，有一种猛兽名叫年，每到除夕之夜就会出现。它专吃禽类，有时还会吃人，为了驱赶它，人们在这晚都不睡觉，并在午夜之时放起年最害怕的烟花爆竹，以将它吓走，于是便有了熬年守岁这一习俗。",
        "miniImage": "http://s.cn.bing.net/th?id=OJ.o8sbma37lwDlNg&pid=MSNJVFeeds",
        "miniUrl": "https://zhanghao-zhoushan.cn/image/story/s.OJ.o8sbma37lwDlNg.png"
      },
      {
        "title": "家中守护神",
        "au": "贴门神",
        "describe": "贴门神起源一千多年前的后蜀时期，专用来赶走妖魔鬼怪。直至今日，为了祈求全家人健康、平安，许多人家仍保留了贴门神的习惯。在汉族民间，门神是正气和武力的象征，将他们的画像贴在门上，一切鬼怪都会望而生畏。",
        "miniImage": "http://s.cn.bing.net/th?id=OJ.JQW0F0oD62KsFQ&pid=MSNJVFeeds",
        "miniUrl": "https://zhanghao-zhoushan.cn/image/story/s.OJ.JQW0F0oD62KsFQ.png"
      }
    ],
    "primaryImageUrl": "http://hpimges.blob.core.chinacloudapi.cn/coverstory/watermark_traditionalbanners_zh-cn8428576502_1920x1080.jpg",
    "imageUrl": "https://zhanghao-zhoushan.cn/image/large/SnubNosedMonkey_ZH-CN11146495688_1366x768.jpg",
    "downLoadUrl": "https://zhanghao-zhoushan.cn/image/large/SnubNosedMonkey_ZH-CN11146495688.jpg",
    "url": "http://cdn.nanxiongnandi.com/bing/SnubNosedMonkey_ZH-CN11146495688_1366x768.jpg",
    "name": "SnubNosedMonkey_ZH-CN11146495688.jpg",
    "provider": "© Ulana Switucha / Alamy Stock Photo",
    "copyright": "中国，秦岭，小金丝猴 (© Nate Polta/Tandem Stills + Motion)(Bing China)",
    "Continent": "",
    "Country": "",
    "City": "",
    "Longitude": "",
    "Latitude": ""
  },
  {
    "dateString": "20160208",
    "date": 1454889600000,
    "attribute": "中国，台湾",
    "title": "大年初一",
    "story": [
      {
        "title": "新年到",
        "au": "年初新气象",
        "describe": "与家人一起迈向新一年，美好的生活就这样开始了。走亲访友，拜年送祝福，共同享用一顿丰盛的晚餐后，一起点燃烟花，看黑暗的夜空被灿烂烟花划破，热闹、喜庆，有让人觉得幸福无比。",
        "miniImage": "http://s3.cn.bing.net/th?id=OJ.xJtHA89aNHNtaA&pid=MSNJVFeeds",
        "miniUrl": "https://zhanghao-zhoushan.cn/image/story/s3.OJ.xJtHA89aNHNtaA.png"
      },
      {
        "title": "火树银花的浪漫夜空",
        "au": "放烟花",
        "describe": "初一当晚放烟花是个流传已久的习俗。晚饭后，全家人来到空旷的地方，聚在一起，将烟火点燃，看着夜空被璀璨的花火点亮，整片天空像是一片火树银花的海洋。",
        "miniImage": "http://s.cn.bing.net/th?id=OJ.V40NjGey49Rblw&pid=MSNJVFeeds",
        "miniUrl": "https://zhanghao-zhoushan.cn/image/story/s.OJ.V40NjGey49Rblw.png"
      },
      {
        "title": "更岁交子",
        "au": "吃饺子",
        "describe": "饺子是春节时不可缺少的食物，形如元宝，吃下去，有“招财进宝”的寓意。饺子的馅料大有可发挥的余地，人们喜欢往里塞一些喜气的东西，以表达对新年的美好盼望。",
        "miniImage": "http://s4.cn.bing.net/th?id=OJ.0UFiAoBKn7YStA&pid=MSNJVFeeds",
        "miniUrl": "https://zhanghao-zhoushan.cn/image/story/s4.OJ.0UFiAoBKn7YStA.png"
      }
    ],
    "primaryImageUrl": "http://hpimges.blob.core.chinacloudapi.cn/coverstory/watermark_snubnosedmonkey_zh-cn11146495688_1920x1080.jpg",
    "imageUrl": "https://zhanghao-zhoushan.cn/image/large/SquirrelBowl_ZH-CN6988757053_1366x768.jpg",
    "downLoadUrl": "https://zhanghao-zhoushan.cn/image/large/SquirrelBowl_ZH-CN6988757053.jpg",
    "url": "http://cdn.nanxiongnandi.com/bing/SquirrelBowl_ZH-CN6988757053_1366x768.jpg",
    "name": "SquirrelBowl_ZH-CN6988757053.jpg",
    "provider": "© Clover No. 7 Photography/Moment/Getty Images",
    "copyright": "欧亚红松鼠正在行动 (© Vadim Trunov/Solent News/REX Shutterstock)(Bing China)",
    "Continent": "",
    "Country": "中国",
    "City": "台湾高雄",
    "Longitude": "120.0518919",
    "Latitude": "22.9739411"
  },
  {
    "dateString": "20160209",
    "date": 1454976000000,
    "attribute": "亚欧大陆",
    "title": "欧亚红松鼠",
    "story": [
      {
        "title": "身形小而灵巧",
        "au": "透着一股子机灵劲儿",
        "describe": "身子小而灵巧，毛发顺滑亮丽，脸庞清秀可人，让人忍不住想要上前抚摸。大大的尾巴在身后晃动着，身姿矫健灵动，是草丛中的红色小精灵，哪里有它们，哪里就有勃勃生机。",
        "miniImage": "http://s2.cn.bing.net/th?id=OJ.nc9BU0hXbko09g&pid=MSNJVFeeds",
        "miniUrl": "https://zhanghao-zhoushan.cn/image/story/s2.OJ.nc9BU0hXbko09g.png"
      },
      {
        "title": "晚冬和初夏",
        "au": "生长繁殖",
        "describe": "欧亚红松鼠的交配期一般在晚冬的2至3月和夏季6、7月的时候。雌性红松鼠的孕期一般为一个多月，每次一般可产3－4只小松鼠。它们的寿命一般为3年，偶尔有活7年的例子，但最多不会超过十年。",
        "miniImage": "http://s4.cn.bing.net/th?id=OJ.TLU7HtJhpfYOog&pid=MSNJVFeeds",
        "miniUrl": "https://zhanghao-zhoushan.cn/image/story/s4.OJ.TLU7HtJhpfYOog.png"
      },
      {
        "title": "欧洲的保护动物",
        "au": "种群现状",
        "describe": "这个种类的松鼠有着亮丽的皮毛，常会因此而受到捕猎，目前已被列为保护动物。为了保护它们，已有不少国家签订保育公约，并限制灰松鼠的引进，以此来保证它们能够正常生长。",
        "miniImage": "http://s3.cn.bing.net/th?id=OJ.ynuUkDWZ2ZRHgQ&pid=MSNJVFeeds",
        "miniUrl": "https://zhanghao-zhoushan.cn/image/story/s3.OJ.ynuUkDWZ2ZRHgQ.png"
      }
    ],
    "primaryImageUrl": "http://hpimges.blob.core.chinacloudapi.cn/coverstory/watermark_squirrelbowl_zh-cn6988757053_1920x1080.jpg",
    "imageUrl": "https://zhanghao-zhoushan.cn/image/large/HeartHoleDivers_ZH-CN12875142412_1366x768.jpg",
    "downLoadUrl": "https://zhanghao-zhoushan.cn/image/large/HeartHoleDivers_ZH-CN12875142412.jpg",
    "url": "http://cdn.nanxiongnandi.com/bing/HeartHoleDivers_ZH-CN12875142412_1366x768.jpg",
    "name": "HeartHoleDivers_ZH-CN12875142412.jpg",
    "provider": "© Vadim Trunov/Solent News/REX Shutterstock",
    "copyright": "美国，关岛，蓝洞入口处的潜水者 (© Aflo Relax/Masterfile)(Bing China)",
    "Continent": "",
    "Country": "",
    "City": "",
    "Longitude": "",
    "Latitude": ""
  },
  {
    "dateString": "20160210",
    "date": 1455062400000,
    "attribute": "美国，关岛",
    "title": "在海中嬉戏",
    "story": [
      {
        "title": "神秘关岛",
        "au": "离中国大陆最近的美国领土",
        "describe": "在关岛的西南处的海域，有一个神秘梦幻的海中蓝洞。洞深大约300尺，周围海水清澈无比，时常会有色彩绚丽的鱼群游过，是个潜水胜地。潜入水中，抬头仰望，可看到迷人洞口，唯美画面让人难忘。",
        "miniImage": "http://s.cn.bing.net/th?id=OJ.Ivubrz0gFPsoxg&pid=MSNJVFeeds",
        "miniUrl": "https://zhanghao-zhoushan.cn/image/story/s.OJ.Ivubrz0gFPsoxg.png"
      },
      {
        "title": "海的教堂",
        "au": "彩虹教堂",
        "describe": "彩虹教堂又被称为海的教堂，内外皆是纯白色，看起来轻盈无比，就像浮在水面上一样。教堂的玻璃是彩色的，与洁白的墙体搭配出浪漫唯美的画面，因此又是举办婚礼的热门地。",
        "miniImage": "http://s4.cn.bing.net/th?id=OJ.Tg9Kc7Sh2htTGw&pid=MSNJVFeeds",
        "miniUrl": "https://zhanghao-zhoushan.cn/image/story/s4.OJ.Tg9Kc7Sh2htTGw.png"
      },
      {
        "title": "大珠小珠落玉盘",
        "au": "塔洛佛佛瀑布公园",
        "describe": "瀑布位于关岛南部，是个非常受欢迎的景点。瀑布源于乌干河，总共有10米落差，呈阶梯状飞流而下，大老远就能听见水花声，仿佛大珠小珠落玉盘一般。",
        "miniImage": "http://s2.cn.bing.net/th?id=OJ.yMHl0VNZpnkaOA&pid=MSNJVFeeds",
        "miniUrl": "https://zhanghao-zhoushan.cn/image/story/s2.OJ.yMHl0VNZpnkaOA.png"
      }
    ],
    "primaryImageUrl": "http://hpimges.blob.core.chinacloudapi.cn/coverstory/watermark_heartholedivers_zh-cn12875142412_1920x1080.jpg",
    "imageUrl": "https://zhanghao-zhoushan.cn/image/large/SalzachRiverVideo_ZH-CN10853485740_1366x768.jpg",
    "downLoadUrl": "https://zhanghao-zhoushan.cn/image/large/SalzachRiverVideo_ZH-CN10853485740.jpg",
    "url": "http://cdn.nanxiongnandi.com/bing/SalzachRiverVideo_ZH-CN10853485740_1366x768.jpg",
    "name": "SalzachRiverVideo_ZH-CN10853485740.jpg",
    "provider": "©Aflo Relax/Masterfile",
    "copyright": "奥地利，萨尔兹河 (© T Schäffer/age fotostock)(Bing China)",
    "Continent": "",
    "Country": "美国",
    "City": "关岛",
    "Longitude": "144.6473736",
    "Latitude": "13.4489395"
  },
  {
    "dateString": "20160211",
    "date": 1455148800000,
    "attribute": "奥地利，萨尔兹河",
    "title": "冬日的萨尔兹河",
    "story": [
      {
        "title": "奥地利",
        "au": "音乐王国",
        "describe": "萨尔兹河在萨尔兹堡中穿城而过，总长225千米，是横跨奥地利和德国最长水流最大的一条河流，冬天的萨尔兹河幽静美丽，两岸巴洛克风格的建筑倒映在如镜一般的湖面，就像身在童话世界。",
        "miniImage": "http://s.cn.bing.net/th?id=OJ.e60d07itTsJ7WA&pid=MSNJVFeeds",
        "miniUrl": "https://zhanghao-zhoushan.cn/image/story/s.OJ.e60d07itTsJ7WA.png"
      },
      {
        "title": "富有灵性的观光胜地",
        "au": "哈尔施塔特湖",
        "describe": "哈尔施塔特湖碧绿如宝石一般，青山白云倒映其中，宛如童话世界。清晨的湖面笼罩着薄雾，不时一叶扁舟划过，这些都是最富有灵气的靓丽风景。",
        "miniImage": "http://s.cn.bing.net/th?id=OJ.VTW84QFynDkGLg&pid=MSNJVFeeds",
        "miniUrl": "https://zhanghao-zhoushan.cn/image/story/s.OJ.VTW84QFynDkGLg.png"
      },
      {
        "title": "创意十足的建筑",
        "au": "百水公寓",
        "describe": "这座外形独特的公寓位于维也纳，由著名建筑设计师百水先生亲自打造。公寓的外墙面上大块鲜艳的颜色拼接在一起，十分亮眼。整个建筑的外观都找不到一条直线，造型新颖独特。目前公寓中的住客大都是艺术家，让整个公寓都带着浓厚的艺术气息。",
        "miniImage": "http://s1.cn.bing.net/th?id=OJ.00sTb0aK4FtPDQ&pid=MSNJVFeeds",
        "miniUrl": "https://zhanghao-zhoushan.cn/image/story/s1.OJ.00sTb0aK4FtPDQ.png"
      }
    ],
    "primaryImageUrl": "http://hpimges.blob.core.chinacloudapi.cn/coverstory/watermark_salzachrivervideo_zh-cn10853485740_1920x1080.jpg",
    "imageUrl": "https://zhanghao-zhoushan.cn/image/large/TallGrass_ZH-CN12379752699_1366x768.jpg",
    "downLoadUrl": "https://zhanghao-zhoushan.cn/image/large/TallGrass_ZH-CN12379752699.jpg",
    "url": "http://cdn.nanxiongnandi.com/bing/TallGrass_ZH-CN12379752699_1366x768.jpg",
    "name": "TallGrass_ZH-CN12379752699.jpg",
    "provider": "© T Schäffer/age fotostock",
    "copyright": "津巴布韦，万基国家公园的雄狮 (© Jeremy Woodhouse/Getty Images)(Bing China)",
    "Continent": "",
    "Country": "奥地利",
    "City": "萨尔兹河",
    "Longitude": "6.2866127",
    "Latitude": "49.1957535"
  },
  {
    "dateString": "20160212",
    "date": 1455235200000,
    "attribute": "津巴布韦",
    "title": "魅力雄狮",
    "story": [
      {
        "title": "津巴布韦",
        "au": "纯粹之美",
        "describe": "在广袤的万基国家公园里，栖居着种类繁多的野生动物群，其中不乏飒爽矫健的雄狮。他们时而在丛林中沉睡，时而在旷野上厮打，旺盛的经历，和火热的生命力都在它们身上得以完美体现。",
        "miniImage": "http://s2.cn.bing.net/th?id=OJ.NJNp0iuBX0MvMQ&pid=MSNJVFeeds",
        "miniUrl": "https://zhanghao-zhoushan.cn/image/story/s2.OJ.NJNp0iuBX0MvMQ.png"
      },
      {
        "title": "沉醉在大自然中",
        "au": "东部高地",
        "describe": "在津巴布韦东部有纵深南北的延绵山脉，它风光旖旎，有着多样的迷人景色，让人沉醉在大自然中。东部地区的地貌丰富多样，植物种类也丰富多彩，松林、蔷薇花、凤凰木等都是常见的美物，非常适合骑马散步。",
        "miniImage": "http://s2.cn.bing.net/th?id=OJ.CAMKZoqMOA3EuA&pid=MSNJVFeeds",
        "miniUrl": "https://zhanghao-zhoushan.cn/image/story/s2.OJ.CAMKZoqMOA3EuA.png"
      },
      {
        "title": "妙趣横生",
        "au": "卡里巴水库",
        "describe": "水库横跨赞比亚和津巴布韦两国边境，竣工后，自1958年至1963年完成蓄水。这里是津巴布韦重要的渔业产地，也是尼罗鳄、河马等动物的休憩地。",
        "miniImage": "http://s4.cn.bing.net/th?id=OJ.js2l6G10RG0Nmw&pid=MSNJVFeeds",
        "miniUrl": "https://zhanghao-zhoushan.cn/image/story/s4.OJ.js2l6G10RG0Nmw.png"
      }
    ],
    "primaryImageUrl": "http://hpimges.blob.core.chinacloudapi.cn/coverstory/watermark_tallgrass_zh-cn12379752699_1920x1080.jpg",
    "imageUrl": "https://zhanghao-zhoushan.cn/image/large/BledSnow_ZH-CN8899741731_1366x768.jpg",
    "downLoadUrl": "https://zhanghao-zhoushan.cn/image/large/BledSnow_ZH-CN8899741731.jpg",
    "url": "http://cdn.nanxiongnandi.com/bing/BledSnow_ZH-CN8899741731_1366x768.jpg",
    "name": "BledSnow_ZH-CN8899741731.jpg",
    "provider": "© Jeremy Woodhouse/Getty Images",
    "copyright": "斯洛文尼亚，布莱德湖 (© Dan Briski/500px)(Bing China)",
    "Continent": "",
    "Country": "",
    "City": "",
    "Longitude": "",
    "Latitude": ""
  },
  {
    "dateString": "20160213",
    "date": 1455321600000,
    "attribute": "斯洛文尼亚，布莱德湖",
    "title": "雪中城堡",
    "story": [
      {
        "title": "布莱德湖",
        "au": "浪漫的湖光山色",
        "describe": "静谧的布莱德湖湖面上，厚厚的冰层覆盖着。湖心岛上白雪皑皑，巨崖上的城堡在雪中挺立，沉稳、大气，又不乏梦幻的气氛。",
        "miniImage": "http://s1.cn.bing.net/th?id=OJ.rSu43qC1Zkw38w&pid=MSNJVFeeds",
        "miniUrl": "https://zhanghao-zhoushan.cn/image/story/s1.OJ.rSu43qC1Zkw38w.png"
      },
      {
        "title": "亲近大自然的绝佳方式",
        "au": "农家旅游",
        "describe": "布莱德湖周边一直以新鲜空气和梦幻的风景吸引着游客。湖边小镇里，不少农家开始向游客开放，类似乡间旅馆。住在这里，可以体验当地人的生活方式，还能尝试滑雪、跳伞、玩滑翔机等刺激的活动。",
        "miniImage": "http://s1.cn.bing.net/th?id=OJ.Ezn89D9ffi0RjQ&pid=MSNJVFeeds",
        "miniUrl": "https://zhanghao-zhoushan.cn/image/story/s1.OJ.Ezn89D9ffi0RjQ.png"
      },
      {
        "title": "浪漫传说",
        "au": "教堂里的大钟",
        "describe": "传说在16世纪，一对青年夫妇来到这里游玩，因陶醉于此地唯美的湖光山色而定居于此。后来丈夫应征入伍，战死沙场，妻子便花掉所有家产购铸了一口巨大的钟，以寄托对丈夫的哀思。现在湖心教堂里的那口178公斤的大钟，正是源于这个美丽的传说。",
        "miniImage": "http://s3.cn.bing.net/th?id=OJ.lfdTetinAk3Yrg&pid=MSNJVFeeds",
        "miniUrl": "https://zhanghao-zhoushan.cn/image/story/s3.OJ.lfdTetinAk3Yrg.png"
      }
    ],
    "primaryImageUrl": "http://hpimges.blob.core.chinacloudapi.cn/coverstory/watermark_bledsnow_zh-cn8899741731_1920x1080.jpg",
    "imageUrl": "https://zhanghao-zhoushan.cn/image/large/CourtingCranes_ZH-CN10152658125_1366x768.jpg",
    "downLoadUrl": "https://zhanghao-zhoushan.cn/image/large/CourtingCranes_ZH-CN10152658125.jpg",
    "url": "http://cdn.nanxiongnandi.com/bing/CourtingCranes_ZH-CN10152658125_1366x768.jpg",
    "name": "CourtingCranes_ZH-CN10152658125.jpg",
    "provider": "© Dan Briski/500px",
    "copyright": "[情人节快乐]日本，北海道，丹顶鹤在舞蹈 (© Paul McKenzie/Minden Pictures)(Bing China)",
    "Continent": "",
    "Country": "斯洛文尼亚",
    "City": "布莱德湖",
    "Longitude": "14.0865061",
    "Latitude": "46.3639118"
  },
  {
    "dateString": "20160214",
    "date": 1455408000000,
    "attribute": "日本，北海道",
    "title": "雪中丹顶鹤",
    "story": [
      {
        "title": "冬天的北海道",
        "au": "浪漫的冰雪世界",
        "describe": "冬日里的湿地白雪皑皑，水面雾气蔼蔼，雪白的丹顶鹤站在水中，时而扑闪着翅膀，时而抖动洁白的身躯…… 和爱人站在桥上，将这一浪漫美景尽收眼底，按下快门，将情人节的甜蜜时光定格在此刻。",
        "miniImage": "http://s2.cn.bing.net/th?id=OJ.OA4240Rwpje9dw&pid=MSNJVFeeds",
        "miniUrl": "https://zhanghao-zhoushan.cn/image/story/s2.OJ.OA4240Rwpje9dw.png"
      },
      {
        "title": "梦幻的冰雪王国",
        "au": "温泉冰瀑",
        "describe": "今年温泉冰瀑节已在上川町的层云峡温泉开幕，将持续到3月27日。五光十色的灯光打在雪白的冰雕上，就像一个浪漫的冰雪世界。",
        "miniImage": "http://s3.cn.bing.net/th?id=OJ.Up80CDdlrsA6Bw&pid=MSNJVFeeds",
        "miniUrl": "https://zhanghao-zhoushan.cn/image/story/s3.OJ.Up80CDdlrsA6Bw.png"
      },
      {
        "title": "泡汤胜地",
        "au": "地狱谷",
        "describe": "地狱谷位于温泉之乡登别，被白雪覆盖着的山谷中，时刻冒着腾腾热气。在露天温泉池里泡着，雪花飘落在发梢上，周围万籁俱寂，心里也踏实，沉静。",
        "miniImage": "http://s4.cn.bing.net/th?id=OJ.1FGRhtCd0qJzJA&pid=MSNJVFeeds",
        "miniUrl": "https://zhanghao-zhoushan.cn/image/story/s4.OJ.1FGRhtCd0qJzJA.png"
      }
    ],
    "primaryImageUrl": "http://hpimges.blob.core.chinacloudapi.cn/coverstory/watermark_courtingcranes_zh-cn10152658125_1920x1080.jpg",
    "imageUrl": "https://zhanghao-zhoushan.cn/image/large/Eistobel_ZH-CN9499709851_1366x768.jpg",
    "downLoadUrl": "https://zhanghao-zhoushan.cn/image/large/Eistobel_ZH-CN9499709851.jpg",
    "url": "http://cdn.nanxiongnandi.com/bing/Eistobel_ZH-CN9499709851_1366x768.jpg",
    "name": "Eistobel_ZH-CN9499709851.jpg",
    "provider": "© Paul McKenzie/Minden Pictures",
    "copyright": "德国，巴伐利亚，Allgäu，Eistobel峡谷的冰柱 (© Claus Puhlmann/500px)(Bing China)",
    "Continent": "",
    "Country": "",
    "City": "",
    "Longitude": "",
    "Latitude": ""
  },
  {
    "dateString": "20160215",
    "date": 1455494400000,
    "attribute": "德国，巴伐利亚",
    "title": "冬日巴伐利亚",
    "story": [
      {
        "title": "唯美的巴伐利亚",
        "au": "山水皆美的童话梦境",
        "describe": "如果说夏日的巴伐利亚是浪漫而温情的，那冬日的巴伐利亚就是神秘而梦幻的。崇山峻岭、险峻峡谷间纷纷出现晶莹剔透的巨型冰柱，俨然一个惊艳无比的冰雪王国。",
        "miniImage": "http://s1.cn.bing.net/th?id=OJ.YV2QFWj9cmye9g&pid=MSNJVFeeds",
        "miniUrl": "https://zhanghao-zhoushan.cn/image/story/s1.OJ.YV2QFWj9cmye9g.png"
      },
      {
        "title": "车控们的天堂",
        "au": "宝马世界",
        "describe": "集汽车交付、体验馆、博物馆与活动现场于一体的宝马世界实在是爱车一族的天堂。120多米长的汽车展示区向客人们展示着全新的宝马系列产品，面向小朋友还开设了青少年课堂区，大人小孩都可以玩的不亦乐乎。",
        "miniImage": "http://s4.cn.bing.net/th?id=OJ.PE9mU400nVFwrQ&pid=MSNJVFeeds",
        "miniUrl": "https://zhanghao-zhoushan.cn/image/story/s4.OJ.PE9mU400nVFwrQ.png"
      },
      {
        "title": "“酒鬼”们的打卡地",
        "au": "皇家啤酒馆",
        "describe": "啤酒馆始建于1589年，是当时的皇家啤酒厂，历史非常悠久。整个建筑可容纳5000人，客人可以在此举办大型派对，一起欢饮。酒厂主要酿造HB啤酒，每天都有近万升的啤酒运到各个酒馆和餐厅里。",
        "miniImage": "http://s3.cn.bing.net/th?id=OJ.uoHJ3WhH4TM5jg&pid=MSNJVFeeds",
        "miniUrl": "https://zhanghao-zhoushan.cn/image/story/s3.OJ.uoHJ3WhH4TM5jg.png"
      }
    ],
    "primaryImageUrl": "http://hpimges.blob.core.chinacloudapi.cn/coverstory/watermark_eistobel_zh-cn9499709851_1920x1080.jpg",
    "imageUrl": "https://zhanghao-zhoushan.cn/image/large/BetAmanuel_ZH-CN7364286844_1366x768.jpg",
    "downLoadUrl": "https://zhanghao-zhoushan.cn/image/large/BetAmanuel_ZH-CN7364286844.jpg",
    "url": "http://cdn.nanxiongnandi.com/bing/BetAmanuel_ZH-CN7364286844_1366x768.jpg",
    "name": "BetAmanuel_ZH-CN7364286844.jpg",
    "provider": "© Claus Puhlmann/500px",
    "copyright": "埃塞俄比亚，拉利贝拉古城，妇女出现在通往Bet Amanue教堂的地道口 (© Andrew McConnell/plainpicture)(Bing China)",
    "Continent": "",
    "Country": "",
    "City": "",
    "Longitude": "",
    "Latitude": ""
  },
  {
    "dateString": "20160216",
    "date": 1455580800000,
    "attribute": "埃塞俄比亚，拉利贝拉古城",
    "title": "岩石教堂",
    "story": [
      {
        "title": "魅力古城",
        "au": "神秘莫测",
        "describe": "相传12世纪埃塞俄比亚第七代国王在梦中得到神谕，要在这里建造一座耶路撒冷城，并用一整块岩石打造一座教堂。于是国王便在海拔2600米的岩石上，花了30年时间，动用5千人工，凿刻出11座岩石教堂，打造出耶路撒冷城之外的又一座圣城。",
        "miniImage": "http://s4.cn.bing.net/th?id=OJ.55M0m48FDg7X1Q&pid=MSNJVFeeds",
        "miniUrl": "https://zhanghao-zhoushan.cn/image/story/s4.OJ.55M0m48FDg7X1Q.png"
      },
      {
        "title": "多瑙河两岸的哥德式建筑",
        "au": "布达城堡区",
        "describe": "匈牙利首都布达佩斯被多瑙河分成东西两岸，西岸为布达，东岸为佩斯。13世纪起匈牙利帝国在布达建造了王宫以及一批哥特式和巴洛克式的建筑，而佩斯则逐渐形成商业中心。",
        "miniImage": "http://s1.cn.bing.net/th?id=OJ.EQF85FHLVjeP8g&pid=MSNJVFeeds",
        "miniUrl": "https://zhanghao-zhoushan.cn/image/story/s1.OJ.EQF85FHLVjeP8g.png"
      },
      {
        "title": "爱尔兰西南部的神秘岛屿",
        "au": "斯凯利格·迈克尔岛",
        "describe": "迈克尔岛位于爱尔兰西南部12海里外的海域上，是一座与世隔绝的孤岛。岛上的斯凯利格·迈克尔修道院建于公元7世纪，是欧洲现存最古老的修道院之一。房屋形如蜂窝，没有丝毫修饰的痕迹，古老而神秘。",
        "miniImage": "http://s4.cn.bing.net/th?id=OJ.l80TarYzKlXG0Q&pid=MSNJVFeeds",
        "miniUrl": "https://zhanghao-zhoushan.cn/image/story/s4.OJ.l80TarYzKlXG0Q.png"
      }
    ],
    "primaryImageUrl": "http://hpimges.blob.core.chinacloudapi.cn/coverstory/watermark_betamanuel_zh-cn7364286844_1920x1080.jpg",
    "imageUrl": "https://zhanghao-zhoushan.cn/image/large/GGBView_ZH-CN13606118254_1366x768.jpg",
    "downLoadUrl": "https://zhanghao-zhoushan.cn/image/large/GGBView_ZH-CN13606118254.jpg",
    "url": "http://cdn.nanxiongnandi.com/bing/GGBView_ZH-CN13606118254_1366x768.jpg",
    "name": "GGBView_ZH-CN13606118254.jpg",
    "provider": "© Andrew McConnell/plainpicture",
    "copyright": "加利福尼亚，连接着马林郡的金门大桥 (© George Steinmetz/Corbis)(Bing China)",
    "Continent": "",
    "Country": "埃塞俄比亚",
    "City": "拉利贝拉古城",
    "Longitude": "39.0379643",
    "Latitude": "12.0319961"
  },
  {
    "dateString": "20160217",
    "date": 1455667200000,
    "attribute": "美国，旧金山",
    "title": "雄伟的金门大桥",
    "story": [
      {
        "title": "魅力旧金山",
        "au": "阳光海岸 美丽浪漫",
        "describe": "这个加州地标早已为世人所熟知，这座世界上最大的单孔吊桥之一，是旧金山一张闪亮的名片。红色的桥体横跨旧金山湾和金门海峡，雄伟壮观。",
        "miniImage": "http://s2.cn.bing.net/th?id=OJ.vsCZbQOI2lX0VA&pid=MSNJVFeeds",
        "miniUrl": "https://zhanghao-zhoushan.cn/image/story/s2.OJ.vsCZbQOI2lX0VA.png"
      },
      {
        "title": "将迷人夜色尽收眼底",
        "au": "双子峰",
        "describe": "双子峰是旧金山唯一的天然山丘，登上它是一件很辛苦的事，但到达山顶后，美丽的旧金山城市景色会是最好的回报。入夜后，华丽的城市夜色和红色金门大桥映入眼帘，美的令人窒息。",
        "miniImage": "http://s.cn.bing.net/th?id=OJ.f9Ekv0kRZabFWA&pid=MSNJVFeeds",
        "miniUrl": "https://zhanghao-zhoushan.cn/image/story/s.OJ.f9Ekv0kRZabFWA.png"
      },
      {
        "title": "葡萄酒王国",
        "au": "纳帕谷",
        "describe": "纳帕谷位于旧金山以北，是有名的葡萄酒产区。坐落在丘陵地带，类似平原又颇有起伏，景色颇美。这里的气候温暖宜人，和煦的阳光为葡萄生长提供了很好的条件。",
        "miniImage": "http://s1.cn.bing.net/th?id=OJ.0R0LMQ7pGcSMew&pid=MSNJVFeeds",
        "miniUrl": "https://zhanghao-zhoushan.cn/image/story/s1.OJ.0R0LMQ7pGcSMew.png"
      }
    ],
    "primaryImageUrl": "http://hpimges.blob.core.chinacloudapi.cn/coverstory/watermark_ggbview_zh-cn13606118254_1920x1080.jpg",
    "imageUrl": "https://zhanghao-zhoushan.cn/image/large/Pluto_ZH-CN12044921779_1366x768.jpg",
    "downLoadUrl": "https://zhanghao-zhoushan.cn/image/large/Pluto_ZH-CN12044921779.jpg",
    "url": "http://cdn.nanxiongnandi.com/bing/Pluto_ZH-CN12044921779_1366x768.jpg",
    "name": "Pluto_ZH-CN12044921779.jpg",
    "provider": "© George Steinmetz/Corbis",
    "copyright": "NASA新视野号宇宙飞船拍摄的一张色彩增强的冥王星照片 (© NASA/JHUAPL/SwRI)(Bing China)",
    "Continent": "",
    "Country": "美国",
    "City": "旧金山",
    "Longitude": "-122.419639587402",
    "Latitude": "37.7771186828613"
  },
  {
    "dateString": "20160218",
    "date": 1455753600000,
    "attribute": "宇宙",
    "title": "九年跋涉只为遇见你",
    "story": [
      {
        "title": "神秘冥王星",
        "au": "关于它的六个秘密",
        "describe": "2015年7月，经过了九年的艰苦跋涉，新视野号探测器终于飞越冥王星，得以看到它的庐山真面目，成为人类首颗造访冥王星的探测器。发回的照片，让无数期待已久的地球人感动不已。",
        "miniImage": "http://s1.cn.bing.net/th?id=OJ.IDSJ2XqTVb6Y0g&pid=MSNJVFeeds",
        "miniUrl": "https://zhanghao-zhoushan.cn/image/story/s1.OJ.IDSJ2XqTVb6Y0g.png"
      },
      {
        "title": "独一无二",
        "au": "轨道",
        "describe": "冥王星的轨道呈椭圆形，与太阳最近距离是44.3亿公里，最远为73.1亿公里。与地球环绕太阳的轨道平面之间倾角为17度，有着与其它八颗行星完全不同的轨道。",
        "miniImage": "http://s4.cn.bing.net/th?id=OJ.i5XyqiNYEXJ70Q&pid=MSNJVFeeds",
        "miniUrl": "https://zhanghao-zhoushan.cn/image/story/s4.OJ.i5XyqiNYEXJ70Q.png"
      },
      {
        "title": "空气稀薄",
        "au": "缺少空气",
        "describe": "上世纪八十年代，研究人员发现冥王星存在大气层。这里有充足的氮气，但氧气却很少。这里的空气中包含一氧化碳和甲烷，但比地球大气层稀薄许多。",
        "miniImage": "http://s.cn.bing.net/th?id=OJ.DVtdJMSgbRAy2g&pid=MSNJVFeeds",
        "miniUrl": "https://zhanghao-zhoushan.cn/image/story/s.OJ.DVtdJMSgbRAy2g.png"
      }
    ],
    "primaryImageUrl": "http://hpimges.blob.core.chinacloudapi.cn/coverstory/watermark_pluto_zh-cn12044921779_1920x1080.jpg",
    "imageUrl": "https://zhanghao-zhoushan.cn/image/large/AdelaideFrog_ZH-CN11037278287_1366x768.jpg",
    "downLoadUrl": "https://zhanghao-zhoushan.cn/image/large/AdelaideFrog_ZH-CN11037278287.jpg",
    "url": "http://cdn.nanxiongnandi.com/bing/AdelaideFrog_ZH-CN11037278287_1366x768.jpg",
    "name": "AdelaideFrog_ZH-CN11037278287.jpg",
    "provider": "© NASA/JHUAPL/SwRI",
    "copyright": "[今日雨水]澳大利亚，阿德莱德，一只青蛙紧抱着枝梢 (© Rob Sturman/Corbis)(Bing China)",
    "Continent": "",
    "Country": "",
    "City": "",
    "Longitude": "",
    "Latitude": ""
  },
  {
    "dateString": "20160219",
    "date": 1455840000000,
    "attribute": "澳大利亚，阿德莱德",
    "title": "紧抱着树梢的青蛙",
    "story": [
      {
        "title": "阿德莱德",
        "au": "阳光甚好的温柔之都",
        "describe": "雨水是一年中的第二个节气。此时，气温将会回升，冰雪融化，降水增多，春天即将来临，万物开始萌动。刚被雨水浸洗过的枝梢上，一只青蛙静静呆着，如同一只报春精灵，在告诉人们温暖的春天即将来到。",
        "miniImage": "http://s4.cn.bing.net/th?id=OJ.eWCPif2eD4fLZA&pid=MSNJVFeeds",
        "miniUrl": "https://zhanghao-zhoushan.cn/image/story/s4.OJ.eWCPif2eD4fLZA.png"
      },
      {
        "title": "袋鼠和考拉的天堂",
        "au": "格莱兰德野生动物园",
        "describe": "格莱兰德野生动物园是个开放式的野生动物园，里面生活着不少澳洲特有的野生动物。在这里，可以抱着考拉照相，向袋鼠喂食，与这些萌萌的动物们亲密接触。",
        "miniImage": "http://s3.cn.bing.net/th?id=OJ.kK8EOJaLV1AuzA&pid=MSNJVFeeds",
        "miniUrl": "https://zhanghao-zhoushan.cn/image/story/s3.OJ.kK8EOJaLV1AuzA.png"
      },
      {
        "title": "澳洲第二大艺术馆",
        "au": "南澳大利亚美术馆",
        "describe": "馆内珍藏了澳洲艺术界大师级人物与杰出代表的艺术作品，不失国际水准的收藏让每一位参观者留下了深刻的印象。艾尔德馆侧厅内陈列的殖民州时期的收藏和联邦时代的景观都非常值得参观。",
        "miniImage": "http://s2.cn.bing.net/th?id=OJ.FmGrtnFzKzJn7w&pid=MSNJVFeeds",
        "miniUrl": "https://zhanghao-zhoushan.cn/image/story/s2.OJ.FmGrtnFzKzJn7w.png"
      }
    ],
    "primaryImageUrl": "http://hpimges.blob.core.chinacloudapi.cn/coverstory/watermark_adelaidefrog_zh-cn11037278287_1920x1080.jpg",
    "imageUrl": "https://zhanghao-zhoushan.cn/image/large/WhiteNightMelb_ZH-CN9705829579_1366x768.jpg",
    "downLoadUrl": "https://zhanghao-zhoushan.cn/image/large/WhiteNightMelb_ZH-CN9705829579.jpg",
    "url": "http://cdn.nanxiongnandi.com/bing/WhiteNightMelb_ZH-CN9705829579_1366x768.jpg",
    "name": "WhiteNightMelb_ZH-CN9705829579.jpg",
    "provider": "© Rob Sturman/Corbis",
    "copyright": "澳大利亚，墨尔本，白夜节 (© John W Banagan/Getty Images)(Bing China)",
    "Continent": "",
    "Country": "",
    "City": "",
    "Longitude": "",
    "Latitude": ""
  },
  {
    "dateString": "20160220",
    "date": 1455926400000,
    "attribute": "澳大利亚，墨尔本",
    "title": "白夜节",
    "story": [
      {
        "title": "墨尔本的传统节日",
        "au": "那些狂欢的日子",
        "describe": "每年的2月20日前后，在墨尔本的繁华地段会举办惊艳的大型户外灯光展。岸边的摩天高楼均被璀璨灯光装点，闪亮一整夜，浪漫白夜让人迷醉。",
        "miniImage": "http://s3.cn.bing.net/th?id=OJ.Lcju7pKGa5zARQ&pid=MSNJVFeeds",
        "miniUrl": "https://zhanghao-zhoushan.cn/image/story/s3.OJ.Lcju7pKGa5zARQ.png"
      },
      {
        "title": "举国欢庆",
        "au": "国庆日",
        "describe": "1788年，英国人进入澳大利亚后开始了在这片土地上的殖民统治，并在1月26日这天宣布澳洲为英国领地。此后，1月26日就成了这里的建国纪念日。",
        "miniImage": "http://s1.cn.bing.net/th?id=OJ.2YSGbODJngDfsw&pid=MSNJVFeeds",
        "miniUrl": "https://zhanghao-zhoushan.cn/image/story/s1.OJ.2YSGbODJngDfsw.png"
      },
      {
        "title": "不忘历史",
        "au": "澳纽军团日",
        "describe": "一战时期，澳大利亚新西兰联合军被英国借去，在土耳其与敌方交战时失去生命。4月25日的澳纽军团日，就是为了纪念他们而设。",
        "miniImage": "http://s1.cn.bing.net/th?id=OJ.X0op4gcx4mKWkA&pid=MSNJVFeeds",
        "miniUrl": "https://zhanghao-zhoushan.cn/image/story/s1.OJ.X0op4gcx4mKWkA.png"
      }
    ],
    "primaryImageUrl": "http://hpimges.blob.core.chinacloudapi.cn/coverstory/watermark_whitenightmelb_zh-cn9705829579_1920x1080.jpg",
    "imageUrl": "https://zhanghao-zhoushan.cn/image/large/GlowWorms_ZH-CN10708592012_1366x768.jpg",
    "downLoadUrl": "https://zhanghao-zhoushan.cn/image/large/GlowWorms_ZH-CN10708592012.jpg",
    "url": "http://cdn.nanxiongnandi.com/bing/GlowWorms_ZH-CN10708592012_1366x768.jpg",
    "name": "GlowWorms_ZH-CN10708592012.jpg",
    "provider": "© John W Banagan/Getty Images",
    "copyright": "新西兰，怀托莫萤火虫洞 (© Fabian Ebi/500px)(Bing China)",
    "Continent": "",
    "Country": "澳大利亚",
    "City": "墨尔本",
    "Longitude": "144.977996826172",
    "Latitude": "-37.8242988586426"
  },
  {
    "dateString": "20160221",
    "date": 1456012800000,
    "attribute": "新西兰，怀卡托",
    "title": "如梦境般的地方",
    "story": [
      {
        "title": "新西兰",
        "au": "童话王国",
        "describe": "幽深的洞里，形态各异的钟乳石让人叹为观止。乘着小舟穿梭于幽暗之中，头顶的萤火虫如点点繁星般闪耀，让人有一种身在另一个世界的错觉。",
        "miniImage": "http://s2.cn.bing.net/th?id=OJ.dJzovhWLMaWT2w&pid=MSNJVFeeds",
        "miniUrl": "https://zhanghao-zhoushan.cn/image/story/s2.OJ.dJzovhWLMaWT2w.png"
      },
      {
        "title": "见证艰苦淘金岁月",
        "au": "箭镇",
        "describe": "百年前，包括大量华人在内的冒险者们来到这个地方，只为圆他们的淘金梦。镇上白金大街上的湖区博物馆中，仍能寻觅到当年淘金者们生活的足迹，华人定居遗址还原了当年中国劳工的生活状态，让人感受到当年他们生活的不易。",
        "miniImage": "http://s.cn.bing.net/th?id=OJ.wr5w0lUa2CKKhg&pid=MSNJVFeeds",
        "miniUrl": "https://zhanghao-zhoushan.cn/image/story/s.OJ.wr5w0lUa2CKKhg.png"
      },
      {
        "title": "死火山口",
        "au": "伊甸山",
        "describe": "伊甸山位于市中心以南，是一座死火山的火山口。这里海拔接近200米，站在山顶可将市区和附近的海面一览无遗。山顶还专为游人设置了瞭望台，是眺望城市景观的好地方。",
        "miniImage": "http://s3.cn.bing.net/th?id=OJ.RHDfcLLipEDDpQ&pid=MSNJVFeeds",
        "miniUrl": "https://zhanghao-zhoushan.cn/image/story/s3.OJ.RHDfcLLipEDDpQ.png"
      }
    ],
    "primaryImageUrl": "http://hpimges.blob.core.chinacloudapi.cn/coverstory/watermark_glowworms_zh-cn10708592012_1920x1080.jpg",
    "imageUrl": "https://zhanghao-zhoushan.cn/image/large/JinliStreetView_ZH-CN10751235981_1366x768.jpg",
    "downLoadUrl": "https://zhanghao-zhoushan.cn/image/large/JinliStreetView_ZH-CN10751235981.jpg",
    "url": "http://cdn.nanxiongnandi.com/bing/JinliStreetView_ZH-CN10751235981_1366x768.jpg",
    "name": "JinliStreetView_ZH-CN10751235981.jpg",
    "provider": "© Fabian Ebi/500px",
    "copyright": "中国，四川，成都，美丽的锦里古街 (© Kiszon Pascal/Moment/Getty Images)(Bing China)",
    "Continent": "",
    "Country": "新西兰",
    "City": "怀卡托",
    "Longitude": "175.4997253418",
    "Latitude": "-38.0015736037"
  },
  {
    "dateString": "20160222",
    "date": 1456099200000,
    "attribute": "中国，四川，成都",
    "title": "年味十足的锦里",
    "story": [
      {
        "title": "成都",
        "au": "将闲适生活演绎到极致",
        "describe": "石街已被岁月磨得光滑蹭亮，两旁的木屋无时无刻不诉说着源自清朝的故事。二楼的古旧窗檐上挂着大红灯笼，浓浓的节日气氛布满整个街巷。",
        "miniImage": "http://s2.cn.bing.net/th?id=OJ.8lJHMPJzTcfa0A&pid=MSNJVFeeds",
        "miniUrl": "https://zhanghao-zhoushan.cn/image/story/s2.OJ.8lJHMPJzTcfa0A.png"
      },
      {
        "title": "与国宝亲密接触",
        "au": "大熊猫研究基地",
        "describe": "对于很多人而言，来到成都必做的一件事就是看大熊猫。这里既是大熊猫繁育的研究机构，也是一个生态公园，面向游客开放。在这里，不仅可以近距离看到熊猫憨态可掬的样子，运气好的话还可以看到熊猫宝宝出生的场景。",
        "miniImage": "http://s1.cn.bing.net/th?id=OJ.70BqSYtuE0R12Q&pid=MSNJVFeeds",
        "miniUrl": "https://zhanghao-zhoushan.cn/image/story/s1.OJ.70BqSYtuE0R12Q.png"
      },
      {
        "title": "蜀汉英雄纪念地",
        "au": "武侯祠",
        "describe": "武侯祠是中国唯一一座君臣合祀的祠庙，也是诸葛亮、刘备以及各蜀汉英雄的纪念地。作为全世界影响最大的三国遗迹博物馆，这里处处都散发着历史的气息。若你是个三国迷，此处一定能让你过足瘾。",
        "miniImage": "http://s3.cn.bing.net/th?id=OJ.aT7Fx2yWbyY80g&pid=MSNJVFeeds",
        "miniUrl": "https://zhanghao-zhoushan.cn/image/story/s3.OJ.aT7Fx2yWbyY80g.png"
      }
    ],
    "primaryImageUrl": "http://hpimges.blob.core.chinacloudapi.cn/coverstory/watermark_jinlistreetview_zh-cn10751235981_1920x1080.jpg",
    "imageUrl": "https://zhanghao-zhoushan.cn/image/large/MountHuaSnow_ZH-CN10489400024_1366x768.jpg",
    "downLoadUrl": "https://zhanghao-zhoushan.cn/image/large/MountHuaSnow_ZH-CN10489400024.jpg",
    "url": "http://cdn.nanxiongnandi.com/bing/MountHuaSnow_ZH-CN10489400024_1366x768.jpg",
    "name": "MountHuaSnow_ZH-CN10489400024.jpg",
    "provider": "© Kiszon Pascal/Moment/Getty Images",
    "copyright": "中国，陕西省，华山 (© Tao Ming/REX Shutterstock)(Bing China)",
    "Continent": "",
    "Country": "中国",
    "City": "成都",
    "Longitude": "104.065734863281",
    "Latitude": "30.6594619750977"
  },
  {
    "dateString": "20160223",
    "date": 1456185600000,
    "attribute": "中国，陕西,华山",
    "title": "雪中华山",
    "story": [
      {
        "title": "险峰之美",
        "au": "风光无限",
        "describe": "华山被认为是五岳当中最险峻的一座。怪石嶙峋，奇峰林立，每一条步道都让人屏住呼吸，每一座峰顶都有迷人美景。入冬后，雪中的华山更是让人迷醉，恍若置身仙境。",
        "miniImage": "http://s.cn.bing.net/th?id=OJ.GNQfnulwbYf2Ow&pid=MSNJVFeeds",
        "miniUrl": "https://zhanghao-zhoushan.cn/image/story/s.OJ.GNQfnulwbYf2Ow.png"
      },
      {
        "title": "绝壁三尺 三面临空",
        "au": "苍龙岭",
        "describe": "苍龙岭呈苍黑色，气势如同游龙一般，于是便有了这个名字。山岭西边是深涧，东边则为飞鱼岭峡谷。整个山岭长约百米，宽不足三尺，游人在上面行走，如同走在云端一般。",
        "miniImage": "http://s.cn.bing.net/th?id=OJ.9Mqc2z69VWYg7A&pid=MSNJVFeeds",
        "miniUrl": "https://zhanghao-zhoushan.cn/image/story/s.OJ.9Mqc2z69VWYg7A.png"
      },
      {
        "title": "华山五关之一",
        "au": "金锁关",
        "describe": "金锁关是华山五关之一，是通往东、西、南和中峰的必经之路。来到这里的人们必做事之一就是求金锁，并把它绑在山路的两侧，以保平安。",
        "miniImage": "http://s2.cn.bing.net/th?id=OJ.cgQzVdlFKQRpzw&pid=MSNJVFeeds",
        "miniUrl": "https://zhanghao-zhoushan.cn/image/story/s2.OJ.cgQzVdlFKQRpzw.png"
      }
    ],
    "primaryImageUrl": "http://hpimges.blob.core.chinacloudapi.cn/coverstory/watermark_mounthuasnow_zh-cn10489400024_1920x1080.jpg",
    "imageUrl": "https://zhanghao-zhoushan.cn/image/large/Snowboard_ZH-CN12050607515_1366x768.jpg",
    "downLoadUrl": "https://zhanghao-zhoushan.cn/image/large/Snowboard_ZH-CN12050607515.jpg",
    "url": "http://cdn.nanxiongnandi.com/bing/Snowboard_ZH-CN12050607515_1366x768.jpg",
    "name": "Snowboard_ZH-CN12050607515.jpg",
    "provider": "© Tao Ming/REX Shutterstock",
    "copyright": "高山滑雪，滑雪板在转弯时溅起粉末 (© Jeff Curtes/Aurora Photos)(Bing China)",
    "Continent": "",
    "Country": "中国",
    "City": "华山",
    "Longitude": "110.1053324",
    "Latitude": "34.5555485"
  },
  {
    "dateString": "20160224",
    "date": 1456272000000,
    "attribute": "中国",
    "title": "热血沸腾的冬季",
    "story": [
      {
        "title": "国内热门滑雪场",
        "au": "在冰天雪地中驰骋",
        "describe": "身着滑雪服，手持雪杖，脚踏滑雪板，一切就绪后，向着白茫茫的一片驰骋而下。雪花飞溅，耳旁寒风呼啸，但急速的下降让整个人热血沸腾。",
        "miniImage": "http://s.cn.bing.net/th?id=OJ.0s8YLT2CtANIvg&pid=MSNJVFeeds",
        "miniUrl": "https://zhanghao-zhoushan.cn/image/story/s.OJ.0s8YLT2CtANIvg.png"
      },
      {
        "title": "冰雪世界",
        "au": "月亮湾",
        "describe": "东临太阳岛的雪雕园，北靠东北虎林园，是赏冰灯，看冬泳、看雪雕、滑雪的好地方。每到冬季，这里便游人如织，是一个颇受欢迎的冰雪王国。",
        "miniImage": "http://s1.cn.bing.net/th?id=OJ.tWxeJzaHhYmLZg&pid=MSNJVFeeds",
        "miniUrl": "https://zhanghao-zhoushan.cn/image/story/s1.OJ.tWxeJzaHhYmLZg.png"
      },
      {
        "title": "城市中的滑雪场",
        "au": "净月潭",
        "describe": "净月潭位于长春市东南侧，是个城市中的滑雪场。这里湖光山色、空气清新，是逃脱城市喧闹的好去处。入冬后，在这里滑雪、看雪松，寻味真正的北国风光。",
        "miniImage": "http://s4.cn.bing.net/th?id=OJ.M6LxqdF00evCRQ&pid=MSNJVFeeds",
        "miniUrl": "https://zhanghao-zhoushan.cn/image/story/s4.OJ.M6LxqdF00evCRQ.png"
      }
    ],
    "primaryImageUrl": "http://hpimges.blob.core.chinacloudapi.cn/coverstory/watermark_snowboard_zh-cn12050607515_1920x1080.jpg",
    "imageUrl": "https://zhanghao-zhoushan.cn/image/large/IcelandAurora_ZH-CN6140649446_1366x768.jpg",
    "downLoadUrl": "https://zhanghao-zhoushan.cn/image/large/IcelandAurora_ZH-CN6140649446.jpg",
    "url": "http://cdn.nanxiongnandi.com/bing/IcelandAurora_ZH-CN6140649446_1366x768.jpg",
    "name": "IcelandAurora_ZH-CN6140649446.jpg",
    "provider": "© Jeff Curtes/Aurora Photos",
    "copyright": "冰岛海岸上空的极光 (© Babak Tafreshi/Nimia)(Bing China)",
    "Continent": "",
    "Country": "",
    "City": "",
    "Longitude": "",
    "Latitude": ""
  },
  {
    "dateString": "20160225",
    "date": 1456358400000,
    "attribute": "冰岛",
    "title": "冰岛海岸的极光",
    "story": [
      {
        "title": "看极光的最佳地点",
        "au": "冰天雪地中的唯美光束",
        "describe": "冬天的冰岛海岸，美得不食人间烟火。大海浩瀚无比，海岸线蜿蜒悠长，入夜后，漆黑的夜空中出现灿烂极光，让人分不清是现实还是梦境。",
        "miniImage": "http://s4.cn.bing.net/th?id=OJ.p5sefbqP7jobIA&pid=MSNJVFeeds",
        "miniUrl": "https://zhanghao-zhoushan.cn/image/story/s4.OJ.p5sefbqP7jobIA.png"
      },
      {
        "title": "秋冬季最佳",
        "au": "理想观赏时间",
        "describe": "每年的9月至来年3月是极光出现的高频时段，其中10月至11月和2月至3月是最佳时期，一般在晚上9点至凌晨3点是黄金时段。",
        "miniImage": "http://s3.cn.bing.net/th?id=OJ.rlaotYNUw6veUw&pid=MSNJVFeeds",
        "miniUrl": "https://zhanghao-zhoushan.cn/image/story/s3.OJ.rlaotYNUw6veUw.png"
      },
      {
        "title": "避开满月",
        "au": "赏极光的技巧",
        "describe": "好天气是看极光的重要条件，同时最好避开满月和光污染。天空越黑，看到极光的几率就越大。",
        "miniImage": "http://s1.cn.bing.net/th?id=OJ.KJgHO2Ssv8mXcA&pid=MSNJVFeeds",
        "miniUrl": "https://zhanghao-zhoushan.cn/image/story/s1.OJ.KJgHO2Ssv8mXcA.png"
      }
    ],
    "primaryImageUrl": "http://hpimges.blob.core.chinacloudapi.cn/coverstory/watermark_icelandaurora_zh-cn6140649446_1920x1080.jpg",
    "imageUrl": "https://zhanghao-zhoushan.cn/image/large/LaPedrera_ZH-CN9374830496_1366x768.jpg",
    "downLoadUrl": "https://zhanghao-zhoushan.cn/image/large/LaPedrera_ZH-CN9374830496.jpg",
    "url": "http://cdn.nanxiongnandi.com/bing/LaPedrera_ZH-CN9374830496_1366x768.jpg",
    "name": "LaPedrera_ZH-CN9374830496.jpg",
    "provider": "© Babak Tafreshi/Nimia",
    "copyright": "西班牙，巴塞罗那，米拉之家 (© Nora De Angelli/500px)(Bing China)",
    "Continent": "",
    "Country": "冰岛",
    "City": "",
    "Longitude": "-23.5034121",
    "Latitude": "64.8685266"
  },
  {
    "dateString": "20160226",
    "date": 1456444800000,
    "attribute": "西班牙，巴塞罗那",
    "title": "独具魅力的米拉之家",
    "story": [
      {
        "title": "高迪名作",
        "au": "巴塞罗那的知名建筑",
        "describe": "在巴塞罗那的格拉西亚大道上，一座充满抛物线和悬链线的建筑异常显眼，它就是米拉之家。这座建筑是高迪生前设计的最后一幢私人住宅，几乎无直角的设计让它独具魅力。",
        "miniImage": "http://s4.cn.bing.net/th?id=OJ.0rVFHH8voV5LQw&pid=MSNJVFeeds",
        "miniUrl": "https://zhanghao-zhoushan.cn/image/story/s4.OJ.0rVFHH8voV5LQw.png"
      },
      {
        "title": "现代主义工艺精品",
        "au": "巴特罗之家",
        "describe": "巴特里奥公寓里，每一处细节都透露着原汁原味的现代主义风格。位于一楼的主厅是整幢房子最精华的部分，占地730平米，有内部楼梯通往各间卧室，还可通向一个面积为230平米的庭院。这里不仅是节日晚宴的理想场地，也是举办私人派对的绝佳场所。",
        "miniImage": "http://s2.cn.bing.net/th?id=OJ.zYqsgep6lAEnWw&pid=MSNJVFeeds",
        "miniUrl": "https://zhanghao-zhoushan.cn/image/story/s2.OJ.zYqsgep6lAEnWw.png"
      },
      {
        "title": "未完工的赎罪教堂",
        "au": "圣家族大教堂",
        "describe": "教堂原名为神圣家族赎罪教堂，始建于1882年，至今仍未完工，是世界上唯一尚未完工就被列为世界遗产的建筑。教堂的资金来源于捐款，因此会影响到工程进度。高迪自从接手这座教堂，倾注了43年的心血在其中，甚至还搬到教堂的工地去住，直至1926年遭遇车祸去世为止。",
        "miniImage": "http://s3.cn.bing.net/th?id=OJ.S0QDDw2C6GNueA&pid=MSNJVFeeds",
        "miniUrl": "https://zhanghao-zhoushan.cn/image/story/s3.OJ.S0QDDw2C6GNueA.png"
      }
    ],
    "primaryImageUrl": "http://hpimges.blob.core.chinacloudapi.cn/coverstory/watermark_lapedrera_zh-cn9374830496_1920x1080.jpg",
    "imageUrl": "https://zhanghao-zhoushan.cn/image/large/CubsPlaying_ZH-CN10631979300_1366x768.jpg",
    "downLoadUrl": "https://zhanghao-zhoushan.cn/image/large/CubsPlaying_ZH-CN10631979300.jpg",
    "url": "http://cdn.nanxiongnandi.com/bing/CubsPlaying_ZH-CN10631979300_1366x768.jpg",
    "name": "CubsPlaying_ZH-CN10631979300.jpg",
    "provider": "© Nora De Angelli/500px",
    "copyright": "加拿大，哈德逊湾，小北极熊在玩耍 (© Meril D & Manon M/Minden Pictures)(Bing China)",
    "Continent": "",
    "Country": "西班牙",
    "City": "巴塞罗那",
    "Longitude": "2.0787283",
    "Latitude": "41.3948976"
  },
  {
    "dateString": "20160227",
    "date": 1456531200000,
    "attribute": "加拿大，哈德逊湾",
    "title": "哈德逊湾的小北极熊",
    "story": [
      {
        "title": "冰雪国王",
        "au": "体型笨重 却有王者风范",
        "describe": "冬日的哈德逊湾多雾、多冰，可爱的小北极熊在冰面上憨态踱步，柔软的白色毛发与周遭景色融为一体。它们时而嬉戏打闹，时而卧倒酣睡，为死寂的严冬增添了迷人生气。",
        "miniImage": "http://s1.cn.bing.net/th?id=OJ.p0FDTPgi02cY3Q&pid=MSNJVFeeds",
        "miniUrl": "https://zhanghao-zhoushan.cn/image/story/s1.OJ.p0FDTPgi02cY3Q.png"
      },
      {
        "title": "掠食者",
        "au": "哈德逊湾狼",
        "describe": "哈德逊湾狼，生活在加拿大哈德逊湾的掠食者。它们体型中等，冬季毛色是几乎纯白的。狭窄的胸部，强健有力的背部与腿，使它们具备很有效率的机动能力，能以约10公里的时速走十几公里，追逐猎物时速度能提高到接近每小时65公里，冲刺时每一步的距离可以长达5米。",
        "miniImage": "http://s1.cn.bing.net/th?id=OJ.BoiU6RLVNhsKlA&pid=MSNJVFeeds",
        "miniUrl": "https://zhanghao-zhoushan.cn/image/story/s1.OJ.BoiU6RLVNhsKlA.png"
      },
      {
        "title": "草食性动物",
        "au": "哈得逊湾驯鹿",
        "describe": "哈得逊湾驯鹿，无论雌鹿还是雄鹿都拥有着分枝繁复的长角，鹿角扁平，有点像麋鹿的角。它们腿细长，善奔跑，善游泳，典型的运动健将的架势。雄鹿一般大于雌鹿。毛色冬深夏浅，幼鹿有白色斑点。尾巴极短。栖息于高地苔原、成熟针叶林区、荒漠、灌丛和沼泽。是典型的草食性动物，以各种植物为食，吃草、树皮、嫩枝和幼树苗。",
        "miniImage": "http://s3.cn.bing.net/th?id=OJ.gEY7Z0UtSnlDtw&pid=MSNJVFeeds",
        "miniUrl": "https://zhanghao-zhoushan.cn/image/story/s3.OJ.gEY7Z0UtSnlDtw.png"
      }
    ],
    "primaryImageUrl": "http://hpimges.blob.core.chinacloudapi.cn/coverstory/watermark_cubsplaying_zh-cn10631979300_1920x1080.jpg",
    "imageUrl": "https://zhanghao-zhoushan.cn/image/large/ThingvellirCrater_ZH-CN10532060195_1366x768.jpg",
    "downLoadUrl": "https://zhanghao-zhoushan.cn/image/large/ThingvellirCrater_ZH-CN10532060195.jpg",
    "url": "http://cdn.nanxiongnandi.com/bing/ThingvellirCrater_ZH-CN10532060195_1366x768.jpg",
    "name": "ThingvellirCrater_ZH-CN10532060195.jpg",
    "provider": "© Meril D & Manon M/Minden Pictures",
    "copyright": "冰岛，辛格韦德利国家公园的火山口 (© Ragnar Th Sigurdsson/Alamy)(Bing China)",
    "Continent": "",
    "Country": "",
    "City": "",
    "Longitude": "",
    "Latitude": ""
  },
  {
    "dateString": "20160228",
    "date": 1456617600000,
    "attribute": "冰岛，辛格韦德利",
    "title": "辛格韦德利国家公园",
    "story": [
      {
        "title": "冰岛",
        "au": "火山之国",
        "describe": "北美板块和亚欧板块分裂时，地壳运动促使湖泊、河流、山川等自然美景的形成。古老的火山口至今仍在活跃着，安静的火山口内部，熔岩不停运动着，酝酿着。",
        "miniImage": "http://s1.cn.bing.net/th?id=OJ.ORVT0IE5dIx0cw&pid=MSNJVFeeds",
        "miniUrl": "https://zhanghao-zhoushan.cn/image/story/s1.OJ.ORVT0IE5dIx0cw.png"
      },
      {
        "title": "“黄金圈”的招牌景点",
        "au": "居德瀑布",
        "describe": "居德瀑布位于雷克雅未克以北的赫维陶河上，宽2500米，高70米，是冰岛最大的断层瀑布。在阳光照射下，喷溅的水珠折射出梦幻的彩虹，散发着金色光彩，因此又被称作“黄金瀑布”。",
        "miniImage": "http://s1.cn.bing.net/th?id=OJ.rhra9wnvY3B0sg&pid=MSNJVFeeds",
        "miniUrl": "https://zhanghao-zhoushan.cn/image/story/s1.OJ.rhra9wnvY3B0sg.png"
      },
      {
        "title": "冰岛最大间歇泉",
        "au": "大间歇泉",
        "describe": "位于豪卡道鲁山谷，是冰岛最大的间歇泉。它是一个直径约18米的圆池，池中央的泉眼内水温高达一百多度，每次喷发时，沸水随之升涌，最后冲出洞口，向高空喷射出约为二、三十米高的水柱，非常壮观。",
        "miniImage": "http://s3.cn.bing.net/th?id=OJ.KNR1ee4XHxI3kQ&pid=MSNJVFeeds",
        "miniUrl": "https://zhanghao-zhoushan.cn/image/story/s3.OJ.KNR1ee4XHxI3kQ.png"
      }
    ],
    "primaryImageUrl": "http://hpimges.blob.core.chinacloudapi.cn/coverstory/watermark_thingvellircrater_zh-cn10532060195_1920x1080.jpg",
    "imageUrl": "https://zhanghao-zhoushan.cn/image/large/HenkelGecko_ZH-CN11306915158_1366x768.jpg",
    "downLoadUrl": "https://zhanghao-zhoushan.cn/image/large/HenkelGecko_ZH-CN11306915158.jpg",
    "url": "http://cdn.nanxiongnandi.com/bing/HenkelGecko_ZH-CN11306915158_1366x768.jpg",
    "name": "HenkelGecko_ZH-CN11306915158.jpg",
    "provider": "© Ragnar Th Sigurdsson/Alamy",
    "copyright": "一只跳跃中的Henkel叶尾壁虎 (© Stephen Dalton/Minden Pictures)(Bing China)",
    "Continent": "",
    "Country": "冰岛",
    "City": "辛格韦德利",
    "Longitude": "-27.4639429",
    "Latitude": "64.0849779"
  },
  {
    "dateString": "20160229",
    "date": 1456704000000,
    "attribute": "Henkel叶尾壁虎",
    "title": "跳跃中的小家伙",
    "story": [
      {
        "title": "完美的伪装者",
        "au": "长相奇特的动物们",
        "describe": "枯败的树枝上耷拉着金黄的枯叶，若是看到其中一片正在跳动，不要以为是风在作祟，那是聪明的伪装者——叶尾壁虎——正在活动筋骨。它们外形与枯叶没什么两样，完美地伪装技能让它们巧妙躲过来自天敌的杀身之祸。",
        "miniImage": "http://s2.cn.bing.net/th?id=OJ.7it7OcaYG0R7JA&pid=MSNJVFeeds",
        "miniUrl": "https://zhanghao-zhoushan.cn/image/story/s2.OJ.7it7OcaYG0R7JA.png"
      },
      {
        "title": "高明的掠食者",
        "au": "兰花螳螂",
        "describe": "兰花螳螂产于东南亚的热带雨林区，常常附着在兰花上，身体可随着花色变化来调节，有最完美的伪装。它们刚出生时身体呈现红黑色，第一次蜕皮后才转变成白色和粉红相间的兰花色。",
        "miniImage": "http://s3.cn.bing.net/th?id=OJ.X7TIJmWzKU257g&pid=MSNJVFeeds",
        "miniUrl": "https://zhanghao-zhoushan.cn/image/story/s3.OJ.X7TIJmWzKU257g.png"
      },
      {
        "title": "又名枯叶鱼",
        "au": "叶形鱼",
        "describe": "叶形鱼一般生活在25－28度的水里，当它们一动不动躺在水底时，几乎与树叶没什么区别。这种鱼以捕食更小的鱼和昆虫为生，它们会躺在水底很长时间，不动声色，直到有猎物靠近时会突然袭击，通常十拿九稳。",
        "miniImage": "http://s4.cn.bing.net/th?id=OJ.2XpnqIJLVS0wzQ&pid=MSNJVFeeds",
        "miniUrl": "https://zhanghao-zhoushan.cn/image/story/s4.OJ.2XpnqIJLVS0wzQ.png"
      }
    ],
    "primaryImageUrl": "http://hpimges.blob.core.chinacloudapi.cn/coverstory/watermark_henkelgecko_zh-cn11306915158_1920x1080.jpg",
    "imageUrl": "",
    "downLoadUrl": "",
    "provider": "© Stephen Dalton/Minden Pictures",
    "Continent": "",
    "Country": "",
    "City": "",
    "Longitude": "",
    "Latitude": ""
  }
]