[
  {
    "enddate": "20100131",
    "url": "http://cdn.nanxiongnandi.com/bing/GangwonSnow_ZH-CN3119374952.jpg",
    "copyright": "韩国东部江原道被积雪覆盖的山庙 -- YONHAP/Corbis © (Bing China)"
  },
  {
    "enddate": "20100130",
    "url": "http://cdn.nanxiongnandi.com/bing/Cuttlefish_ZH-CN396217963.jpg",
    "copyright": "印度尼西亚海域中一只因求偶而变色的雄性乌贼 -- White/Photolibrary © (Bing China)"
  },
  {
    "enddate": "20100129",
    "url": "http://cdn.nanxiongnandi.com/bing/LibraryofCongress_ZH-CN1392643047.jpg",
    "copyright": "华盛顿区的美国国会图书馆 -- Michele Falzone/age fotostock/Photolibrary © (Bing China)"
  },
  {
    "enddate": "20100128",
    "url": "http://cdn.nanxiongnandi.com/bing/MountainLion_ZH-CN320894998.jpg",
    "copyright": "蒙大拿州从树上一跃而下的美洲狮 -- Daniel J. Cox/Corbis © (Bing China)"
  },
  {
    "enddate": "20100127",
    "url": "http://cdn.nanxiongnandi.com/bing/MtHood_ZH-CN650574640.jpg",
    "copyright": "冬季里的滑雪爱好者 -- Brian Stevenson/Corbis © (Bing China)"
  },
  {
    "enddate": "20100126",
    "url": "http://cdn.nanxiongnandi.com/bing/Spoonbill_ZH-CN3126535782.jpg",
    "copyright": "正在空中飞翔的玫瑰色琵鹭-- Jack Milchanowski/Photolibrary © (Bing China)"
  },
  {
    "enddate": "20100125",
    "url": "http://cdn.nanxiongnandi.com/bing/Palmyra_ZH-CN3288571808.jpg",
    "copyright": "叙利亚中南部的巴尔米拉古城 -- Panoramic Images/Getty Images © (Bing China)"
  },
  {
    "enddate": "20100124",
    "url": "http://cdn.nanxiongnandi.com/bing/Marais_ZH-CN3893087721.jpg",
    "copyright": "夜色中的法国巴黎街巷 -- Peet Simard/Corbis © (Bing China)"
  },
  {
    "enddate": "20100123",
    "url": "http://cdn.nanxiongnandi.com/bing/PirateDay_ZH-CN654822860.jpg",
    "copyright": "西班牙的维京海盗节 -- Bjorn Svensson/age fotostock © (Bing China)"
  },
  {
    "enddate": "20100122",
    "url": "http://cdn.nanxiongnandi.com/bing/Huyanglin_ZH-CN1010611032.jpg",
    "copyright": "携程&MSN十年旅行摄影大赛作品精选：内蒙古额济纳旗的胡杨林 -- 门小燕/北京 © (Bing China)"
  },
  {
    "enddate": "20100121",
    "url": "http://cdn.nanxiongnandi.com/bing/Takelamagan_ZH-CN1555042610.jpg",
    "copyright": "携程&MSN十年旅行摄影大赛作品精选：新疆塔克拉玛干沙漠 -- 潘若巍/上海 © (Bing China)"
  },
  {
    "enddate": "20100120",
    "url": "http://cdn.nanxiongnandi.com/bing/Hulunbeier_ZH-CN1354136929.jpg",
    "copyright": "携程&MSN十年旅行摄影大赛作品精选：内蒙古呼伦贝尔草原 -- 李长山/北京 © (Bing China)"
  },
  {
    "enddate": "20100119",
    "url": "http://cdn.nanxiongnandi.com/bing/Lijiang_ZH-CN3269220934.jpg",
    "copyright": "携程&MSN十年旅行摄影大赛作品精选：云南丽江的乡村太安 -- 李廷刚/四川成都 © (Bing China)"
  },
  {
    "enddate": "20100118",
    "url": "http://cdn.nanxiongnandi.com/bing/Baihaba_ZH-CN3100002733.jpg",
    "copyright": "携程&MSN十年旅行摄影大赛作品精选：新疆白哈巴村的清晨 -- 张可/江苏常州 © (Bing China)"
  },
  {
    "enddate": "20100117",
    "url": "http://cdn.nanxiongnandi.com/bing/OperaHouse_ZH-CN276379589.jpg",
    "copyright": "无处不浪漫：时尚浪漫的澳大利亚悉尼海湾 -- Walter Bibikow/Getty Images © (Bing China)"
  },
  {
    "enddate": "20100116",
    "url": "http://cdn.nanxiongnandi.com/bing/Lebanon_ZH-CN1963773181.jpg",
    "copyright": "无处不浪漫：浪漫的黎巴嫩贝鲁特 -- Paul Thuysbaert/Photolibrary © (Bing China)"
  },
  {
    "enddate": "20100115",
    "url": "http://cdn.nanxiongnandi.com/bing/Luxembourg_ZH-CN1550929008.jpg",
    "copyright": "无处不浪漫：皇室的浪漫情怀飘荡在卢森堡上空 -- John B. MuellerGetty Images © (Bing China)"
  },
  {
    "enddate": "20100114",
    "url": "http://cdn.nanxiongnandi.com/bing/Lupines_ZH-CN422796503.jpg",
    "copyright": "无处不浪漫：神秘的新西兰峡湾国家公园 – Tony Ernst © (Bing China)"
  },
  {
    "enddate": "20100113",
    "url": "http://cdn.nanxiongnandi.com/bing/MiskitoCays_ZH-CN2943787599.jpg",
    "copyright": "无处不浪漫：炽热的尼加拉瓜海岸 -- Jay Dickman/CORBIS © (Bing China)"
  },
  {
    "enddate": "20100112",
    "url": "http://cdn.nanxiongnandi.com/bing/StockholmStreet_ZH-CN1479708815.jpg",
    "copyright": "无处不浪漫：如邻家女孩般亲切的瑞典老城 -- Jaynes Gallery © (Bing China)"
  },
  {
    "enddate": "20100111",
    "url": "http://cdn.nanxiongnandi.com/bing/Palouse_ZH-CN609752408.jpg",
    "copyright": "无处不浪漫：云淡风轻的华盛顿州立公园 -- Michael Sedam/Photolibrary © (Bing China)"
  },
  {
    "enddate": "20100110",
    "url": "http://cdn.nanxiongnandi.com/bing/TajMahal_ZH-CN1750602671.jpg",
    "copyright": "无处不浪漫：印度泰姬陵因爱情而永恒浪漫 -- Bob Krist/Corbis © (Bing China)"
  },
  {
    "enddate": "2010019",
    "url": "http://cdn.nanxiongnandi.com/bing/Dalian_ZH-CN442590110.jpg",
    "copyright": "东北冰雪之旅：大连市中山广场灯火通明 --  Jerry Driendl/Stone +/Getty Images © (Bing China)"
  },
  {
    "enddate": "20100108",
    "url": "http://cdn.nanxiongnandi.com/bing/FarmCorn_ZH-CN3069644158.jpg",
    "copyright": "东北冰雪之旅：冬阳下的东北农家院 -- TAO Images Limited/Tao Images/Photolibrary © (Bing China)"
  },
  {
    "enddate": "20100107",
    "url": "http://cdn.nanxiongnandi.com/bing/Tianchi_ZH-CN1664950212.jpg",
    "copyright": "东北冰雪之旅：东北最高峰吉林长白山 -- China Tourism Press/Riser © (Bing China)"
  },
  {
    "enddate": "20100106",
    "url": "http://cdn.nanxiongnandi.com/bing/FrozenBranches_ZH-CN373687758.jpg",
    "copyright": "东北冰雪之旅：银装素裹的吉林雾凇 -- View Stock RF/age fotostock © (Bing China)"
  },
  {
    "enddate": "20100105",
    "url": "http://cdn.nanxiongnandi.com/bing/HarbinChurch_ZH-CN1520169469.jpg",
    "copyright": "东北冰雪之旅：哈尔滨夜色中的圣索菲亚大教堂 -- Best View Stock/Photolibrary © (Bing China)"
  },
  {
    "enddate": "20100104",
    "url": "http://cdn.nanxiongnandi.com/bing/Harbin_ZH-CN1108609339.jpg",
    "copyright": "东北冰雪之旅：一年一度的哈尔滨冰雪节今天盛大开幕 -- Christian Kober/Photolibrary © (Bing China)"
  },
  {
    "enddate": "20100103",
    "url": "http://cdn.nanxiongnandi.com/bing/Weasel_ZH-CN694077802.jpg",
    "copyright": "科罗拉多州落基山国家公园中的长尾黄鼬 -- Joe McDonald/CORBIS © (Bing China)"
  },
  {
    "enddate": "20100102",
    "url": "http://cdn.nanxiongnandi.com/bing/ANewChapter_ZH-CN1549600135.jpg",
    "copyright": "从“新”开始：祝福中的新人踏上新的人生旅程 -- Paul D Van Hoy II/age fotostock/Photolibrary © (Bing China)"
  },
  {
    "enddate": "20100101",
    "url": "http://cdn.nanxiongnandi.com/bing/ANewLife_ZH-CN881578549.jpg",
    "copyright": "从“新”开始：新生的企鹅宝宝寄托新的希望 -- Thorsten Milse/Robert Harding Travel/Photolibrary © (Bing China)"
  }
]
